Workbook

Sheet Übersicht
A1: WoW Forever · Lederverarbeitung und Verzauberkunst 1-300 · Rechnung
A2: Stand 12.10.2026 · Mengen: Wowhead-Guides (Classic Era) · Preise: AHledger, Scans aus der Forever-Beta (Horde US, Stufenlimit 30)
A4: Markt | B4: NH | C4: NH = Normal Horde US, PH = PvP Horde US
A5: Preisbasis | B5: jetzt | C5: jetzt = aktueller Median, 30d = Median der letzten 30 Tage
A6: Schwelle dünner Markt | B6: 50 | C6: Preise mit weniger gelisteten Stück gelten als «dünn» (meine Wahl, frei änderbar)
A8: Band (Fertigkeit) | B8: LW Kosten (Gold) | C8: LW in g/s/c | D8: LW Posten ohne Preis | E8: LW Posten dünner Markt | F8: VZ Kosten (Gold) | G8: VZ in g/s/c | H8: VZ Posten ohne Preis | I8: VZ Posten dünner Markt | J8: LW + VZ (Gold)
A9: 1-100 | B9: =SUMIFS(Bedarf!$H$3:$H$85,Bedarf!$A$3:$A$85,"LW",Bedarf!$B$3:$B$85,$A9)/100 -> 1.424 | C9: =IF(B9="","",INT(ROUND(B9*10000,0)/10000)&"g "&INT(MOD(ROUND(B9*10000,0),10000)/100)&"s "&MOD(ROUND(B9*10000,0),100)&"c") -> 1g 42s 40c | D9: =SUMIFS(Bedarf!$I$3:$I$85,Bedarf!$A$3:$A$85,"LW",Bedarf!$B$3:$B$85,$A9) -> 0 | E9: =SUMIFS(Bedarf!$J$3:$J$85,Bedarf!$A$3:$A$85,"LW",Bedarf!$B$3:$B$85,$A9) -> 0 | F9: =SUMIFS(Bedarf!$H$3:$H$85,Bedarf!$A$3:$A$85,"VZ",Bedarf!$B$3:$B$85,$A9)/100 -> 1.1745 | G9: =IF(F9="","",INT(ROUND(F9*10000,0)/10000)&"g "&INT(MOD(ROUND(F9*10000,0),10000)/100)&"s "&MOD(ROUND(F9*10000,0),100)&"c") -> 1g 17s 45c | H9: =SUMIFS(Bedarf!$I$3:$I$85,Bedarf!$A$3:$A$85,"VZ",Bedarf!$B$3:$B$85,$A9) -> 1 | I9: =SUMIFS(Bedarf!$J$3:$J$85,Bedarf!$A$3:$A$85,"VZ",Bedarf!$B$3:$B$85,$A9) -> 0 | J9: =B9+F9 -> 2.5985
A10: 100-150 | B10: =SUMIFS(Bedarf!$H$3:$H$85,Bedarf!$A$3:$A$85,"LW",Bedarf!$B$3:$B$85,$A10)/100 -> 5.1228 | C10: =IF(B10="","",INT(ROUND(B10*10000,0)/10000)&"g "&INT(MOD(ROUND(B10*10000,0),10000)/100)&"s "&MOD(ROUND(B10*10000,0),100)&"c") -> 5g 12s 28c | D10: =SUMIFS(Bedarf!$I$3:$I$85,Bedarf!$A$3:$A$85,"LW",Bedarf!$B$3:$B$85,$A10) -> 0 | E10: =SUMIFS(Bedarf!$J$3:$J$85,Bedarf!$A$3:$A$85,"LW",Bedarf!$B$3:$B$85,$A10) -> 0 | F10: =SUMIFS(Bedarf!$H$3:$H$85,Bedarf!$A$3:$A$85,"VZ",Bedarf!$B$3:$B$85,$A10)/100 -> 4.964 | G10: =IF(F10="","",INT(ROUND(F10*10000,0)/10000)&"g "&INT(MOD(ROUND(F10*10000,0),10000)/100)&"s "&MOD(ROUND(F10*10000,0),100)&"c") -> 4g 96s 40c | H10: =SUMIFS(Bedarf!$I$3:$I$85,Bedarf!$A$3:$A$85,"VZ",Bedarf!$B$3:$B$85,$A10) -> 0 | I10: =SUMIFS(Bedarf!$J$3:$J$85,Bedarf!$A$3:$A$85,"VZ",Bedarf!$B$3:$B$85,$A10) -> 0 | J10: =B10+F10 -> 10.0868
A11: 150-200 | B11: =SUMIFS(Bedarf!$H$3:$H$85,Bedarf!$A$3:$A$85,"LW",Bedarf!$B$3:$B$85,$A11)/100 -> 36.3315 | C11: =IF(B11="","",INT(ROUND(B11*10000,0)/10000)&"g "&INT(MOD(ROUND(B11*10000,0),10000)/100)&"s "&MOD(ROUND(B11*10000,0),100)&"c") -> 36g 33s 15c | D11: =SUMIFS(Bedarf!$I$3:$I$85,Bedarf!$A$3:$A$85,"LW",Bedarf!$B$3:$B$85,$A11) -> 0 | E11: =SUMIFS(Bedarf!$J$3:$J$85,Bedarf!$A$3:$A$85,"LW",Bedarf!$B$3:$B$85,$A11) -> 0 | F11: =SUMIFS(Bedarf!$H$3:$H$85,Bedarf!$A$3:$A$85,"VZ",Bedarf!$B$3:$B$85,$A11)/100 -> 12.5645 | G11: =IF(F11="","",INT(ROUND(F11*10000,0)/10000)&"g "&INT(MOD(ROUND(F11*10000,0),10000)/100)&"s "&MOD(ROUND(F11*10000,0),100)&"c") -> 12g 56s 45c | H11: =SUMIFS(Bedarf!$I$3:$I$85,Bedarf!$A$3:$A$85,"VZ",Bedarf!$B$3:$B$85,$A11) -> 0 | I11: =SUMIFS(Bedarf!$J$3:$J$85,Bedarf!$A$3:$A$85,"VZ",Bedarf!$B$3:$B$85,$A11) -> 2 | J11: =B11+F11 -> 48.896
A12: 200-250 | B12: =SUMIFS(Bedarf!$H$3:$H$85,Bedarf!$A$3:$A$85,"LW",Bedarf!$B$3:$B$85,$A12)/100 -> 161.7865 | C12: =IF(B12="","",INT(ROUND(B12*10000,0)/10000)&"g "&INT(MOD(ROUND(B12*10000,0),10000)/100)&"s "&MOD(ROUND(B12*10000,0),100)&"c") -> 161g 78s 65c | D12: =SUMIFS(Bedarf!$I$3:$I$85,Bedarf!$A$3:$A$85,"LW",Bedarf!$B$3:$B$85,$A12) -> 0 | E12: =SUMIFS(Bedarf!$J$3:$J$85,Bedarf!$A$3:$A$85,"LW",Bedarf!$B$3:$B$85,$A12) -> 0 | F12: =SUMIFS(Bedarf!$H$3:$H$85,Bedarf!$A$3:$A$85,"VZ",Bedarf!$B$3:$B$85,$A12)/100 -> 68.9352 | G12: =IF(F12="","",INT(ROUND(F12*10000,0)/10000)&"g "&INT(MOD(ROUND(F12*10000,0),10000)/100)&"s "&MOD(ROUND(F12*10000,0),100)&"c") -> 68g 93s 52c | H12: =SUMIFS(Bedarf!$I$3:$I$85,Bedarf!$A$3:$A$85,"VZ",Bedarf!$B$3:$B$85,$A12) -> 0 | I12: =SUMIFS(Bedarf!$J$3:$J$85,Bedarf!$A$3:$A$85,"VZ",Bedarf!$B$3:$B$85,$A12) -> 3 | J12: =B12+F12 -> 230.7217
A13: 250-300 | B13: =SUMIFS(Bedarf!$H$3:$H$85,Bedarf!$A$3:$A$85,"LW",Bedarf!$B$3:$B$85,$A13)/100 -> 108.1272 | C13: =IF(B13="","",INT(ROUND(B13*10000,0)/10000)&"g "&INT(MOD(ROUND(B13*10000,0),10000)/100)&"s "&MOD(ROUND(B13*10000,0),100)&"c") -> 108g 12s 72c | D13: =SUMIFS(Bedarf!$I$3:$I$85,Bedarf!$A$3:$A$85,"LW",Bedarf!$B$3:$B$85,$A13) -> 0 | E13: =SUMIFS(Bedarf!$J$3:$J$85,Bedarf!$A$3:$A$85,"LW",Bedarf!$B$3:$B$85,$A13) -> 0 | F13: =SUMIFS(Bedarf!$H$3:$H$85,Bedarf!$A$3:$A$85,"VZ",Bedarf!$B$3:$B$85,$A13)/100 -> 1536.32 | G13: =IF(F13="","",INT(ROUND(F13*10000,0)/10000)&"g "&INT(MOD(ROUND(F13*10000,0),10000)/100)&"s "&MOD(ROUND(F13*10000,0),100)&"c") -> 1536g 32s 0c | H13: =SUMIFS(Bedarf!$I$3:$I$85,Bedarf!$A$3:$A$85,"VZ",Bedarf!$B$3:$B$85,$A13) -> 3 | I13: =SUMIFS(Bedarf!$J$3:$J$85,Bedarf!$A$3:$A$85,"VZ",Bedarf!$B$3:$B$85,$A13) -> 8 | J13: =B13+F13 -> 1644.4472
A14: Summe 1-300 | B14: =SUM(B9:B13) -> 312.792 | C14: =IF(B14="","",INT(ROUND(B14*10000,0)/10000)&"g "&INT(MOD(ROUND(B14*10000,0),10000)/100)&"s "&MOD(ROUND(B14*10000,0),100)&"c") -> 312g 79s 20c | D14: =SUM(D9:D13) -> 0 | E14: =SUM(E9:E13) -> 0 | F14: =SUM(F9:F13) -> 1623.9582 | G14: =IF(F14="","",INT(ROUND(F14*10000,0)/10000)&"g "&INT(MOD(ROUND(F14*10000,0),10000)/100)&"s "&MOD(ROUND(F14*10000,0),100)&"c") -> 1623g 95s 82c | H14: =SUM(H9:H13) -> 4 | I14: =SUM(I9:I13) -> 13 | J14: =SUM(J9:J13) -> 1936.7502
A15: davon 1-200 | B15: =SUM(B9:B11) -> 42.8783 | C15: =IF(B15="","",INT(ROUND(B15*10000,0)/10000)&"g "&INT(MOD(ROUND(B15*10000,0),10000)/100)&"s "&MOD(ROUND(B15*10000,0),100)&"c") -> 42g 87s 83c | F15: =SUM(F9:F11) -> 18.703 | G15: =IF(F15="","",INT(ROUND(F15*10000,0)/10000)&"g "&INT(MOD(ROUND(F15*10000,0),10000)/100)&"s "&MOD(ROUND(F15*10000,0),100)&"c") -> 18g 70s 30c | J15: =B15+F15 -> 61.5813
A16: VZ-Material aus eigener Entzauberung der LW-Teile (Wert, Gold) | F16: =Kreislauf!H59 -> 201.58456 | G16: =IF(F16="","",INT(ROUND(F16*10000,0)/10000)&"g "&INT(MOD(ROUND(F16*10000,0),10000)/100)&"s "&MOD(ROUND(F16*10000,0),100)&"c") -> 201g 58s 46c
A17: VZ netto zu kaufen (Gold) | F17: =F14-F16 -> 1422.3736 | G17: =IF(F17="","",INT(ROUND(F17*10000,0)/10000)&"g "&INT(MOD(ROUND(F17*10000,0),10000)/100)&"s "&MOD(ROUND(F17*10000,0),100)&"c") -> 1422g 37s 36c
A18: LW + VZ netto (Gold) | J18: =B14+F17 -> 1735.1656
A20: So liest du das Blatt
A21: Gelb = hier änderst du: Markt (B4), Preisbasis (B5), Schwelle (B6); im Blatt Preise die Spalte «Eigener Preis»; im Blatt Kreislauf die Chancen.
A22: Beispiel: Am 04.11. kostet Medium Leather 3s 50c → im Blatt Preise bei Medium Leather in Spalte K «3.5» eintragen. Alles rechnet neu.
A23: Blau = Werte aus Quellen (Wowhead, AHledger, Blizzard Dev Notes). Grün = Bezug auf ein anderes Blatt. Schwarz = Formel.
A24: Die Mengen sind Wowheads Classic-Era-Routen. Forever weicht ab (LW-Rezepte rund 25 Punkte tiefer, einige VZ-Rezepte der Route fehlen in Forever). Siehe Bemerkungen im Blatt Bedarf.
A25: Posten ohne Preis zählen als 0: Die Summe ist dann zu tief. «Dünner Markt» = wenige gelistete Stück, der Preis ist ein Zufallswert.
A27: Materialliste (Summe der Routenschritte; zum Vergleich Wowheads eigene Einkaufsliste)
A28: Material | B28: Beruf | C28: Menge Route | D28: Menge Wowhead-Liste | E28: Rechenpreis (s) | F28: Kosten (Gold) | G28: Hinweis
A29: Ruined Leather Scraps | B29: LW | C29: =SUMIFS(Bedarf!$F$3:$F$85,Bedarf!$A$3:$A$85,B29,Bedarf!$E$3:$E$85,A29) -> 90 | D29: 90 | E29: =IFERROR(INDEX(Preise!$L$3:$L$53,MATCH(A29,Preise!$A$3:$A$53,0)),"") -> 0.25 | F29: =IF(E29="","",C29*E29/100) -> 0.225 | G29: =IFERROR(INDEX(Preise!$M$3:$M$53,MATCH(A29,Preise!$A$3:$A$53,0)),"")
A30: Light Leather | B30: LW | C30: =SUMIFS(Bedarf!$F$3:$F$85,Bedarf!$A$3:$A$85,B30,Bedarf!$E$3:$E$85,A30) -> 198 | D30: 198 | E30: =IFERROR(INDEX(Preise!$L$3:$L$53,MATCH(A30,Preise!$A$3:$A$53,0)),"") -> 0.5 | F30: =IF(E30="","",C30*E30/100) -> 0.99 | G30: =IFERROR(INDEX(Preise!$M$3:$M$53,MATCH(A30,Preise!$A$3:$A$53,0)),"")
A31: Light Hide | B31: LW | C31: =SUMIFS(Bedarf!$F$3:$F$85,Bedarf!$A$3:$A$85,B31,Bedarf!$E$3:$E$85,A31) -> 10 | D31: 10 | E31: =IFERROR(INDEX(Preise!$L$3:$L$53,MATCH(A31,Preise!$A$3:$A$53,0)),"") -> 0.69 | F31: =IF(E31="","",C31*E31/100) -> 0.069 | G31: =IFERROR(INDEX(Preise!$M$3:$M$53,MATCH(A31,Preise!$A$3:$A$53,0)),"")
A32: Salt | B32: LW | C32: =SUMIFS(Bedarf!$F$3:$F$85,Bedarf!$A$3:$A$85,B32,Bedarf!$E$3:$E$85,A32) -> 85 | D32: 40 (135) | E32: =IFERROR(INDEX(Preise!$L$3:$L$53,MATCH(A32,Preise!$A$3:$A$53,0)),"") -> 0.5 | F32: =IF(E32="","",C32*E32/100) -> 0.425 | G32: =IFERROR(INDEX(Preise!$M$3:$M$53,MATCH(A32,Preise!$A$3:$A$53,0)),"") -> Händler
A33: Coarse Thread | B33: LW | C33: =SUMIFS(Bedarf!$F$3:$F$85,Bedarf!$A$3:$A$85,B33,Bedarf!$E$3:$E$85,A33) -> 90 | D33: 90 | E33: =IFERROR(INDEX(Preise!$L$3:$L$53,MATCH(A33,Preise!$A$3:$A$53,0)),"") -> 0.1 | F33: =IF(E33="","",C33*E33/100) -> 0.09 | G33: =IFERROR(INDEX(Preise!$M$3:$M$53,MATCH(A33,Preise!$A$3:$A$53,0)),"") -> Händler
A34: Medium Hide | B34: LW | C34: =SUMIFS(Bedarf!$F$3:$F$85,Bedarf!$A$3:$A$85,B34,Bedarf!$E$3:$E$85,A34) -> 15 | D34: 15 | E34: =IFERROR(INDEX(Preise!$L$3:$L$53,MATCH(A34,Preise!$A$3:$A$53,0)),"") -> 8.88 | F34: =IF(E34="","",C34*E34/100) -> 1.332 | G34: =IFERROR(INDEX(Preise!$M$3:$M$53,MATCH(A34,Preise!$A$3:$A$53,0)),"")
A35: Medium Leather | B35: LW | C35: =SUMIFS(Bedarf!$F$3:$F$85,Bedarf!$A$3:$A$85,B35,Bedarf!$E$3:$E$85,A35) -> 113 | D35: 113 | E35: =IFERROR(INDEX(Preise!$L$3:$L$53,MATCH(A35,Preise!$A$3:$A$53,0)),"") -> 1.91 | F35: =IF(E35="","",C35*E35/100) -> 2.1583 | G35: =IFERROR(INDEX(Preise!$M$3:$M$53,MATCH(A35,Preise!$A$3:$A$53,0)),"")
A36: Fine Thread | B36: LW | C36: =SUMIFS(Bedarf!$F$3:$F$85,Bedarf!$A$3:$A$85,B36,Bedarf!$E$3:$E$85,A36) -> 116 | D36: 116 | E36: =IFERROR(INDEX(Preise!$L$3:$L$53,MATCH(A36,Preise!$A$3:$A$53,0)),"") -> 1 | F36: =IF(E36="","",C36*E36/100) -> 1.16 | G36: =IFERROR(INDEX(Preise!$M$3:$M$53,MATCH(A36,Preise!$A$3:$A$53,0)),"") -> Händler
A37: Gray Dye | B37: LW | C37: =SUMIFS(Bedarf!$F$3:$F$85,Bedarf!$A$3:$A$85,B37,Bedarf!$E$3:$E$85,A37) -> 37 | D37: 37 | E37: =IFERROR(INDEX(Preise!$L$3:$L$53,MATCH(A37,Preise!$A$3:$A$53,0)),"") -> 3.5 | F37: =IF(E37="","",C37*E37/100) -> 1.295 | G37: =IFERROR(INDEX(Preise!$M$3:$M$53,MATCH(A37,Preise!$A$3:$A$53,0)),"") -> Händler
A38: Heavy Hide | B38: LW | C38: =SUMIFS(Bedarf!$F$3:$F$85,Bedarf!$A$3:$A$85,B38,Bedarf!$E$3:$E$85,A38) -> 20 | D38: 5 (40) | E38: =IFERROR(INDEX(Preise!$L$3:$L$53,MATCH(A38,Preise!$A$3:$A$53,0)),"") -> 35.4 | F38: =IF(E38="","",C38*E38/100) -> 7.08 | G38: =IFERROR(INDEX(Preise!$M$3:$M$53,MATCH(A38,Preise!$A$3:$A$53,0)),"")
A39: Heavy Leather | B39: LW | C39: =SUMIFS(Bedarf!$F$3:$F$85,Bedarf!$A$3:$A$85,B39,Bedarf!$E$3:$E$85,A39) -> 230 | D39: 230 | E39: =IFERROR(INDEX(Preise!$L$3:$L$53,MATCH(A39,Preise!$A$3:$A$53,0)),"") -> 11.98 | F39: =IF(E39="","",C39*E39/100) -> 27.554 | G39: =IFERROR(INDEX(Preise!$M$3:$M$53,MATCH(A39,Preise!$A$3:$A$53,0)),"")
A40: Silken Thread | B40: LW | C40: =SUMIFS(Bedarf!$F$3:$F$85,Bedarf!$A$3:$A$85,B40,Bedarf!$E$3:$E$85,A40) -> 132 | D40: 122 | E40: =IFERROR(INDEX(Preise!$L$3:$L$53,MATCH(A40,Preise!$A$3:$A$53,0)),"") -> 5 | F40: =IF(E40="","",C40*E40/100) -> 6.6 | G40: =IFERROR(INDEX(Preise!$M$3:$M$53,MATCH(A40,Preise!$A$3:$A$53,0)),"") -> Händler
A41: Thick Leather | B41: LW | C41: =SUMIFS(Bedarf!$F$3:$F$85,Bedarf!$A$3:$A$85,B41,Bedarf!$E$3:$E$85,A41) -> 435 | D41: 435 | E41: =IFERROR(INDEX(Preise!$L$3:$L$53,MATCH(A41,Preise!$A$3:$A$53,0)),"") -> 35.79 | F41: =IF(E41="","",C41*E41/100) -> 155.6865 | G41: =IFERROR(INDEX(Preise!$M$3:$M$53,MATCH(A41,Preise!$A$3:$A$53,0)),"")
A42: Rugged Leather | B42: LW | C42: =SUMIFS(Bedarf!$F$3:$F$85,Bedarf!$A$3:$A$85,B42,Bedarf!$E$3:$E$85,A42) -> 436 | D42: 436 | E42: =IFERROR(INDEX(Preise!$L$3:$L$53,MATCH(A42,Preise!$A$3:$A$53,0)),"") -> 19.02 | F42: =IF(E42="","",C42*E42/100) -> 82.9272 | G42: =IFERROR(INDEX(Preise!$M$3:$M$53,MATCH(A42,Preise!$A$3:$A$53,0)),"")
A43: Black Dye | B43: LW | C43: =SUMIFS(Bedarf!$F$3:$F$85,Bedarf!$A$3:$A$85,B43,Bedarf!$E$3:$E$85,A43) -> 42 | D43: 42 | E43: =IFERROR(INDEX(Preise!$L$3:$L$53,MATCH(A43,Preise!$A$3:$A$53,0)),"") -> 10 | F43: =IF(E43="","",C43*E43/100) -> 4.2 | G43: =IFERROR(INDEX(Preise!$M$3:$M$53,MATCH(A43,Preise!$A$3:$A$53,0)),"") -> Händler
A44: Rune Thread | B44: LW | C44: =SUMIFS(Bedarf!$F$3:$F$85,Bedarf!$A$3:$A$85,B44,Bedarf!$E$3:$E$85,A44) -> 42 | D44: 42 | E44: =IFERROR(INDEX(Preise!$L$3:$L$53,MATCH(A44,Preise!$A$3:$A$53,0)),"") -> 50 | F44: =IF(E44="","",C44*E44/100) -> 21 | G44: =IFERROR(INDEX(Preise!$M$3:$M$53,MATCH(A44,Preise!$A$3:$A$53,0)),"") -> Händler
A45: Copper Rod | B45: VZ | C45: =SUMIFS(Bedarf!$F$3:$F$85,Bedarf!$A$3:$A$85,B45,Bedarf!$E$3:$E$85,A45) -> 1 | D45: 1 | E45: =IFERROR(INDEX(Preise!$L$3:$L$53,MATCH(A45,Preise!$A$3:$A$53,0)),"") | F45: =IF(E45="","",C45*E45/100) | G45: =IFERROR(INDEX(Preise!$M$3:$M$53,MATCH(A45,Preise!$A$3:$A$53,0)),"") -> kein Preis
A46: Strange Dust | B46: VZ | C46: =SUMIFS(Bedarf!$F$3:$F$85,Bedarf!$A$3:$A$85,B46,Bedarf!$E$3:$E$85,A46) -> 145 | D46: 145 | E46: =IFERROR(INDEX(Preise!$L$3:$L$53,MATCH(A46,Preise!$A$3:$A$53,0)),"") -> 0.84 | F46: =IF(E46="","",C46*E46/100) -> 1.218 | G46: =IFERROR(INDEX(Preise!$M$3:$M$53,MATCH(A46,Preise!$A$3:$A$53,0)),"")
A47: Lesser Magic Essence | B47: VZ | C47: =SUMIFS(Bedarf!$F$3:$F$85,Bedarf!$A$3:$A$85,B47,Bedarf!$E$3:$E$85,A47) -> 1 | D47: 1 | E47: =IFERROR(INDEX(Preise!$L$3:$L$53,MATCH(A47,Preise!$A$3:$A$53,0)),"") -> 0.69 | F47: =IF(E47="","",C47*E47/100) -> 0.0069 | G47: =IFERROR(INDEX(Preise!$M$3:$M$53,MATCH(A47,Preise!$A$3:$A$53,0)),"")
A48: Silver Rod | B48: VZ | C48: =SUMIFS(Bedarf!$F$3:$F$85,Bedarf!$A$3:$A$85,B48,Bedarf!$E$3:$E$85,A48) -> 1 | D48: 1 | E48: =IFERROR(INDEX(Preise!$L$3:$L$53,MATCH(A48,Preise!$A$3:$A$53,0)),"") -> 19 | F48: =IF(E48="","",C48*E48/100) -> 0.19 | G48: =IFERROR(INDEX(Preise!$M$3:$M$53,MATCH(A48,Preise!$A$3:$A$53,0)),"")
A49: Greater Magic Essence | B49: VZ | C49: =SUMIFS(Bedarf!$F$3:$F$85,Bedarf!$A$3:$A$85,B49,Bedarf!$E$3:$E$85,A49) -> 12 | D49: 12 | E49: =IFERROR(INDEX(Preise!$L$3:$L$53,MATCH(A49,Preise!$A$3:$A$53,0)),"") -> 1.96 | F49: =IF(E49="","",C49*E49/100) -> 0.2352 | G49: =IFERROR(INDEX(Preise!$M$3:$M$53,MATCH(A49,Preise!$A$3:$A$53,0)),"")
A50: Shadowgem | B50: VZ | C50: =SUMIFS(Bedarf!$F$3:$F$85,Bedarf!$A$3:$A$85,B50,Bedarf!$E$3:$E$85,A50) -> 1 | D50: nicht in Liste | E50: =IFERROR(INDEX(Preise!$L$3:$L$53,MATCH(A50,Preise!$A$3:$A$53,0)),"") -> 3.14 | F50: =IF(E50="","",C50*E50/100) -> 0.0314 | G50: =IFERROR(INDEX(Preise!$M$3:$M$53,MATCH(A50,Preise!$A$3:$A$53,0)),"")
A51: Simple Wood | B51: VZ | C51: =SUMIFS(Bedarf!$F$3:$F$85,Bedarf!$A$3:$A$85,B51,Bedarf!$E$3:$E$85,A51) -> 9 | D51: 9 | E51: =IFERROR(INDEX(Preise!$L$3:$L$53,MATCH(A51,Preise!$A$3:$A$53,0)),"") -> 0.7 | F51: =IF(E51="","",C51*E51/100) -> 0.063 | G51: =IFERROR(INDEX(Preise!$M$3:$M$53,MATCH(A51,Preise!$A$3:$A$53,0)),"")
A52: Lesser Astral Essence | B52: VZ | C52: =SUMIFS(Bedarf!$F$3:$F$85,Bedarf!$A$3:$A$85,B52,Bedarf!$E$3:$E$85,A52) -> 25 | D52: 25 | E52: =IFERROR(INDEX(Preise!$L$3:$L$53,MATCH(A52,Preise!$A$3:$A$53,0)),"") -> 6.04 | F52: =IF(E52="","",C52*E52/100) -> 1.51 | G52: =IFERROR(INDEX(Preise!$M$3:$M$53,MATCH(A52,Preise!$A$3:$A$53,0)),"")
A53: Soul Dust | B53: VZ | C53: =SUMIFS(Bedarf!$F$3:$F$85,Bedarf!$A$3:$A$85,B53,Bedarf!$E$3:$E$85,A53) -> 122 | D53: 130 | E53: =IFERROR(INDEX(Preise!$L$3:$L$53,MATCH(A53,Preise!$A$3:$A$53,0)),"") -> 7.21 | F53: =IF(E53="","",C53*E53/100) -> 8.7962 | G53: =IFERROR(INDEX(Preise!$M$3:$M$53,MATCH(A53,Preise!$A$3:$A$53,0)),"")
A54: Golden Rod | B54: VZ | C54: =SUMIFS(Bedarf!$F$3:$F$85,Bedarf!$A$3:$A$85,B54,Bedarf!$E$3:$E$85,A54) -> 1 | D54: 1 | E54: =IFERROR(INDEX(Preise!$L$3:$L$53,MATCH(A54,Preise!$A$3:$A$53,0)),"") -> 8 | F54: =IF(E54="","",C54*E54/100) -> 0.08 | G54: =IFERROR(INDEX(Preise!$M$3:$M$53,MATCH(A54,Preise!$A$3:$A$53,0)),"") -> dünn
A55: Iridescent Pearl | B55: VZ | C55: =SUMIFS(Bedarf!$F$3:$F$85,Bedarf!$A$3:$A$85,B55,Bedarf!$E$3:$E$85,A55) -> 1 | D55: 1 | E55: =IFERROR(INDEX(Preise!$L$3:$L$53,MATCH(A55,Preise!$A$3:$A$53,0)),"") -> 304.5 | F55: =IF(E55="","",C55*E55/100) -> 3.045 | G55: =IFERROR(INDEX(Preise!$M$3:$M$53,MATCH(A55,Preise!$A$3:$A$53,0)),"") -> dünn
A56: Greater Astral Essence | B56: VZ | C56: =SUMIFS(Bedarf!$F$3:$F$85,Bedarf!$A$3:$A$85,B56,Bedarf!$E$3:$E$85,A56) -> 2 | D56: 2 | E56: =IFERROR(INDEX(Preise!$L$3:$L$53,MATCH(A56,Preise!$A$3:$A$53,0)),"") -> 28.54 | F56: =IF(E56="","",C56*E56/100) -> 0.5708 | G56: =IFERROR(INDEX(Preise!$M$3:$M$53,MATCH(A56,Preise!$A$3:$A$53,0)),"")
A57: Vision Dust | B57: VZ | C57: =SUMIFS(Bedarf!$F$3:$F$85,Bedarf!$A$3:$A$85,B57,Bedarf!$E$3:$E$85,A57) -> 237 | D57: 240 | E57: =IFERROR(INDEX(Preise!$L$3:$L$53,MATCH(A57,Preise!$A$3:$A$53,0)),"") -> 19.71 | F57: =IF(E57="","",C57*E57/100) -> 46.7127 | G57: =IFERROR(INDEX(Preise!$M$3:$M$53,MATCH(A57,Preise!$A$3:$A$53,0)),"")
A58: Truesilver Rod | B58: VZ | C58: =SUMIFS(Bedarf!$F$3:$F$85,Bedarf!$A$3:$A$85,B58,Bedarf!$E$3:$E$85,A58) -> 1 | D58: 1 | E58: =IFERROR(INDEX(Preise!$L$3:$L$53,MATCH(A58,Preise!$A$3:$A$53,0)),"") -> 85 | F58: =IF(E58="","",C58*E58/100) -> 0.85 | G58: =IFERROR(INDEX(Preise!$M$3:$M$53,MATCH(A58,Preise!$A$3:$A$53,0)),"") -> dünn
A59: Black Pearl | B59: VZ | C59: =SUMIFS(Bedarf!$F$3:$F$85,Bedarf!$A$3:$A$85,B59,Bedarf!$E$3:$E$85,A59) -> 1 | D59: 1 | E59: =IFERROR(INDEX(Preise!$L$3:$L$53,MATCH(A59,Preise!$A$3:$A$53,0)),"") -> 1000 | F59: =IF(E59="","",C59*E59/100) -> 10 | G59: =IFERROR(INDEX(Preise!$M$3:$M$53,MATCH(A59,Preise!$A$3:$A$53,0)),"") -> dünn
A60: Greater Mystic Essence | B60: VZ | C60: =SUMIFS(Bedarf!$F$3:$F$85,Bedarf!$A$3:$A$85,B60,Bedarf!$E$3:$E$85,A60) -> 2 | D60: 2 | E60: =IFERROR(INDEX(Preise!$L$3:$L$53,MATCH(A60,Preise!$A$3:$A$53,0)),"") -> 44 | F60: =IF(E60="","",C60*E60/100) -> 0.88 | G60: =IFERROR(INDEX(Preise!$M$3:$M$53,MATCH(A60,Preise!$A$3:$A$53,0)),"")
A61: Lesser Nether Essence | B61: VZ | C61: =SUMIFS(Bedarf!$F$3:$F$85,Bedarf!$A$3:$A$85,B61,Bedarf!$E$3:$E$85,A61) -> 5 | D61: 5 | E61: =IFERROR(INDEX(Preise!$L$3:$L$53,MATCH(A61,Preise!$A$3:$A$53,0)),"") -> 268.98 | F61: =IF(E61="","",C61*E61/100) -> 13.449 | G61: =IFERROR(INDEX(Preise!$M$3:$M$53,MATCH(A61,Preise!$A$3:$A$53,0)),"") -> dünn
A62: Dream Dust | B62: VZ | C62: =SUMIFS(Bedarf!$F$3:$F$85,Bedarf!$A$3:$A$85,B62,Bedarf!$E$3:$E$85,A62) -> 360 | D62: 360 | E62: =IFERROR(INDEX(Preise!$L$3:$L$53,MATCH(A62,Preise!$A$3:$A$53,0)),"") -> 58 | F62: =IF(E62="","",C62*E62/100) -> 208.8 | G62: =IFERROR(INDEX(Preise!$M$3:$M$53,MATCH(A62,Preise!$A$3:$A$53,0)),"") -> dünn
... A67: Illusion Dust | B67: VZ | C67: =SUMIFS(Bedarf!$F$3:$F$85,Bedarf!$A$3:$A$85,B67,Bedarf!$E$3:$E$85,A67) -> 50 | D67: 82 | E67: =IFERROR(INDEX(Preise!$L$3:$L$53,MATCH(A67,Preise!$A$3:$A$53,0)),"") -> 1000 | F67: =IF(E67="","",C67*E67/100) -> 500 | G67: =IFERROR(INDEX(Preise!$M$3:$M$53,MATCH(A67,Preise!$A$3:$A$53,0)),"") -> dünn
A68: Greater Eternal Essence | B68: VZ | C68: =SUMIFS(Bedarf!$F$3:$F$85,Bedarf!$A$3:$A$85,B68,Bedarf!$E$3:$E$85,A68) -> 4 | D68: 4 + 4 | E68: =IFERROR(INDEX(Preise!$L$3:$L$53,MATCH(A68,Preise!$A$3:$A$53,0)),"") | F68: =IF(E68="","",C68*E68/100) | G68: =IFERROR(INDEX(Preise!$M$3:$M$53,MATCH(A68,Preise!$A$3:$A$53,0)),"") -> kein Preis
A69: Small Brilliant Shard | B69: VZ | C69: =SUMIFS(Bedarf!$F$3:$F$85,Bedarf!$A$3:$A$85,B69,Bedarf!$E$3:$E$85,A69) -> 4 | D69: 4 | E69: =IFERROR(INDEX(Preise!$L$3:$L$53,MATCH(A69,Preise!$A$3:$A$53,0)),"") -> 488 | F69: =IF(E69="","",C69*E69/100) -> 19.52 | G69: =IFERROR(INDEX(Preise!$M$3:$M$53,MATCH(A69,Preise!$A$3:$A$53,0)),"") -> dünn
A70: Large Brilliant Shard | B70: VZ | C70: =SUMIFS(Bedarf!$F$3:$F$85,Bedarf!$A$3:$A$85,B70,Bedarf!$E$3:$E$85,A70) -> 2 | D70: 2 | E70: =IFERROR(INDEX(Preise!$L$3:$L$53,MATCH(A70,Preise!$A$3:$A$53,0)),"") | F70: =IF(E70="","",C70*E70/100) | G70: =IFERROR(INDEX(Preise!$M$3:$M$53,MATCH(A70,Preise!$A$3:$A$53,0)),"") -> kein Preis

Sheet Preise
A1: Preise in Silber (1 Gold = 100 Silber, 1 Silber = 100 Kupfer). Marktpreise: AHledger, Forever-Beta, Horde US. Gelbe Spalte K: eigener Preis überschreibt alles.
A2: Material | B2: Beruf | C2: Händlerpreis (s) | D2: NH Median (s) | E2: PH Median (s) | F2: NH 30 Tage (s) | G2: PH 30 Tage (s) | H2: NH gelistet (Stück) | I2: PH gelistet (Stück) | J2: Stand Seite | K2: Eigener Preis (s) | L2: Rechenpreis (s) | M2: Hinweis | N2: Quelle | O2: Bemerkung
A3: Ruined Leather Scraps | B3: LW | D3: 0.25 | E3: 0.28 | F3: 0.28 | G3: 0.4 | H3: 2553 | I3: 4407 | J3: 12.10. | L3: =IF(K3<>"",K3,IF(C3<>"",C3,IF(Übersicht!$B$4="NH",IF(Übersicht!$B$5="jetzt",IF(D3="","",D3),IF(F3="","",F3)),IF(Übersicht!$B$5="jetzt",IF(E3="","",E3),IF(G3="","",G3))))) -> 0.25 | M3: =IF(L3="","kein Preis",IF(K3<>"","eigener Preis",IF(C3<>"","Händler",IF(IF(Übersicht!$B$4="NH",H3,I3)<Übersicht!$B$6,"dünn","")))) | N3: https://ahledger.com/items/2934-ruined-leather-scraps
A4: Light Leather | B4: LW | D4: 0.5 | E4: 0.68 | F4: 0.79 | G4: 1.09 | H4: 2729 | I4: 5335 | J4: 12.10. | L4: =IF(K4<>"",K4,IF(C4<>"",C4,IF(Übersicht!$B$4="NH",IF(Übersicht!$B$5="jetzt",IF(D4="","",D4),IF(F4="","",F4)),IF(Übersicht!$B$5="jetzt",IF(E4="","",E4),IF(G4="","",G4))))) -> 0.5 | M4: =IF(L4="","kein Preis",IF(K4<>"","eigener Preis",IF(C4<>"","Händler",IF(IF(Übersicht!$B$4="NH",H4,I4)<Übersicht!$B$6,"dünn","")))) | N4: https://ahledger.com/items/2318-light-leather
A5: Medium Leather | B5: LW | D5: 1.91 | E5: 2.1 | F5: 2.56 | G5: 2.29 | H5: 3562 | I5: 2894 | J5: 12.10. | L5: =IF(K5<>"",K5,IF(C5<>"",C5,IF(Übersicht!$B$4="NH",IF(Übersicht!$B$5="jetzt",IF(D5="","",D5),IF(F5="","",F5)),IF(Übersicht!$B$5="jetzt",IF(E5="","",E5),IF(G5="","",G5))))) -> 1.91 | M5: =IF(L5="","kein Preis",IF(K5<>"","eigener Preis",IF(C5<>"","Händler",IF(IF(Übersicht!$B$4="NH",H5,I5)<Übersicht!$B$6,"dünn","")))) | N5: https://ahledger.com/items/2319-medium-leather
A6: Heavy Leather | B6: LW | D6: 11.98 | E6: 11 | F6: 12.7 | G6: 12.23 | H6: 2372 | I6: 1784 | J6: 08.10. | L6: =IF(K6<>"",K6,IF(C6<>"",C6,IF(Übersicht!$B$4="NH",IF(Übersicht!$B$5="jetzt",IF(D6="","",D6),IF(F6="","",F6)),IF(Übersicht!$B$5="jetzt",IF(E6="","",E6),IF(G6="","",G6))))) -> 11.98 | M6: =IF(L6="","kein Preis",IF(K6<>"","eigener Preis",IF(C6<>"","Händler",IF(IF(Übersicht!$B$4="NH",H6,I6)<Übersicht!$B$6,"dünn","")))) | N6: https://ahledger.com/items/4234-heavy-leather | O6: Marktseite 12.10.: NH 9.40 s, PH 9.13 s
A7: Thick Leather | B7: LW | D7: 35.79 | E7: 62 | F7: 40.2 | G7: 48.48 | H7: 348 | I7: 264 | J7: 12.10. | L7: =IF(K7<>"",K7,IF(C7<>"",C7,IF(Übersicht!$B$4="NH",IF(Übersicht!$B$5="jetzt",IF(D7="","",D7),IF(F7="","",F7)),IF(Übersicht!$B$5="jetzt",IF(E7="","",E7),IF(G7="","",G7))))) -> 35.79 | M7: =IF(L7="","kein Preis",IF(K7<>"","eigener Preis",IF(C7<>"","Händler",IF(IF(Übersicht!$B$4="NH",H7,I7)<Übersicht!$B$6,"dünn","")))) | N7: https://ahledger.com/items/4304-thick-leather
A8: Rugged Leather | B8: LW | D8: 19.02 | E8: 5 | F8: 9.8 | G8: 7.78 | H8: 214 | I8: 135 | J8: 05.10. | L8: =IF(K8<>"",K8,IF(C8<>"",C8,IF(Übersicht!$B$4="NH",IF(Übersicht!$B$5="jetzt",IF(D8="","",D8),IF(F8="","",F8)),IF(Übersicht!$B$5="jetzt",IF(E8="","",E8),IF(G8="","",G8))))) -> 19.02 | M8: =IF(L8="","kein Preis",IF(K8<>"","eigener Preis",IF(C8<>"","Händler",IF(IF(Übersicht!$B$4="NH",H8,I8)<Übersicht!$B$6,"dünn","")))) | N8: https://ahledger.com/items/8170-rugged-leather | O8: Beta bis Stufe 30: kaum Angebot
A9: Light Hide | B9: LW | D9: 0.69 | E9: 0.56 | F9: 0.78 | G9: 0.64 | H9: 189 | I9: 793 | J9: 09.10. | L9: =IF(K9<>"",K9,IF(C9<>"",C9,IF(Übersicht!$B$4="NH",IF(Übersicht!$B$5="jetzt",IF(D9="","",D9),IF(F9="","",F9)),IF(Übersicht!$B$5="jetzt",IF(E9="","",E9),IF(G9="","",G9))))) -> 0.69 | M9: =IF(L9="","kein Preis",IF(K9<>"","eigener Preis",IF(C9<>"","Händler",IF(IF(Übersicht!$B$4="NH",H9,I9)<Übersicht!$B$6,"dünn","")))) | N9: https://ahledger.com/items/783-light-hide
A10: Medium Hide | B10: LW | D10: 8.88 | E10: 7.32 | F10: 9.12 | G10: 7.78 | H10: 221 | I10: 667 | J10: 30.09. | L10: =IF(K10<>"",K10,IF(C10<>"",C10,IF(Übersicht!$B$4="NH",IF(Übersicht!$B$5="jetzt",IF(D10="","",D10),IF(F10="","",F10)),IF(Übersicht!$B$5="jetzt",IF(E10="","",E10),IF(G10="","",G10))))) -> 8.88 | M10: =IF(L10="","kein Preis",IF(K10<>"","eigener Preis",IF(C10<>"","Händler",IF(IF(Übersicht!$B$4="NH",H10,I10)<Übersicht!$B$6,"dünn","")))) | N10: https://ahledger.com/items/4232-medium-hide
A11: Heavy Hide | B11: LW | D11: 35.4 | E11: 30.69 | F11: 96.75 | G11: 72.99 | H11: 231 | I11: 279 | J11: 08.10. | L11: =IF(K11<>"",K11,IF(C11<>"",C11,IF(Übersicht!$B$4="NH",IF(Übersicht!$B$5="jetzt",IF(D11="","",D11),IF(F11="","",F11)),IF(Übersicht!$B$5="jetzt",IF(E11="","",E11),IF(G11="","",G11))))) -> 35.4 | M11: =IF(L11="","kein Preis",IF(K11<>"","eigener Preis",IF(C11<>"","Händler",IF(IF(Übersicht!$B$4="NH",H11,I11)<Übersicht!$B$6,"dünn","")))) | N11: https://ahledger.com/items/4235-heavy-hide
A12: Salt | B12: LW | C12: 0.5 | D12: 1 | E12: 0.7 | F12: 0.82 | G12: 0.82 | H12: 64 | I12: 493 | J12: 05.10. | L12: =IF(K12<>"",K12,IF(C12<>"",C12,IF(Übersicht!$B$4="NH",IF(Übersicht!$B$5="jetzt",IF(D12="","",D12),IF(F12="","",F12)),IF(Übersicht!$B$5="jetzt",IF(E12="","",E12),IF(G12="","",G12))))) -> 0.5 | M12: =IF(L12="","kein Preis",IF(K12<>"","eigener Preis",IF(C12<>"","Händler",IF(IF(Übersicht!$B$4="NH",H12,I12)<Übersicht!$B$6,"dünn","")))) -> Händler | N12: https://ahledger.com/items/4289-salt | O12: Händlerpreis laut AHledger
A13: Coarse Thread | B13: LW | C13: 0.1 | D13: 0.17 | E13: 0.22 | F13: 0.34 | G13: 0.34 | H13: 1596 | I13: 1796 | J13: 12.10. | L13: =IF(K13<>"",K13,IF(C13<>"",C13,IF(Übersicht!$B$4="NH",IF(Übersicht!$B$5="jetzt",IF(D13="","",D13),IF(F13="","",F13)),IF(Übersicht!$B$5="jetzt",IF(E13="","",E13),IF(G13="","",G13))))) -> 0.1 | M13: =IF(L13="","kein Preis",IF(K13<>"","eigener Preis",IF(C13<>"","Händler",IF(IF(Übersicht!$B$4="NH",H13,I13)<Übersicht!$B$6,"dünn","")))) -> Händler | N13: https://ahledger.com/items/2320-coarse-thread | O13: Händlerpreis laut warcraft.wiki.gg (Version nicht angegeben)
A14: Fine Thread | B14: LW | C14: 1 | D14: 1.87 | E14: 1.48 | F14: 1.55 | G14: 1.44 | H14: 163 | I14: 1126 | J14: 03.10. | L14: =IF(K14<>"",K14,IF(C14<>"",C14,IF(Übersicht!$B$4="NH",IF(Übersicht!$B$5="jetzt",IF(D14="","",D14),IF(F14="","",F14)),IF(Übersicht!$B$5="jetzt",IF(E14="","",E14),IF(G14="","",G14))))) -> 1 | M14: =IF(L14="","kein Preis",IF(K14<>"","eigener Preis",IF(C14<>"","Händler",IF(IF(Übersicht!$B$4="NH",H14,I14)<Übersicht!$B$6,"dünn","")))) -> Händler | N14: https://ahledger.com/items/2321-fine-thread | O14: Händlerpreis laut AHledger und warcraft.wiki.gg
A15: Silken Thread | B15: LW | C15: 5 | D15: 10 | E15: 8.5 | F15: 10 | G15: 8.52 | H15: 22 | I15: 48 | J15: 27.09. | L15: =IF(K15<>"",K15,IF(C15<>"",C15,IF(Übersicht!$B$4="NH",IF(Übersicht!$B$5="jetzt",IF(D15="","",D15),IF(F15="","",F15)),IF(Übersicht!$B$5="jetzt",IF(E15="","",E15),IF(G15="","",G15))))) -> 5 | M15: =IF(L15="","kein Preis",IF(K15<>"","eigener Preis",IF(C15<>"","Händler",IF(IF(Übersicht!$B$4="NH",H15,I15)<Übersicht!$B$6,"dünn","")))) -> Händler | N15: https://ahledger.com/items/4291-silken-thread | O15: Händlerpreis laut warcraft.wiki.gg (Version nicht angegeben, für Forever ungeprüft)
A16: Rune Thread | B16: LW | C16: 50 | E16: 99.99 | F16: 19 | G16: 63 | H16: 0 | I16: 1 | J16: 05.10. | L16: =IF(K16<>"",K16,IF(C16<>"",C16,IF(Übersicht!$B$4="NH",IF(Übersicht!$B$5="jetzt",IF(D16="","",D16),IF(F16="","",F16)),IF(Übersicht!$B$5="jetzt",IF(E16="","",E16),IF(G16="","",G16))))) -> 50 | M16: =IF(L16="","kein Preis",IF(K16<>"","eigener Preis",IF(C16<>"","Händler",IF(IF(Übersicht!$B$4="NH",H16,I16)<Übersicht!$B$6,"dünn","")))) -> Händler | N16: https://ahledger.com/items/14341-rune-thread | O16: Händlerpreis laut AHledger
A17: Gray Dye | B17: LW | C17: 3.5 | D17: 4.69 | E17: 2.99 | F17: 6.16 | G17: 5.54 | H17: 28 | I17: 20 | J17: 05.10. | L17: =IF(K17<>"",K17,IF(C17<>"",C17,IF(Übersicht!$B$4="NH",IF(Übersicht!$B$5="jetzt",IF(D17="","",D17),IF(F17="","",F17)),IF(Übersicht!$B$5="jetzt",IF(E17="","",E17),IF(G17="","",G17))))) -> 3.5 | M17: =IF(L17="","kein Preis",IF(K17<>"","eigener Preis",IF(C17<>"","Händler",IF(IF(Übersicht!$B$4="NH",H17,I17)<Übersicht!$B$6,"dünn","")))) -> Händler | N17: https://ahledger.com/items/4340-gray-dye | O17: Händlerpreis laut AHledger
A18: Black Dye | B18: LW | C18: 10 | D18: 20 | E18: 24 | F18: 5.7 | G18: 8 | H18: 20 | I18: 21 | J18: 05.10. | L18: =IF(K18<>"",K18,IF(C18<>"",C18,IF(Übersicht!$B$4="NH",IF(Übersicht!$B$5="jetzt",IF(D18="","",D18),IF(F18="","",F18)),IF(Übersicht!$B$5="jetzt",IF(E18="","",E18),IF(G18="","",G18))))) -> 10 | M18: =IF(L18="","kein Preis",IF(K18<>"","eigener Preis",IF(C18<>"","Händler",IF(IF(Übersicht!$B$4="NH",H18,I18)<Übersicht!$B$6,"dünn","")))) -> Händler | N18: https://ahledger.com/items/2325-black-dye | O18: Händlerpreis laut AHledger
A19: Strange Dust | B19: VZ | D19: 0.84 | E19: 0.65 | F19: 2.42 | G19: 2.53 | H19: 7166 | I19: 3403 | J19: 12.10. | L19: =IF(K19<>"",K19,IF(C19<>"",C19,IF(Übersicht!$B$4="NH",IF(Übersicht!$B$5="jetzt",IF(D19="","",D19),IF(F19="","",F19)),IF(Übersicht!$B$5="jetzt",IF(E19="","",E19),IF(G19="","",G19))))) -> 0.84 | M19: =IF(L19="","kein Preis",IF(K19<>"","eigener Preis",IF(C19<>"","Händler",IF(IF(Übersicht!$B$4="NH",H19,I19)<Übersicht!$B$6,"dünn","")))) | N19: https://ahledger.com/items/10940-strange-dust
A20: Soul Dust | B20: VZ | D20: 7.21 | E20: 5.8 | F20: 8.53 | G20: 9.04 | H20: 1555 | I20: 2780 | J20: 12.10. | L20: =IF(K20<>"",K20,IF(C20<>"",C20,IF(Übersicht!$B$4="NH",IF(Übersicht!$B$5="jetzt",IF(D20="","",D20),IF(F20="","",F20)),IF(Übersicht!$B$5="jetzt",IF(E20="","",E20),IF(G20="","",G20))))) -> 7.21 | M20: =IF(L20="","kein Preis",IF(K20<>"","eigener Preis",IF(C20<>"","Händler",IF(IF(Übersicht!$B$4="NH",H20,I20)<Übersicht!$B$6,"dünn","")))) | N20: https://ahledger.com/items/11083-soul-dust
A21: Vision Dust | B21: VZ | D21: 19.71 | E21: 24.49 | F21: 37.3 | G21: 45.98 | H21: 637 | I21: 738 | J21: 12.10. | L21: =IF(K21<>"",K21,IF(C21<>"",C21,IF(Übersicht!$B$4="NH",IF(Übersicht!$B$5="jetzt",IF(D21="","",D21),IF(F21="","",F21)),IF(Übersicht!$B$5="jetzt",IF(E21="","",E21),IF(G21="","",G21))))) -> 19.71 | M21: =IF(L21="","kein Preis",IF(K21<>"","eigener Preis",IF(C21<>"","Händler",IF(IF(Übersicht!$B$4="NH",H21,I21)<Übersicht!$B$6,"dünn","")))) | N21: https://ahledger.com/items/11137-vision-dust
A22: Dream Dust | B22: VZ | D22: 58 | E22: 48.55 | F22: 46.43 | G22: 65.44 | H22: 47 | I22: 592 | J22: 12.10. | L22: =IF(K22<>"",K22,IF(C22<>"",C22,IF(Übersicht!$B$4="NH",IF(Übersicht!$B$5="jetzt",IF(D22="","",D22),IF(F22="","",F22)),IF(Übersicht!$B$5="jetzt",IF(E22="","",E22),IF(G22="","",G22))))) -> 58 | M22: =IF(L22="","kein Preis",IF(K22<>"","eigener Preis",IF(C22<>"","Händler",IF(IF(Übersicht!$B$4="NH",H22,I22)<Übersicht!$B$6,"dünn","")))) -> dünn | N22: https://ahledger.com/items/11176-dream-dust
A23: Illusion Dust | B23: VZ | D23: 1000 | F23: 1000 | G23: 481 | H23: 2 | I23: 0 | J23: 12.10. | L23: =IF(K23<>"",K23,IF(C23<>"",C23,IF(Übersicht!$B$4="NH",IF(Übersicht!$B$5="jetzt",IF(D23="","",D23),IF(F23="","",F23)),IF(Übersicht!$B$5="jetzt",IF(E23="","",E23),IF(G23="","",G23))))) -> 1000 | M23: =IF(L23="","kein Preis",IF(K23<>"","eigener Preis",IF(C23<>"","Händler",IF(IF(Übersicht!$B$4="NH",H23,I23)<Übersicht!$B$6,"dünn","")))) -> dünn | N23: https://ahledger.com/items/16204-illusion-dust | O23: NH: 2 Stück, Ausnahmewert
A24: Lesser Magic Essence | B24: VZ | D24: 0.69 | E24: 3.9 | F24: 7.35 | G24: 7.3 | H24: 2563 | I24: 18247 | J24: 03.10. | L24: =IF(K24<>"",K24,IF(C24<>"",C24,IF(Übersicht!$B$4="NH",IF(Übersicht!$B$5="jetzt",IF(D24="","",D24),IF(F24="","",F24)),IF(Übersicht!$B$5="jetzt",IF(E24="","",E24),IF(G24="","",G24))))) -> 0.69 | M24: =IF(L24="","kein Preis",IF(K24<>"","eigener Preis",IF(C24<>"","Händler",IF(IF(Übersicht!$B$4="NH",H24,I24)<Übersicht!$B$6,"dünn","")))) | N24: https://ahledger.com/items/10938-lesser-magic-essence
A25: Greater Magic Essence | B25: VZ | D25: 1.96 | E25: 1.89 | F25: 21.58 | G25: 21.36 | H25: 898 | I25: 424 | J25: 09.10. | L25: =IF(K25<>"",K25,IF(C25<>"",C25,IF(Übersicht!$B$4="NH",IF(Übersicht!$B$5="jetzt",IF(D25="","",D25),IF(F25="","",F25)),IF(Übersicht!$B$5="jetzt",IF(E25="","",E25),IF(G25="","",G25))))) -> 1.96 | M25: =IF(L25="","kein Preis",IF(K25<>"","eigener Preis",IF(C25<>"","Händler",IF(IF(Übersicht!$B$4="NH",H25,I25)<Übersicht!$B$6,"dünn","")))) | N25: https://ahledger.com/items/10939-greater-magic-essence
A26: Lesser Astral Essence | B26: VZ | D26: 6.04 | E26: 5.79 | F26: 9.42 | G26: 8.11 | H26: 681 | I26: 404 | J26: 30.09. | L26: =IF(K26<>"",K26,IF(C26<>"",C26,IF(Übersicht!$B$4="NH",IF(Übersicht!$B$5="jetzt",IF(D26="","",D26),IF(F26="","",F26)),IF(Übersicht!$B$5="jetzt",IF(E26="","",E26),IF(G26="","",G26))))) -> 6.04 | M26: =IF(L26="","kein Preis",IF(K26<>"","eigener Preis",IF(C26<>"","Händler",IF(IF(Übersicht!$B$4="NH",H26,I26)<Übersicht!$B$6,"dünn","")))) | N26: https://ahledger.com/items/10998-lesser-astral-essence
A27: Greater Astral Essence | B27: VZ | D27: 28.54 | E27: 29.99 | F27: 36.7 | G27: 30.33 | H27: 137 | I27: 102 | J27: 27.09. | L27: =IF(K27<>"",K27,IF(C27<>"",C27,IF(Übersicht!$B$4="NH",IF(Übersicht!$B$5="jetzt",IF(D27="","",D27),IF(F27="","",F27)),IF(Übersicht!$B$5="jetzt",IF(E27="","",E27),IF(G27="","",G27))))) -> 28.54 | M27: =IF(L27="","kein Preis",IF(K27<>"","eigener Preis",IF(C27<>"","Händler",IF(IF(Übersicht!$B$4="NH",H27,I27)<Übersicht!$B$6,"dünn","")))) | N27: https://ahledger.com/items/11082-greater-astral-essence
A28: Lesser Mystic Essence | B28: VZ | D28: 15.96 | E28: 10.99 | F28: 62.09 | G28: 33.56 | H28: 122 | I28: 713 | J28: 12.10. | L28: =IF(K28<>"",K28,IF(C28<>"",C28,IF(Übersicht!$B$4="NH",IF(Übersicht!$B$5="jetzt",IF(D28="","",D28),IF(F28="","",F28)),IF(Übersicht!$B$5="jetzt",IF(E28="","",E28),IF(G28="","",G28))))) -> 15.96 | M28: =IF(L28="","kein Preis",IF(K28<>"","eigener Preis",IF(C28<>"","Händler",IF(IF(Übersicht!$B$4="NH",H28,I28)<Übersicht!$B$6,"dünn","")))) | N28: https://ahledger.com/items/11134-lesser-mystic-essence
A29: Greater Mystic Essence | B29: VZ | D29: 44 | E29: 27.97 | F29: 191.72 | G29: 109.75 | H29: 99 | I29: 110 | J29: 12.10. | L29: =IF(K29<>"",K29,IF(C29<>"",C29,IF(Übersicht!$B$4="NH",IF(Übersicht!$B$5="jetzt",IF(D29="","",D29),IF(F29="","",F29)),IF(Übersicht!$B$5="jetzt",IF(E29="","",E29),IF(G29="","",G29))))) -> 44 | M29: =IF(L29="","kein Preis",IF(K29<>"","eigener Preis",IF(C29<>"","Händler",IF(IF(Übersicht!$B$4="NH",H29,I29)<Übersicht!$B$6,"dünn","")))) | N29: https://ahledger.com/items/11135-greater-mystic-essence
A30: Lesser Nether Essence | B30: VZ | D30: 268.98 | E30: 345.93 | F30: 132.42 | G30: 139.36 | H30: 46 | I30: 67 | J30: 12.10. | L30: =IF(K30<>"",K30,IF(C30<>"",C30,IF(Übersicht!$B$4="NH",IF(Übersicht!$B$5="jetzt",IF(D30="","",D30),IF(F30="","",F30)),IF(Übersicht!$B$5="jetzt",IF(E30="","",E30),IF(G30="","",G30))))) -> 268.98 | M30: =IF(L30="","kein Preis",IF(K30<>"","eigener Preis",IF(C30<>"","Händler",IF(IF(Übersicht!$B$4="NH",H30,I30)<Übersicht!$B$6,"dünn","")))) -> dünn | N30: https://ahledger.com/items/11174-lesser-nether-essence
A31: Greater Nether Essence | B31: VZ | D31: 800 | E31: 1099 | F31: 439.94 | G31: 412.27 | H31: 17 | I31: 17 | J31: 12.10. | L31: =IF(K31<>"",K31,IF(C31<>"",C31,IF(Übersicht!$B$4="NH",IF(Übersicht!$B$5="jetzt",IF(D31="","",D31),IF(F31="","",F31)),IF(Übersicht!$B$5="jetzt",IF(E31="","",E31),IF(G31="","",G31))))) -> 800 | M31: =IF(L31="","kein Preis",IF(K31<>"","eigener Preis",IF(C31<>"","Händler",IF(IF(Übersicht!$B$4="NH",H31,I31)<Übersicht!$B$6,"dünn","")))) -> dünn | N31: https://ahledger.com/items/11175-greater-nether-essence
A32: Lesser Eternal Essence | B32: VZ | D32: 200 | E32: 65 | F32: 500 | G32: 228.06 | H32: 42 | I32: 16 | J32: 12.10. | L32: =IF(K32<>"",K32,IF(C32<>"",C32,IF(Übersicht!$B$4="NH",IF(Übersicht!$B$5="jetzt",IF(D32="","",D32),IF(F32="","",F32)),IF(Übersicht!$B$5="jetzt",IF(E32="","",E32),IF(G32="","",G32))))) -> 200 | M32: =IF(L32="","kein Preis",IF(K32<>"","eigener Preis",IF(C32<>"","Händler",IF(IF(Übersicht!$B$4="NH",H32,I32)<Übersicht!$B$6,"dünn","")))) -> dünn | N32: https://ahledger.com/items/16202-lesser-eternal-essence
A33: Greater Eternal Essence | B33: VZ | E33: 454 | G33: 1001 | H33: 0 | I33: 12 | J33: 12.10. | L33: =IF(K33<>"",K33,IF(C33<>"",C33,IF(Übersicht!$B$4="NH",IF(Übersicht!$B$5="jetzt",IF(D33="","",D33),IF(F33="","",F33)),IF(Übersicht!$B$5="jetzt",IF(E33="","",E33),IF(G33="","",G33))))) | M33: =IF(L33="","kein Preis",IF(K33<>"","eigener Preis",IF(C33<>"","Händler",IF(IF(Übersicht!$B$4="NH",H33,I33)<Übersicht!$B$6,"dünn","")))) -> kein Preis | N33: https://ahledger.com/items/16203-greater-eternal-essence | O33: NH: keine Zeile
A34: Small Glimmering Shard | B34: VZ | D34: 3.66 | E34: 2.18 | F34: 3.51 | G34: 2.87 | H34: 637 | I34: 1060 | J34: 30.09. | L34: =IF(K34<>"",K34,IF(C34<>"",C34,IF(Übersicht!$B$4="NH",IF(Übersicht!$B$5="jetzt",IF(D34="","",D34),IF(F34="","",F34)),IF(Übersicht!$B$5="jetzt",IF(E34="","",E34),IF(G34="","",G34))))) -> 3.66 | M34: =IF(L34="","kein Preis",IF(K34<>"","eigener Preis",IF(C34<>"","Händler",IF(IF(Übersicht!$B$4="NH",H34,I34)<Übersicht!$B$6,"dünn","")))) | N34: https://ahledger.com/items/10978-small-glimmering-shard
A35: Large Glimmering Shard | B35: VZ | D35: 78.99 | E35: 62 | F35: 111.64 | G35: 85.88 | H35: 121 | I35: 291 | J35: 30.09. | L35: =IF(K35<>"",K35,IF(C35<>"",C35,IF(Übersicht!$B$4="NH",IF(Übersicht!$B$5="jetzt",IF(D35="","",D35),IF(F35="","",F35)),IF(Übersicht!$B$5="jetzt",IF(E35="","",E35),IF(G35="","",G35))))) -> 78.99 | M35: =IF(L35="","kein Preis",IF(K35<>"","eigener Preis",IF(C35<>"","Händler",IF(IF(Übersicht!$B$4="NH",H35,I35)<Übersicht!$B$6,"dünn","")))) | N35: https://ahledger.com/items/11084-large-glimmering-shard
A36: Small Glowing Shard | B36: VZ | D36: 75.99 | E36: 73 | F36: 184.38 | G36: 198.99 | H36: 10 | I36: 7 | J36: 30.09. | L36: =IF(K36<>"",K36,IF(C36<>"",C36,IF(Übersicht!$B$4="NH",IF(Übersicht!$B$5="jetzt",IF(D36="","",D36),IF(F36="","",F36)),IF(Übersicht!$B$5="jetzt",IF(E36="","",E36),IF(G36="","",G36))))) -> 75.99 | M36: =IF(L36="","kein Preis",IF(K36<>"","eigener Preis",IF(C36<>"","Händler",IF(IF(Übersicht!$B$4="NH",H36,I36)<Übersicht!$B$6,"dünn","")))) -> dünn | N36: https://ahledger.com/items/11138-small-glowing-shard
A37: Large Glowing Shard | B37: VZ | D37: 700 | E37: 580.99 | F37: 938.92 | G37: 853.02 | H37: 6 | I37: 33 | J37: 30.09. | L37: =IF(K37<>"",K37,IF(C37<>"",C37,IF(Übersicht!$B$4="NH",IF(Übersicht!$B$5="jetzt",IF(D37="","",D37),IF(F37="","",F37)),IF(Übersicht!$B$5="jetzt",IF(E37="","",E37),IF(G37="","",G37))))) -> 700 | M37: =IF(L37="","kein Preis",IF(K37<>"","eigener Preis",IF(C37<>"","Händler",IF(IF(Übersicht!$B$4="NH",H37,I37)<Übersicht!$B$6,"dünn","")))) -> dünn | N37: https://ahledger.com/items/11139-large-glowing-shard
A38: Small Radiant Shard | B38: VZ | D38: 799.98 | E38: 498 | F38: 592.74 | G38: 918.75 | H38: 33 | I38: 81 | J38: 12.10. | L38: =IF(K38<>"",K38,IF(C38<>"",C38,IF(Übersicht!$B$4="NH",IF(Übersicht!$B$5="jetzt",IF(D38="","",D38),IF(F38="","",F38)),IF(Übersicht!$B$5="jetzt",IF(E38="","",E38),IF(G38="","",G38))))) -> 799.98 | M38: =IF(L38="","kein Preis",IF(K38<>"","eigener Preis",IF(C38<>"","Händler",IF(IF(Übersicht!$B$4="NH",H38,I38)<Übersicht!$B$6,"dünn","")))) -> dünn | N38: https://ahledger.com/items/11177-small-radiant-shard
A39: Large Radiant Shard | B39: VZ | D39: 1149 | E39: 1099 | F39: 1025 | G39: 1449 | H39: 16 | I39: 77 | J39: 12.10. | L39: =IF(K39<>"",K39,IF(C39<>"",C39,IF(Übersicht!$B$4="NH",IF(Übersicht!$B$5="jetzt",IF(D39="","",D39),IF(F39="","",F39)),IF(Übersicht!$B$5="jetzt",IF(E39="","",E39),IF(G39="","",G39))))) -> 1149 | M39: =IF(L39="","kein Preis",IF(K39<>"","eigener Preis",IF(C39<>"","Händler",IF(IF(Übersicht!$B$4="NH",H39,I39)<Übersicht!$B$6,"dünn","")))) -> dünn | N39: https://ahledger.com/items/11178-large-radiant-shard
A40: Small Brilliant Shard | B40: VZ | D40: 488 | E40: 375 | F40: 700 | G40: 465.05 | H40: 4 | I40: 4 | J40: 12.10. | L40: =IF(K40<>"",K40,IF(C40<>"",C40,IF(Übersicht!$B$4="NH",IF(Übersicht!$B$5="jetzt",IF(D40="","",D40),IF(F40="","",F40)),IF(Übersicht!$B$5="jetzt",IF(E40="","",E40),IF(G40="","",G40))))) -> 488 | M40: =IF(L40="","kein Preis",IF(K40<>"","eigener Preis",IF(C40<>"","Händler",IF(IF(Übersicht!$B$4="NH",H40,I40)<Übersicht!$B$6,"dünn","")))) -> dünn | N40: https://ahledger.com/items/14343-small-brilliant-shard
A41: Large Brilliant Shard | B41: VZ | E41: 5001 | G41: 5001 | H41: 0 | I41: 1 | J41: 10.10. | L41: =IF(K41<>"",K41,IF(C41<>"",C41,IF(Übersicht!$B$4="NH",IF(Übersicht!$B$5="jetzt",IF(D41="","",D41),IF(F41="","",F41)),IF(Übersicht!$B$5="jetzt",IF(E41="","",E41),IF(G41="","",G41))))) | M41: =IF(L41="","kein Preis",IF(K41<>"","eigener Preis",IF(C41<>"","Händler",IF(IF(Übersicht!$B$4="NH",H41,I41)<Übersicht!$B$6,"dünn","")))) -> kein Preis | N41: https://ahledger.com/items/14344-large-brilliant-shard | O41: PH: 1 Stück
A42: Copper Rod | B42: VZ | H42: 0 | I42: 0 | J42: – | L42: =IF(K42<>"",K42,IF(C42<>"",C42,IF(Übersicht!$B$4="NH",IF(Übersicht!$B$5="jetzt",IF(D42="","",D42),IF(F42="","",F42)),IF(Übersicht!$B$5="jetzt",IF(E42="","",E42),IF(G42="","",G42))))) | M42: =IF(L42="","kein Preis",IF(K42<>"","eigener Preis",IF(C42<>"","Händler",IF(IF(Übersicht!$B$4="NH",H42,I42)<Übersicht!$B$6,"dünn","")))) -> kein Preis | N42: https://www.wow-professions.com/forever/enchanting-leveling-guide | O42: Händlerware, Preis nicht belegt
A43: Silver Rod | B43: VZ | D43: 19 | E43: 20 | F43: 2 | G43: 2 | H43: 121 | I43: 6 | J43: 02.10. | L43: =IF(K43<>"",K43,IF(C43<>"",C43,IF(Übersicht!$B$4="NH",IF(Übersicht!$B$5="jetzt",IF(D43="","",D43),IF(F43="","",F43)),IF(Übersicht!$B$5="jetzt",IF(E43="","",E43),IF(G43="","",G43))))) -> 19 | M43: =IF(L43="","kein Preis",IF(K43<>"","eigener Preis",IF(C43<>"","Händler",IF(IF(Übersicht!$B$4="NH",H43,I43)<Übersicht!$B$6,"dünn","")))) | N43: https://ahledger.com/items/6338-silver-rod | O43: Schmiedekunst
A44: Golden Rod | B44: VZ | D44: 8 | E44: 10 | F44: 11.08 | G44: 8.86 | H44: 32 | I44: 124 | J44: 12.10. | L44: =IF(K44<>"",K44,IF(C44<>"",C44,IF(Übersicht!$B$4="NH",IF(Übersicht!$B$5="jetzt",IF(D44="","",D44),IF(F44="","",F44)),IF(Übersicht!$B$5="jetzt",IF(E44="","",E44),IF(G44="","",G44))))) -> 8 | M44: =IF(L44="","kein Preis",IF(K44<>"","eigener Preis",IF(C44<>"","Händler",IF(IF(Übersicht!$B$4="NH",H44,I44)<Übersicht!$B$6,"dünn","")))) -> dünn | N44: https://ahledger.com/items/11128-golden-rod | O44: Schmiedekunst
A45: Truesilver Rod | B45: VZ | D45: 85 | E45: 105 | F45: 130.97 | G45: 190.04 | H45: 26 | I45: 71 | J45: 12.10. | L45: =IF(K45<>"",K45,IF(C45<>"",C45,IF(Übersicht!$B$4="NH",IF(Übersicht!$B$5="jetzt",IF(D45="","",D45),IF(F45="","",F45)),IF(Übersicht!$B$5="jetzt",IF(E45="","",E45),IF(G45="","",G45))))) -> 85 | M45: =IF(L45="","kein Preis",IF(K45<>"","eigener Preis",IF(C45<>"","Händler",IF(IF(Übersicht!$B$4="NH",H45,I45)<Übersicht!$B$6,"dünn","")))) -> dünn | N45: https://ahledger.com/items/11144-truesilver-rod | O45: Schmiedekunst
A46: Arcanite Rod | B46: VZ | H46: 0 | I46: 0 | J46: keine Scans | L46: =IF(K46<>"",K46,IF(C46<>"",C46,IF(Übersicht!$B$4="NH",IF(Übersicht!$B$5="jetzt",IF(D46="","",D46),IF(F46="","",F46)),IF(Übersicht!$B$5="jetzt",IF(E46="","",E46),IF(G46="","",G46))))) | M46: =IF(L46="","kein Preis",IF(K46<>"","eigener Preis",IF(C46<>"","Händler",IF(IF(Übersicht!$B$4="NH",H46,I46)<Übersicht!$B$6,"dünn","")))) -> kein Preis | N46: https://ahledger.com/items/16206-arcanite-rod | O46: Schmiedekunst, in der Beta kein Preis
A47: Iridescent Pearl | B47: VZ | D47: 304.5 | E47: 280.89 | F47: 397.07 | G47: 318.49 | H47: 23 | I47: 42 | J47: 30.09. | L47: =IF(K47<>"",K47,IF(C47<>"",C47,IF(Übersicht!$B$4="NH",IF(Übersicht!$B$5="jetzt",IF(D47="","",D47),IF(F47="","",F47)),IF(Übersicht!$B$5="jetzt",IF(E47="","",E47),IF(G47="","",G47))))) -> 304.5 | M47: =IF(L47="","kein Preis",IF(K47<>"","eigener Preis",IF(C47<>"","Händler",IF(IF(Übersicht!$B$4="NH",H47,I47)<Übersicht!$B$6,"dünn","")))) -> dünn | N47: https://ahledger.com/items/5500-iridescent-pearl
A48: Black Pearl | B48: VZ | D48: 1000 | E48: 848.99 | F48: 744.98 | G48: 747.95 | H48: 12 | I48: 33 | J48: 12.10. | L48: =IF(K48<>"",K48,IF(C48<>"",C48,IF(Übersicht!$B$4="NH",IF(Übersicht!$B$5="jetzt",IF(D48="","",D48),IF(F48="","",F48)),IF(Übersicht!$B$5="jetzt",IF(E48="","",E48),IF(G48="","",G48))))) -> 1000 | M48: =IF(L48="","kein Preis",IF(K48<>"","eigener Preis",IF(C48<>"","Händler",IF(IF(Übersicht!$B$4="NH",H48,I48)<Übersicht!$B$6,"dünn","")))) -> dünn | N48: https://ahledger.com/items/7971-black-pearl
A49: Golden Pearl | B49: VZ | D49: 500 | E49: 276 | F49: 379.52 | G49: 324.84 | H49: 31 | I49: 3 | J49: 10.10. | L49: =IF(K49<>"",K49,IF(C49<>"",C49,IF(Übersicht!$B$4="NH",IF(Übersicht!$B$5="jetzt",IF(D49="","",D49),IF(F49="","",F49)),IF(Übersicht!$B$5="jetzt",IF(E49="","",E49),IF(G49="","",G49))))) -> 500 | M49: =IF(L49="","kein Preis",IF(K49<>"","eigener Preis",IF(C49<>"","Händler",IF(IF(Übersicht!$B$4="NH",H49,I49)<Übersicht!$B$6,"dünn","")))) -> dünn | N49: https://ahledger.com/items/13926-golden-pearl
A50: Shadowgem | B50: VZ | D50: 3.14 | E50: 2.92 | F50: 3.86 | G50: 3.88 | H50: 345 | I50: 446 | J50: 12.10. | L50: =IF(K50<>"",K50,IF(C50<>"",C50,IF(Übersicht!$B$4="NH",IF(Übersicht!$B$5="jetzt",IF(D50="","",D50),IF(F50="","",F50)),IF(Übersicht!$B$5="jetzt",IF(E50="","",E50),IF(G50="","",G50))))) -> 3.14 | M50: =IF(L50="","kein Preis",IF(K50<>"","eigener Preis",IF(C50<>"","Händler",IF(IF(Übersicht!$B$4="NH",H50,I50)<Übersicht!$B$6,"dünn","")))) | N50: https://ahledger.com/items/1210-shadowgem
A51: Simple Wood | B51: VZ | D51: 0.7 | F51: 0.75 | G51: 0.74 | H51: 349 | I51: 0 | J51: 09.10. | L51: =IF(K51<>"",K51,IF(C51<>"",C51,IF(Übersicht!$B$4="NH",IF(Übersicht!$B$5="jetzt",IF(D51="","",D51),IF(F51="","",F51)),IF(Übersicht!$B$5="jetzt",IF(E51="","",E51),IF(G51="","",G51))))) -> 0.7 | M51: =IF(L51="","kein Preis",IF(K51<>"","eigener Preis",IF(C51<>"","Händler",IF(IF(Übersicht!$B$4="NH",H51,I51)<Übersicht!$B$6,"dünn","")))) | N51: https://ahledger.com/items/4470-simple-wood
A52: Purple Lotus | B52: VZ | D52: 2005 | E52: 50.79 | F52: 108.19 | G52: 33.9 | H52: 25 | I52: 60 | J52: 11.10. | L52: =IF(K52<>"",K52,IF(C52<>"",C52,IF(Übersicht!$B$4="NH",IF(Übersicht!$B$5="jetzt",IF(D52="","",D52),IF(F52="","",F52)),IF(Übersicht!$B$5="jetzt",IF(E52="","",E52),IF(G52="","",G52))))) -> 2005 | M52: =IF(L52="","kein Preis",IF(K52<>"","eigener Preis",IF(C52<>"","Händler",IF(IF(Übersicht!$B$4="NH",H52,I52)<Übersicht!$B$6,"dünn","")))) -> dünn | N52: https://ahledger.com/items/8831-purple-lotus | O52: NH-Median weit über 30-Tage-Median
A53: Crystal Vial | B53: VZ | D53: 5 | E53: 9.75 | F53: 4.67 | G53: 3.99 | H53: 26 | I53: 335 | J53: 12.10. | L53: =IF(K53<>"",K53,IF(C53<>"",C53,IF(Übersicht!$B$4="NH",IF(Übersicht!$B$5="jetzt",IF(D53="","",D53),IF(F53="","",F53)),IF(Übersicht!$B$5="jetzt",IF(E53="","",E53),IF(G53="","",G53))))) -> 5 | M53: =IF(L53="","kein Preis",IF(K53<>"","eigener Preis",IF(C53<>"","Händler",IF(IF(Übersicht!$B$4="NH",H53,I53)<Übersicht!$B$6,"dünn","")))) -> dünn | N53: https://ahledger.com/items/8925-crystal-vial

Sheet Bedarf
A1: Bedarf nach Wowhead-Route (Classic Era), Schritt für Schritt. Kosten = Menge × Rechenpreis aus Blatt Preise.
A2: Beruf | B2: Band | C2: Fertigkeit | D2: Rezept | E2: Material | F2: Menge | G2: Preis (s) | H2: Kosten (s) | I2: ohne Preis | J2: dünner Markt | K2: Bemerkung
A3: LW | B3: 1-100 | C3: 1-30 | D3: Light Leather x30 | E3: Ruined Leather Scraps | F3: 90 | G3: =IFERROR(INDEX(Preise!$L$3:$L$53,MATCH(E3,Preise!$A$3:$A$53,0)),"") -> 0.25 | H3: =IF(G3="","",F3*G3) -> 22.5 | I3: =IF(G3="",1,0) -> 0 | J3: =IF(IFERROR(INDEX(Preise!$M$3:$M$53,MATCH(E3,Preise!$A$3:$A$53,0)),"")="dünn",1,0) -> 0
A4: LW | B4: 1-100 | C4: 30-45 | D4: Light Armor Kit x18 | E4: Light Leather | F4: 18 | G4: =IFERROR(INDEX(Preise!$L$3:$L$53,MATCH(E4,Preise!$A$3:$A$53,0)),"") -> 0.5 | H4: =IF(G4="","",F4*G4) -> 9 | I4: =IF(G4="",1,0) -> 0 | J4: =IF(IFERROR(INDEX(Preise!$M$3:$M$53,MATCH(E4,Preise!$A$3:$A$53,0)),"")="dünn",1,0) -> 0
A5: LW | B5: 1-100 | C5: 45-55 | D5: Cured Light Hide x10 | E5: Light Hide | F5: 10 | G5: =IFERROR(INDEX(Preise!$L$3:$L$53,MATCH(E5,Preise!$A$3:$A$53,0)),"") -> 0.69 | H5: =IF(G5="","",F5*G5) -> 6.9 | I5: =IF(G5="",1,0) -> 0 | J5: =IF(IFERROR(INDEX(Preise!$M$3:$M$53,MATCH(E5,Preise!$A$3:$A$53,0)),"")="dünn",1,0) -> 0
A6: LW | B6: 1-100 | C6: 45-55 | D6: ↳ Cured Light Hide x10 | E6: Salt | F6: 10 | G6: =IFERROR(INDEX(Preise!$L$3:$L$53,MATCH(E6,Preise!$A$3:$A$53,0)),"") -> 0.5 | H6: =IF(G6="","",F6*G6) -> 5 | I6: =IF(G6="",1,0) -> 0 | J6: =IF(IFERROR(INDEX(Preise!$M$3:$M$53,MATCH(E6,Preise!$A$3:$A$53,0)),"")="dünn",1,0) -> 0
A7: LW | B7: 1-100 | C7: 55-85 | D7: Embossed Leather Gloves x30 | E7: Light Leather | F7: 90 | G7: =IFERROR(INDEX(Preise!$L$3:$L$53,MATCH(E7,Preise!$A$3:$A$53,0)),"") -> 0.5 | H7: =IF(G7="","",F7*G7) -> 45 | I7: =IF(G7="",1,0) -> 0 | J7: =IF(IFERROR(INDEX(Preise!$M$3:$M$53,MATCH(E7,Preise!$A$3:$A$53,0)),"")="dünn",1,0) -> 0 | K7: in Forever grün (entzauberbar)
A8: LW | B8: 1-100 | C8: 55-85 | D8: ↳ Embossed Leather Gloves x30 | E8: Coarse Thread | F8: 60 | G8: =IFERROR(INDEX(Preise!$L$3:$L$53,MATCH(E8,Preise!$A$3:$A$53,0)),"") -> 0.1 | H8: =IF(G8="","",F8*G8) -> 6 | I8: =IF(G8="",1,0) -> 0 | J8: =IF(IFERROR(INDEX(Preise!$M$3:$M$53,MATCH(E8,Preise!$A$3:$A$53,0)),"")="dünn",1,0) -> 0
A9: LW | B9: 1-100 | C9: 85-100 | D9: Fine Leather Belt x15 (aufheben) | E9: Light Leather | F9: 90 | G9: =IFERROR(INDEX(Preise!$L$3:$L$53,MATCH(E9,Preise!$A$3:$A$53,0)),"") -> 0.5 | H9: =IF(G9="","",F9*G9) -> 45 | I9: =IF(G9="",1,0) -> 0 | J9: =IF(IFERROR(INDEX(Preise!$M$3:$M$53,MATCH(E9,Preise!$A$3:$A$53,0)),"")="dünn",1,0) -> 0 | K9: werden bei 135-150 verbraucht
A10: LW | B10: 1-100 | C10: 85-100 | D10: ↳ Fine Leather Belt x15 (aufheben) | E10: Coarse Thread | F10: 30 | G10: =IFERROR(INDEX(Preise!$L$3:$L$53,MATCH(E10,Preise!$A$3:$A$53,0)),"") -> 0.1 | H10: =IF(G10="","",F10*G10) -> 3 | I10: =IF(G10="",1,0) -> 0 | J10: =IF(IFERROR(INDEX(Preise!$M$3:$M$53,MATCH(E10,Preise!$A$3:$A$53,0)),"")="dünn",1,0) -> 0
A11: LW | B11: 100-150 | C11: 100-115 | D11: Cured Medium Hide x15 (aufheben) | E11: Medium Hide | F11: 15 | G11: =IFERROR(INDEX(Preise!$L$3:$L$53,MATCH(E11,Preise!$A$3:$A$53,0)),"") -> 8.88 | H11: =IF(G11="","",F11*G11) -> 133.2 | I11: =IF(G11="",1,0) -> 0 | J11: =IF(IFERROR(INDEX(Preise!$M$3:$M$53,MATCH(E11,Preise!$A$3:$A$53,0)),"")="dünn",1,0) -> 0 | K11: werden bei 135-150 verbraucht
A12: LW | B12: 100-150 | C12: 100-115 | D12: ↳ Cured Medium Hide x15 (aufheben) | E12: Salt | F12: 15 | G12: =IFERROR(INDEX(Preise!$L$3:$L$53,MATCH(E12,Preise!$A$3:$A$53,0)),"") -> 0.5 | H12: =IF(G12="","",F12*G12) -> 7.5 | I12: =IF(G12="",1,0) -> 0 | J12: =IF(IFERROR(INDEX(Preise!$M$3:$M$53,MATCH(E12,Preise!$A$3:$A$53,0)),"")="dünn",1,0) -> 0
A13: LW | B13: 100-150 | C13: 115-125 | D13: Dark Leather Boots x10 | E13: Medium Leather | F13: 40 | G13: =IFERROR(INDEX(Preise!$L$3:$L$53,MATCH(E13,Preise!$A$3:$A$53,0)),"") -> 1.91 | H13: =IF(G13="","",F13*G13) -> 76.4 | I13: =IF(G13="",1,0) -> 0 | J13: =IF(IFERROR(INDEX(Preise!$M$3:$M$53,MATCH(E13,Preise!$A$3:$A$53,0)),"")="dünn",1,0) -> 0
A14: LW | B14: 100-150 | C14: 115-125 | D14: ↳ Dark Leather Boots x10 | E14: Fine Thread | F14: 20 | G14: =IFERROR(INDEX(Preise!$L$3:$L$53,MATCH(E14,Preise!$A$3:$A$53,0)),"") -> 1 | H14: =IF(G14="","",F14*G14) -> 20 | I14: =IF(G14="",1,0) -> 0 | J14: =IF(IFERROR(INDEX(Preise!$M$3:$M$53,MATCH(E14,Preise!$A$3:$A$53,0)),"")="dünn",1,0) -> 0
A15: LW | B15: 100-150 | C15: 115-125 | D15: ↳ Dark Leather Boots x10 | E15: Gray Dye | F15: 10 | G15: =IFERROR(INDEX(Preise!$L$3:$L$53,MATCH(E15,Preise!$A$3:$A$53,0)),"") -> 3.5 | H15: =IF(G15="","",F15*G15) -> 35 | I15: =IF(G15="",1,0) -> 0 | J15: =IF(IFERROR(INDEX(Preise!$M$3:$M$53,MATCH(E15,Preise!$A$3:$A$53,0)),"")="dünn",1,0) -> 0
A16: LW | B16: 100-150 | C16: 125-135 | D16: Dark Leather Boots x12 | E16: Medium Leather | F16: 48 | G16: =IFERROR(INDEX(Preise!$L$3:$L$53,MATCH(E16,Preise!$A$3:$A$53,0)),"") -> 1.91 | H16: =IF(G16="","",F16*G16) -> 91.68 | I16: =IF(G16="",1,0) -> 0 | J16: =IF(IFERROR(INDEX(Preise!$M$3:$M$53,MATCH(E16,Preise!$A$3:$A$53,0)),"")="dünn",1,0) -> 0
A17: LW | B17: 100-150 | C17: 125-135 | D17: ↳ Dark Leather Boots x12 | E17: Fine Thread | F17: 24 | G17: =IFERROR(INDEX(Preise!$L$3:$L$53,MATCH(E17,Preise!$A$3:$A$53,0)),"") -> 1 | H17: =IF(G17="","",F17*G17) -> 24 | I17: =IF(G17="",1,0) -> 0 | J17: =IF(IFERROR(INDEX(Preise!$M$3:$M$53,MATCH(E17,Preise!$A$3:$A$53,0)),"")="dünn",1,0) -> 0
A18: LW | B18: 100-150 | C18: 125-135 | D18: ↳ Dark Leather Boots x12 | E18: Gray Dye | F18: 12 | G18: =IFERROR(INDEX(Preise!$L$3:$L$53,MATCH(E18,Preise!$A$3:$A$53,0)),"") -> 3.5 | H18: =IF(G18="","",F18*G18) -> 42 | I18: =IF(G18="",1,0) -> 0 | J18: =IF(IFERROR(INDEX(Preise!$M$3:$M$53,MATCH(E18,Preise!$A$3:$A$53,0)),"")="dünn",1,0) -> 0
A19: LW | B19: 100-150 | C19: 135-150 | D19: Dark Leather Belt x15 (+15 Fine Leather Belt, +15 Cured Medium Hide) | E19: Fine Thread | F19: 30 | G19: =IFERROR(INDEX(Preise!$L$3:$L$53,MATCH(E19,Preise!$A$3:$A$53,0)),"") -> 1 | H19: =IF(G19="","",F19*G19) -> 30 | I19: =IF(G19="",1,0) -> 0 | J19: =IF(IFERROR(INDEX(Preise!$M$3:$M$53,MATCH(E19,Preise!$A$3:$A$53,0)),"")="dünn",1,0) -> 0
A20: LW | B20: 100-150 | C20: 135-150 | D20: ↳ Dark Leather Belt x15 (+15 Fine Leather Belt, +15 Cured Medium Hide) | E20: Gray Dye | F20: 15 | G20: =IFERROR(INDEX(Preise!$L$3:$L$53,MATCH(E20,Preise!$A$3:$A$53,0)),"") -> 3.5 | H20: =IF(G20="","",F20*G20) -> 52.5 | I20: =IF(G20="",1,0) -> 0 | J20: =IF(IFERROR(INDEX(Preise!$M$3:$M$53,MATCH(E20,Preise!$A$3:$A$53,0)),"")="dünn",1,0) -> 0
A21: LW | B21: 150-200 | C21: 150-155 | D21: Heavy Leather x5 (aufheben) | E21: Medium Leather | F21: 25 | G21: =IFERROR(INDEX(Preise!$L$3:$L$53,MATCH(E21,Preise!$A$3:$A$53,0)),"") -> 1.91 | H21: =IF(G21="","",F21*G21) -> 47.75 | I21: =IF(G21="",1,0) -> 0 | J21: =IF(IFERROR(INDEX(Preise!$M$3:$M$53,MATCH(E21,Preise!$A$3:$A$53,0)),"")="dünn",1,0) -> 0 | K21: Wowhead-Liste kauft trotzdem 230 Heavy Leather
A22: LW | B22: 150-200 | C22: 155-160 | D22: Cured Heavy Hide x5 (aufheben) | E22: Heavy Hide | F22: 5 | G22: =IFERROR(INDEX(Preise!$L$3:$L$53,MATCH(E22,Preise!$A$3:$A$53,0)),"") -> 35.4 | H22: =IF(G22="","",F22*G22) -> 177 | I22: =IF(G22="",1,0) -> 0 | J22: =IF(IFERROR(INDEX(Preise!$M$3:$M$53,MATCH(E22,Preise!$A$3:$A$53,0)),"")="dünn",1,0) -> 0
A23: LW | B23: 150-200 | C23: 155-160 | D23: ↳ Cured Heavy Hide x5 (aufheben) | E23: Salt | F23: 15 | G23: =IFERROR(INDEX(Preise!$L$3:$L$53,MATCH(E23,Preise!$A$3:$A$53,0)),"") -> 0.5 | H23: =IF(G23="","",F23*G23) -> 7.5 | I23: =IF(G23="",1,0) -> 0 | J23: =IF(IFERROR(INDEX(Preise!$M$3:$M$53,MATCH(E23,Preise!$A$3:$A$53,0)),"")="dünn",1,0) -> 0
A24: LW | B24: 150-200 | C24: 160-180 | D24: Heavy Armor Kit x22 | E24: Heavy Leather | F24: 110 | G24: =IFERROR(INDEX(Preise!$L$3:$L$53,MATCH(E24,Preise!$A$3:$A$53,0)),"") -> 11.98 | H24: =IF(G24="","",F24*G24) -> 1317.8 | I24: =IF(G24="",1,0) -> 0 | J24: =IF(IFERROR(INDEX(Preise!$M$3:$M$53,MATCH(E24,Preise!$A$3:$A$53,0)),"")="dünn",1,0) -> 0
A25: LW | B25: 150-200 | C25: 160-180 | D25: ↳ Heavy Armor Kit x22 | E25: Fine Thread | F25: 22 | G25: =IFERROR(INDEX(Preise!$L$3:$L$53,MATCH(E25,Preise!$A$3:$A$53,0)),"") -> 1 | H25: =IF(G25="","",F25*G25) -> 22 | I25: =IF(G25="",1,0) -> 0 | J25: =IF(IFERROR(INDEX(Preise!$M$3:$M$53,MATCH(E25,Preise!$A$3:$A$53,0)),"")="dünn",1,0) -> 0
A26: LW | B26: 150-200 | C26: 180-190 | D26: Barbaric Shoulders x10 (+10 Cured Heavy Hide) | E26: Heavy Leather | F26: 80 | G26: =IFERROR(INDEX(Preise!$L$3:$L$53,MATCH(E26,Preise!$A$3:$A$53,0)),"") -> 11.98 | H26: =IF(G26="","",F26*G26) -> 958.4 | I26: =IF(G26="",1,0) -> 0 | J26: =IF(IFERROR(INDEX(Preise!$M$3:$M$53,MATCH(E26,Preise!$A$3:$A$53,0)),"")="dünn",1,0) -> 0
A27: LW | B27: 150-200 | C27: 180-190 | D27: ↳ Barbaric Shoulders x10 (+10 Cured Heavy Hide) | E27: Fine Thread | F27: 20 | G27: =IFERROR(INDEX(Preise!$L$3:$L$53,MATCH(E27,Preise!$A$3:$A$53,0)),"") -> 1 | H27: =IF(G27="","",F27*G27) -> 20 | I27: =IF(G27="",1,0) -> 0 | J27: =IF(IFERROR(INDEX(Preise!$M$3:$M$53,MATCH(E27,Preise!$A$3:$A$53,0)),"")="dünn",1,0) -> 0
A28: LW | B28: 150-200 | C28: 190-200 | D28: Guardian Gloves x10 (+10 Cured Heavy Hide) | E28: Heavy Leather | F28: 40 | G28: =IFERROR(INDEX(Preise!$L$3:$L$53,MATCH(E28,Preise!$A$3:$A$53,0)),"") -> 11.98 | H28: =IF(G28="","",F28*G28) -> 479.2 | I28: =IF(G28="",1,0) -> 0 | J28: =IF(IFERROR(INDEX(Preise!$M$3:$M$53,MATCH(E28,Preise!$A$3:$A$53,0)),"")="dünn",1,0) -> 0
A29: LW | B29: 150-200 | C29: 190-200 | D29: ↳ Guardian Gloves x10 (+10 Cured Heavy Hide) | E29: Silken Thread | F29: 10 | G29: =IFERROR(INDEX(Preise!$L$3:$L$53,MATCH(E29,Preise!$A$3:$A$53,0)),"") -> 5 | H29: =IF(G29="","",F29*G29) -> 50 | I29: =IF(G29="",1,0) -> 0 | J29: =IF(IFERROR(INDEX(Preise!$M$3:$M$53,MATCH(E29,Preise!$A$3:$A$53,0)),"")="dünn",1,0) -> 0
A30: LW | B30: 150-200 | C30: Korrektur | D30: Cured Heavy Hide x15 (fehlen in der Route: 20 gebraucht, 5 hergestellt) | E30: Heavy Hide | F30: 15 | G30: =IFERROR(INDEX(Preise!$L$3:$L$53,MATCH(E30,Preise!$A$3:$A$53,0)),"") -> 35.4 | H30: =IF(G30="","",F30*G30) -> 531 | I30: =IF(G30="",1,0) -> 0 | J30: =IF(IFERROR(INDEX(Preise!$M$3:$M$53,MATCH(E30,Preise!$A$3:$A$53,0)),"")="dünn",1,0) -> 0 | K30: von mir ergänzt, nicht von Wowhead
A31: LW | B31: 150-200 | C31: Korrektur | D31: ↳ Cured Heavy Hide x15 (fehlen in der Route: 20 gebraucht, 5 hergestellt) | E31: Salt | F31: 45 | G31: =IFERROR(INDEX(Preise!$L$3:$L$53,MATCH(E31,Preise!$A$3:$A$53,0)),"") -> 0.5 | H31: =IF(G31="","",F31*G31) -> 22.5 | I31: =IF(G31="",1,0) -> 0 | J31: =IF(IFERROR(INDEX(Preise!$M$3:$M$53,MATCH(E31,Preise!$A$3:$A$53,0)),"")="dünn",1,0) -> 0
A32: LW | B32: 200-250 | C32: 200-220 | D32: Thick Armor Kit x20 | E32: Thick Leather | F32: 100 | G32: =IFERROR(INDEX(Preise!$L$3:$L$53,MATCH(E32,Preise!$A$3:$A$53,0)),"") -> 35.79 | H32: =IF(G32="","",F32*G32) -> 3579 | I32: =IF(G32="",1,0) -> 0 | J32: =IF(IFERROR(INDEX(Preise!$M$3:$M$53,MATCH(E32,Preise!$A$3:$A$53,0)),"")="dünn",1,0) -> 0
A33: LW | B33: 200-250 | C33: 200-220 | D33: ↳ Thick Armor Kit x20 | E33: Silken Thread | F33: 20 | G33: =IFERROR(INDEX(Preise!$L$3:$L$53,MATCH(E33,Preise!$A$3:$A$53,0)),"") -> 5 | H33: =IF(G33="","",F33*G33) -> 100 | I33: =IF(G33="",1,0) -> 0 | J33: =IF(IFERROR(INDEX(Preise!$M$3:$M$53,MATCH(E33,Preise!$A$3:$A$53,0)),"")="dünn",1,0) -> 0
A34: LW | B34: 200-250 | C34: 220-230 | D34: Nightscape Headband x11 | E34: Thick Leather | F34: 55 | G34: =IFERROR(INDEX(Preise!$L$3:$L$53,MATCH(E34,Preise!$A$3:$A$53,0)),"") -> 35.79 | H34: =IF(G34="","",F34*G34) -> 1968.45 | I34: =IF(G34="",1,0) -> 0 | J34: =IF(IFERROR(INDEX(Preise!$M$3:$M$53,MATCH(E34,Preise!$A$3:$A$53,0)),"")="dünn",1,0) -> 0 | K34: Wowhead: 2 für Tribal aufheben
A35: LW | B35: 200-250 | C35: 220-230 | D35: ↳ Nightscape Headband x11 | E35: Silken Thread | F35: 22 | G35: =IFERROR(INDEX(Preise!$L$3:$L$53,MATCH(E35,Preise!$A$3:$A$53,0)),"") -> 5 | H35: =IF(G35="","",F35*G35) -> 110 | I35: =IF(G35="",1,0) -> 0 | J35: =IF(IFERROR(INDEX(Preise!$M$3:$M$53,MATCH(E35,Preise!$A$3:$A$53,0)),"")="dünn",1,0) -> 0
A36: LW | B36: 200-250 | C36: 230-250 | D36: Nightscape Pants x20 | E36: Thick Leather | F36: 280 | G36: =IFERROR(INDEX(Preise!$L$3:$L$53,MATCH(E36,Preise!$A$3:$A$53,0)),"") -> 35.79 | H36: =IF(G36="","",F36*G36) -> 10021.2 | I36: =IF(G36="",1,0) -> 0 | J36: =IF(IFERROR(INDEX(Preise!$M$3:$M$53,MATCH(E36,Preise!$A$3:$A$53,0)),"")="dünn",1,0) -> 0 | K36: Wowhead: 2 für Tribal aufheben
A37: LW | B37: 200-250 | C37: 230-250 | D37: ↳ Nightscape Pants x20 | E37: Silken Thread | F37: 80 | G37: =IFERROR(INDEX(Preise!$L$3:$L$53,MATCH(E37,Preise!$A$3:$A$53,0)),"") -> 5 | H37: =IF(G37="","",F37*G37) -> 400 | I37: =IF(G37="",1,0) -> 0 | J37: =IF(IFERROR(INDEX(Preise!$M$3:$M$53,MATCH(E37,Preise!$A$3:$A$53,0)),"")="dünn",1,0) -> 0
A38: LW | B38: 250-300 | C38: 250-260 | D38: Rugged Armor Kit x12 | E38: Rugged Leather | F38: 60 | G38: =IFERROR(INDEX(Preise!$L$3:$L$53,MATCH(E38,Preise!$A$3:$A$53,0)),"") -> 19.02 | H38: =IF(G38="","",F38*G38) -> 1141.2 | I38: =IF(G38="",1,0) -> 0 | J38: =IF(IFERROR(INDEX(Preise!$M$3:$M$53,MATCH(E38,Preise!$A$3:$A$53,0)),"")="dünn",1,0) -> 0
A39: LW | B39: 250-300 | C39: 260-290 | D39: Wicked Leather Gauntlets x32 | E39: Rugged Leather | F39: 256 | G39: =IFERROR(INDEX(Preise!$L$3:$L$53,MATCH(E39,Preise!$A$3:$A$53,0)),"") -> 19.02 | H39: =IF(G39="","",F39*G39) -> 4869.12 | I39: =IF(G39="",1,0) -> 0 | J39: =IF(IFERROR(INDEX(Preise!$M$3:$M$53,MATCH(E39,Preise!$A$3:$A$53,0)),"")="dünn",1,0) -> 0 | K39: Muster vom Händler
A40: LW | B40: 250-300 | C40: 260-290 | D40: ↳ Wicked Leather Gauntlets x32 | E40: Black Dye | F40: 32 | G40: =IFERROR(INDEX(Preise!$L$3:$L$53,MATCH(E40,Preise!$A$3:$A$53,0)),"") -> 10 | H40: =IF(G40="","",F40*G40) -> 320 | I40: =IF(G40="",1,0) -> 0 | J40: =IF(IFERROR(INDEX(Preise!$M$3:$M$53,MATCH(E40,Preise!$A$3:$A$53,0)),"")="dünn",1,0) -> 0
A41: LW | B41: 250-300 | C41: 260-290 | D41: ↳ Wicked Leather Gauntlets x32 | E41: Rune Thread | F41: 32 | G41: =IFERROR(INDEX(Preise!$L$3:$L$53,MATCH(E41,Preise!$A$3:$A$53,0)),"") -> 50 | H41: =IF(G41="","",F41*G41) -> 1600 | I41: =IF(G41="",1,0) -> 0 | J41: =IF(IFERROR(INDEX(Preise!$M$3:$M$53,MATCH(E41,Preise!$A$3:$A$53,0)),"")="dünn",1,0) -> 0
A42: LW | B42: 250-300 | C42: 290-300 | D42: Wicked Leather Headband x10 | E42: Rugged Leather | F42: 120 | G42: =IFERROR(INDEX(Preise!$L$3:$L$53,MATCH(E42,Preise!$A$3:$A$53,0)),"") -> 19.02 | H42: =IF(G42="","",F42*G42) -> 2282.4 | I42: =IF(G42="",1,0) -> 0 | J42: =IF(IFERROR(INDEX(Preise!$M$3:$M$53,MATCH(E42,Preise!$A$3:$A$53,0)),"")="dünn",1,0) -> 0 | K42: Muster: Weltdrop (~2 % laut Wowhead)
A43: LW | B43: 250-300 | C43: 290-300 | D43: ↳ Wicked Leather Headband x10 | E43: Black Dye | F43: 10 | G43: =IFERROR(INDEX(Preise!$L$3:$L$53,MATCH(E43,Preise!$A$3:$A$53,0)),"") -> 10 | H43: =IF(G43="","",F43*G43) -> 100 | I43: =IF(G43="",1,0) -> 0 | J43: =IF(IFERROR(INDEX(Preise!$M$3:$M$53,MATCH(E43,Preise!$A$3:$A$53,0)),"")="dünn",1,0) -> 0
A44: LW | B44: 250-300 | C44: 290-300 | D44: ↳ Wicked Leather Headband x10 | E44: Rune Thread | F44: 10 | G44: =IFERROR(INDEX(Preise!$L$3:$L$53,MATCH(E44,Preise!$A$3:$A$53,0)),"") -> 50 | H44: =IF(G44="","",F44*G44) -> 500 | I44: =IF(G44="",1,0) -> 0 | J44: =IF(IFERROR(INDEX(Preise!$M$3:$M$53,MATCH(E44,Preise!$A$3:$A$53,0)),"")="dünn",1,0) -> 0
A45: VZ | B45: 1-100 | C45: 1-2 | D45: Runed Copper Rod | E45: Copper Rod | F45: 1 | G45: =IFERROR(INDEX(Preise!$L$3:$L$53,MATCH(E45,Preise!$A$3:$A$53,0)),"") | H45: =IF(G45="","",F45*G45) | I45: =IF(G45="",1,0) -> 1 | J45: =IF(IFERROR(INDEX(Preise!$M$3:$M$53,MATCH(E45,Preise!$A$3:$A$53,0)),"")="dünn",1,0) -> 0 | K45: Forever-Rezept: Copper Rod + Mote of Magic
A46: VZ | B46: 1-100 | C46: 1-2 | D46: ↳ Runed Copper Rod | E46: Strange Dust | F46: 1 | G46: =IFERROR(INDEX(Preise!$L$3:$L$53,MATCH(E46,Preise!$A$3:$A$53,0)),"") -> 0.84 | H46: =IF(G46="","",F46*G46) -> 0.84 | I46: =IF(G46="",1,0) -> 0 | J46: =IF(IFERROR(INDEX(Preise!$M$3:$M$53,MATCH(E46,Preise!$A$3:$A$53,0)),"")="dünn",1,0) -> 0
A47: VZ | B47: 1-100 | C47: 1-2 | D47: ↳ Runed Copper Rod | E47: Lesser Magic Essence | F47: 1 | G47: =IFERROR(INDEX(Preise!$L$3:$L$53,MATCH(E47,Preise!$A$3:$A$53,0)),"") -> 0.69 | H47: =IF(G47="","",F47*G47) -> 0.69 | I47: =IF(G47="",1,0) -> 0 | J47: =IF(IFERROR(INDEX(Preise!$M$3:$M$53,MATCH(E47,Preise!$A$3:$A$53,0)),"")="dünn",1,0) -> 0
A48: VZ | B48: 1-100 | C48: 2-50 | D48: Enchant Bracer - Minor Health x48 | E48: Strange Dust | F48: 48 | G48: =IFERROR(INDEX(Preise!$L$3:$L$53,MATCH(E48,Preise!$A$3:$A$53,0)),"") -> 0.84 | H48: =IF(G48="","",F48*G48) -> 40.32 | I48: =IF(G48="",1,0) -> 0 | J48: =IF(IFERROR(INDEX(Preise!$M$3:$M$53,MATCH(E48,Preise!$A$3:$A$53,0)),"")="dünn",1,0) -> 0 | K48: Rezept nicht in der Forever-Liste von AHledger
A49: VZ | B49: 1-100 | C49: 50-90 | D49: Enchant Bracer - Minor Health x~60 | E49: Strange Dust | F49: 60 | G49: =IFERROR(INDEX(Preise!$L$3:$L$53,MATCH(E49,Preise!$A$3:$A$53,0)),"") -> 0.84 | H49: =IF(G49="","",F49*G49) -> 50.4 | I49: =IF(G49="",1,0) -> 0 | J49: =IF(IFERROR(INDEX(Preise!$M$3:$M$53,MATCH(E49,Preise!$A$3:$A$53,0)),"")="dünn",1,0) -> 0 | K49: Rezept nicht in der Forever-Liste von AHledger
A50: VZ | B50: 1-100 | C50: 90-100 | D50: Enchant Bracer - Minor Stamina x10 | E50: Strange Dust | F50: 30 | G50: =IFERROR(INDEX(Preise!$L$3:$L$53,MATCH(E50,Preise!$A$3:$A$53,0)),"") -> 0.84 | H50: =IF(G50="","",F50*G50) -> 25.2 | I50: =IF(G50="",1,0) -> 0 | J50: =IF(IFERROR(INDEX(Preise!$M$3:$M$53,MATCH(E50,Preise!$A$3:$A$53,0)),"")="dünn",1,0) -> 0
A51: VZ | B51: 100-150 | C51: 100-101 | D51: Runed Silver Rod | E51: Silver Rod | F51: 1 | G51: =IFERROR(INDEX(Preise!$L$3:$L$53,MATCH(E51,Preise!$A$3:$A$53,0)),"") -> 19 | H51: =IF(G51="","",F51*G51) -> 19 | I51: =IF(G51="",1,0) -> 0 | J51: =IF(IFERROR(INDEX(Preise!$M$3:$M$53,MATCH(E51,Preise!$A$3:$A$53,0)),"")="dünn",1,0) -> 0 | K51: Shadowgem fehlt in Wowheads Einkaufsliste
A52: VZ | B52: 100-150 | C52: 100-101 | D52: ↳ Runed Silver Rod | E52: Strange Dust | F52: 6 | G52: =IFERROR(INDEX(Preise!$L$3:$L$53,MATCH(E52,Preise!$A$3:$A$53,0)),"") -> 0.84 | H52: =IF(G52="","",F52*G52) -> 5.04 | I52: =IF(G52="",1,0) -> 0 | J52: =IF(IFERROR(INDEX(Preise!$M$3:$M$53,MATCH(E52,Preise!$A$3:$A$53,0)),"")="dünn",1,0) -> 0
A53: VZ | B53: 100-150 | C53: 100-101 | D53: ↳ Runed Silver Rod | E53: Greater Magic Essence | F53: 3 | G53: =IFERROR(INDEX(Preise!$L$3:$L$53,MATCH(E53,Preise!$A$3:$A$53,0)),"") -> 1.96 | H53: =IF(G53="","",F53*G53) -> 5.88 | I53: =IF(G53="",1,0) -> 0 | J53: =IF(IFERROR(INDEX(Preise!$M$3:$M$53,MATCH(E53,Preise!$A$3:$A$53,0)),"")="dünn",1,0) -> 0
A54: VZ | B54: 100-150 | C54: 100-101 | D54: ↳ Runed Silver Rod | E54: Shadowgem | F54: 1 | G54: =IFERROR(INDEX(Preise!$L$3:$L$53,MATCH(E54,Preise!$A$3:$A$53,0)),"") -> 3.14 | H54: =IF(G54="","",F54*G54) -> 3.14 | I54: =IF(G54="",1,0) -> 0 | J54: =IF(IFERROR(INDEX(Preise!$M$3:$M$53,MATCH(E54,Preise!$A$3:$A$53,0)),"")="dünn",1,0) -> 0
A55: VZ | B55: 100-150 | C55: 101-110 | D55: Greater Magic Wand x9 | E55: Simple Wood | F55: 9 | G55: =IFERROR(INDEX(Preise!$L$3:$L$53,MATCH(E55,Preise!$A$3:$A$53,0)),"") -> 0.7 | H55: =IF(G55="","",F55*G55) -> 6.3 | I55: =IF(G55="",1,0) -> 0 | J55: =IF(IFERROR(INDEX(Preise!$M$3:$M$53,MATCH(E55,Preise!$A$3:$A$53,0)),"")="dünn",1,0) -> 0
A56: VZ | B56: 100-150 | C56: 101-110 | D56: ↳ Greater Magic Wand x9 | E56: Greater Magic Essence | F56: 9 | G56: =IFERROR(INDEX(Preise!$L$3:$L$53,MATCH(E56,Preise!$A$3:$A$53,0)),"") -> 1.96 | H56: =IF(G56="","",F56*G56) -> 17.64 | I56: =IF(G56="",1,0) -> 0 | J56: =IF(IFERROR(INDEX(Preise!$M$3:$M$53,MATCH(E56,Preise!$A$3:$A$53,0)),"")="dünn",1,0) -> 0
A57: VZ | B57: 100-150 | C57: 110-135 | D57: Enchant Cloak - Minor Agility x25 | E57: Lesser Astral Essence | F57: 25 | G57: =IFERROR(INDEX(Preise!$L$3:$L$53,MATCH(E57,Preise!$A$3:$A$53,0)),"") -> 6.04 | H57: =IF(G57="","",F57*G57) -> 151 | I57: =IF(G57="",1,0) -> 0 | J57: =IF(IFERROR(INDEX(Preise!$M$3:$M$53,MATCH(E57,Preise!$A$3:$A$53,0)),"")="dünn",1,0) -> 0 | K57: Formel: Händler Stonetalon (Horde)
A58: VZ | B58: 100-150 | C58: 135-155 | D58: Enchant Bracer - Lesser Stamina x20 | E58: Soul Dust | F58: 40 | G58: =IFERROR(INDEX(Preise!$L$3:$L$53,MATCH(E58,Preise!$A$3:$A$53,0)),"") -> 7.21 | H58: =IF(G58="","",F58*G58) -> 288.4 | I58: =IF(G58="",1,0) -> 0 | J58: =IF(IFERROR(INDEX(Preise!$M$3:$M$53,MATCH(E58,Preise!$A$3:$A$53,0)),"")="dünn",1,0) -> 0
A59: VZ | B59: 150-200 | C59: 155-156 | D59: Runed Golden Rod | E59: Golden Rod | F59: 1 | G59: =IFERROR(INDEX(Preise!$L$3:$L$53,MATCH(E59,Preise!$A$3:$A$53,0)),"") -> 8 | H59: =IF(G59="","",F59*G59) -> 8 | I59: =IF(G59="",1,0) -> 0 | J59: =IF(IFERROR(INDEX(Preise!$M$3:$M$53,MATCH(E59,Preise!$A$3:$A$53,0)),"")="dünn",1,0) -> 1
A60: VZ | B60: 150-200 | C60: 155-156 | D60: ↳ Runed Golden Rod | E60: Iridescent Pearl | F60: 1 | G60: =IFERROR(INDEX(Preise!$L$3:$L$53,MATCH(E60,Preise!$A$3:$A$53,0)),"") -> 304.5 | H60: =IF(G60="","",F60*G60) -> 304.5 | I60: =IF(G60="",1,0) -> 0 | J60: =IF(IFERROR(INDEX(Preise!$M$3:$M$53,MATCH(E60,Preise!$A$3:$A$53,0)),"")="dünn",1,0) -> 1
A61: VZ | B61: 150-200 | C61: 155-156 | D61: ↳ Runed Golden Rod | E61: Greater Astral Essence | F61: 2 | G61: =IFERROR(INDEX(Preise!$L$3:$L$53,MATCH(E61,Preise!$A$3:$A$53,0)),"") -> 28.54 | H61: =IF(G61="","",F61*G61) -> 57.08 | I61: =IF(G61="",1,0) -> 0 | J61: =IF(IFERROR(INDEX(Preise!$M$3:$M$53,MATCH(E61,Preise!$A$3:$A$53,0)),"")="dünn",1,0) -> 0
A62: VZ | B62: 150-200 | C62: 155-156 | D62: ↳ Runed Golden Rod | E62: Soul Dust | F62: 2 | G62: =IFERROR(INDEX(Preise!$L$3:$L$53,MATCH(E62,Preise!$A$3:$A$53,0)),"") -> 7.21 | H62: =IF(G62="","",F62*G62) -> 14.42 | I62: =IF(G62="",1,0) -> 0 | J62: =IF(IFERROR(INDEX(Preise!$M$3:$M$53,MATCH(E62,Preise!$A$3:$A$53,0)),"")="dünn",1,0) -> 0
A63: VZ | B63: 150-200 | C63: 156-185 | D63: Enchant Bracer - Lesser Strength x~40 | E63: Soul Dust | F63: 80 | G63: =IFERROR(INDEX(Preise!$L$3:$L$53,MATCH(E63,Preise!$A$3:$A$53,0)),"") -> 7.21 | H63: =IF(G63="","",F63*G63) -> 576.8 | I63: =IF(G63="",1,0) -> 0 | J63: =IF(IFERROR(INDEX(Preise!$M$3:$M$53,MATCH(E63,Preise!$A$3:$A$53,0)),"")="dünn",1,0) -> 0 | K63: Formel: Händler Stonetalon (Horde)
A64: VZ | B64: 150-200 | C64: 185-200 | D64: Enchant Bracer - Strength x15 | E64: Vision Dust | F64: 15 | G64: =IFERROR(INDEX(Preise!$L$3:$L$53,MATCH(E64,Preise!$A$3:$A$53,0)),"") -> 19.71 | H64: =IF(G64="","",F64*G64) -> 295.65 | I64: =IF(G64="",1,0) -> 0 | J64: =IF(IFERROR(INDEX(Preise!$M$3:$M$53,MATCH(E64,Preise!$A$3:$A$53,0)),"")="dünn",1,0) -> 0
A65: VZ | B65: 200-250 | C65: 200-201 | D65: Runed Truesilver Rod | E65: Truesilver Rod | F65: 1 | G65: =IFERROR(INDEX(Preise!$L$3:$L$53,MATCH(E65,Preise!$A$3:$A$53,0)),"") -> 85 | H65: =IF(G65="","",F65*G65) -> 85 | I65: =IF(G65="",1,0) -> 0 | J65: =IF(IFERROR(INDEX(Preise!$M$3:$M$53,MATCH(E65,Preise!$A$3:$A$53,0)),"")="dünn",1,0) -> 1 | K65: Artisan-Lehrer ab 200: Annora, Uldaman
A66: VZ | B66: 200-250 | C66: 200-201 | D66: ↳ Runed Truesilver Rod | E66: Black Pearl | F66: 1 | G66: =IFERROR(INDEX(Preise!$L$3:$L$53,MATCH(E66,Preise!$A$3:$A$53,0)),"") -> 1000 | H66: =IF(G66="","",F66*G66) -> 1000 | I66: =IF(G66="",1,0) -> 0 | J66: =IF(IFERROR(INDEX(Preise!$M$3:$M$53,MATCH(E66,Preise!$A$3:$A$53,0)),"")="dünn",1,0) -> 1
A67: VZ | B67: 200-250 | C67: 200-201 | D67: ↳ Runed Truesilver Rod | E67: Greater Mystic Essence | F67: 2 | G67: =IFERROR(INDEX(Preise!$L$3:$L$53,MATCH(E67,Preise!$A$3:$A$53,0)),"") -> 44 | H67: =IF(G67="","",F67*G67) -> 88 | I67: =IF(G67="",1,0) -> 0 | J67: =IF(IFERROR(INDEX(Preise!$M$3:$M$53,MATCH(E67,Preise!$A$3:$A$53,0)),"")="dünn",1,0) -> 0
A68: VZ | B68: 200-250 | C68: 200-201 | D68: ↳ Runed Truesilver Rod | E68: Vision Dust | F68: 2 | G68: =IFERROR(INDEX(Preise!$L$3:$L$53,MATCH(E68,Preise!$A$3:$A$53,0)),"") -> 19.71 | H68: =IF(G68="","",F68*G68) -> 39.42 | I68: =IF(G68="",1,0) -> 0 | J68: =IF(IFERROR(INDEX(Preise!$M$3:$M$53,MATCH(E68,Preise!$A$3:$A$53,0)),"")="dünn",1,0) -> 0
A69: VZ | B69: 200-250 | C69: 201-220 | D69: Enchant Bracer - Strength x~25 | E69: Vision Dust | F69: 25 | G69: =IFERROR(INDEX(Preise!$L$3:$L$53,MATCH(E69,Preise!$A$3:$A$53,0)),"") -> 19.71 | H69: =IF(G69="","",F69*G69) -> 492.75 | I69: =IF(G69="",1,0) -> 0 | J69: =IF(IFERROR(INDEX(Preise!$M$3:$M$53,MATCH(E69,Preise!$A$3:$A$53,0)),"")="dünn",1,0) -> 0
A70: VZ | B70: 200-250 | C70: 220-225 | D70: Enchant Cloak - Greater Defense x5 | E70: Vision Dust | F70: 15 | G70: =IFERROR(INDEX(Preise!$L$3:$L$53,MATCH(E70,Preise!$A$3:$A$53,0)),"") -> 19.71 | H70: =IF(G70="","",F70*G70) -> 295.65 | I70: =IF(G70="",1,0) -> 0 | J70: =IF(IFERROR(INDEX(Preise!$M$3:$M$53,MATCH(E70,Preise!$A$3:$A$53,0)),"")="dünn",1,0) -> 0
A71: VZ | B71: 200-250 | C71: 225-230 | D71: Enchant Gloves - Agility x5 | E71: Lesser Nether Essence | F71: 5 | G71: =IFERROR(INDEX(Preise!$L$3:$L$53,MATCH(E71,Preise!$A$3:$A$53,0)),"") -> 268.98 | H71: =IF(G71="","",F71*G71) -> 1344.9 | I71: =IF(G71="",1,0) -> 0 | J71: =IF(IFERROR(INDEX(Preise!$M$3:$M$53,MATCH(E71,Preise!$A$3:$A$53,0)),"")="dünn",1,0) -> 1
A72: VZ | B72: 200-250 | C72: 225-230 | D72: ↳ Enchant Gloves - Agility x5 | E72: Vision Dust | F72: 5 | G72: =IFERROR(INDEX(Preise!$L$3:$L$53,MATCH(E72,Preise!$A$3:$A$53,0)),"") -> 19.71 | H72: =IF(G72="","",F72*G72) -> 98.55 | I72: =IF(G72="",1,0) -> 0 | J72: =IF(IFERROR(INDEX(Preise!$M$3:$M$53,MATCH(E72,Preise!$A$3:$A$53,0)),"")="dünn",1,0) -> 0
A73: VZ | B73: 200-250 | C73: 230-235 | D73: Enchant Boots - Stamina x5 | E73: Vision Dust | F73: 25 | G73: =IFERROR(INDEX(Preise!$L$3:$L$53,MATCH(E73,Preise!$A$3:$A$53,0)),"") -> 19.71 | H73: =IF(G73="","",F73*G73) -> 492.75 | I73: =IF(G73="",1,0) -> 0 | J73: =IF(IFERROR(INDEX(Preise!$M$3:$M$53,MATCH(E73,Preise!$A$3:$A$53,0)),"")="dünn",1,0) -> 0
A74: VZ | B74: 200-250 | C74: 235-250 | D74: Enchant Chest - Superior Health x~25 | E74: Vision Dust | F74: 150 | G74: =IFERROR(INDEX(Preise!$L$3:$L$53,MATCH(E74,Preise!$A$3:$A$53,0)),"") -> 19.71 | H74: =IF(G74="","",F74*G74) -> 2956.5 | I74: =IF(G74="",1,0) -> 0 | J74: =IF(IFERROR(INDEX(Preise!$M$3:$M$53,MATCH(E74,Preise!$A$3:$A$53,0)),"")="dünn",1,0) -> 0 | K74: Rezept nicht in der Forever-Liste von AHledger
A75: VZ | B75: 250-300 | C75: 250-265 | D75: Lesser Mana Oil x~20 | E75: Dream Dust | F75: 60 | G75: =IFERROR(INDEX(Preise!$L$3:$L$53,MATCH(E75,Preise!$A$3:$A$53,0)),"") -> 58 | H75: =IF(G75="","",F75*G75) -> 3480 | I75: =IF(G75="",1,0) -> 0 | J75: =IF(IFERROR(INDEX(Preise!$M$3:$M$53,MATCH(E75,Preise!$A$3:$A$53,0)),"")="dünn",1,0) -> 1 | K75: Formel: Kania, Cenarion Hold (Silithus)
A76: VZ | B76: 250-300 | C76: 250-265 | D76: ↳ Lesser Mana Oil x~20 | E76: Purple Lotus | F76: 40 | G76: =IFERROR(INDEX(Preise!$L$3:$L$53,MATCH(E76,Preise!$A$3:$A$53,0)),"") -> 2005 | H76: =IF(G76="","",F76*G76) -> 80200 | I76: =IF(G76="",1,0) -> 0 | J76: =IF(IFERROR(INDEX(Preise!$M$3:$M$53,MATCH(E76,Preise!$A$3:$A$53,0)),"")="dünn",1,0) -> 1
A77: VZ | B77: 250-300 | C77: 250-265 | D77: ↳ Lesser Mana Oil x~20 | E77: Crystal Vial | F77: 20 | G77: =IFERROR(INDEX(Preise!$L$3:$L$53,MATCH(E77,Preise!$A$3:$A$53,0)),"") -> 5 | H77: =IF(G77="","",F77*G77) -> 100 | I77: =IF(G77="",1,0) -> 0 | J77: =IF(IFERROR(INDEX(Preise!$M$3:$M$53,MATCH(E77,Preise!$A$3:$A$53,0)),"")="dünn",1,0) -> 1
A78: VZ | B78: 250-300 | C78: 265-294 | D78: Enchant Shield - Greater Stamina x~30 | E78: Dream Dust | F78: 300 | G78: =IFERROR(INDEX(Preise!$L$3:$L$53,MATCH(E78,Preise!$A$3:$A$53,0)),"") -> 58 | H78: =IF(G78="","",F78*G78) -> 17400 | I78: =IF(G78="",1,0) -> 0 | J78: =IF(IFERROR(INDEX(Preise!$M$3:$M$53,MATCH(E78,Preise!$A$3:$A$53,0)),"")="dünn",1,0) -> 1 | K78: Formel BoP, Händler Undercity
A79: VZ | B79: 250-300 | C79: 294-295 | D79: Runed Arcanite Rod | E79: Arcanite Rod | F79: 1 | G79: =IFERROR(INDEX(Preise!$L$3:$L$53,MATCH(E79,Preise!$A$3:$A$53,0)),"") | H79: =IF(G79="","",F79*G79) | I79: =IF(G79="",1,0) -> 1 | J79: =IF(IFERROR(INDEX(Preise!$M$3:$M$53,MATCH(E79,Preise!$A$3:$A$53,0)),"")="dünn",1,0) -> 0 | K79: Formel: Moonglade
A80: VZ | B80: 250-300 | C80: 294-295 | D80: ↳ Runed Arcanite Rod | E80: Golden Pearl | F80: 1 | G80: =IFERROR(INDEX(Preise!$L$3:$L$53,MATCH(E80,Preise!$A$3:$A$53,0)),"") -> 500 | H80: =IF(G80="","",F80*G80) -> 500 | I80: =IF(G80="",1,0) -> 0 | J80: =IF(IFERROR(INDEX(Preise!$M$3:$M$53,MATCH(E80,Preise!$A$3:$A$53,0)),"")="dünn",1,0) -> 1
A81: VZ | B81: 250-300 | C81: 294-295 | D81: ↳ Runed Arcanite Rod | E81: Illusion Dust | F81: 10 | G81: =IFERROR(INDEX(Preise!$L$3:$L$53,MATCH(E81,Preise!$A$3:$A$53,0)),"") -> 1000 | H81: =IF(G81="","",F81*G81) -> 10000 | I81: =IF(G81="",1,0) -> 0 | J81: =IF(IFERROR(INDEX(Preise!$M$3:$M$53,MATCH(E81,Preise!$A$3:$A$53,0)),"")="dünn",1,0) -> 1
A82: VZ | B82: 250-300 | C82: 294-295 | D82: ↳ Runed Arcanite Rod | E82: Greater Eternal Essence | F82: 4 | G82: =IFERROR(INDEX(Preise!$L$3:$L$53,MATCH(E82,Preise!$A$3:$A$53,0)),"") | H82: =IF(G82="","",F82*G82) | I82: =IF(G82="",1,0) -> 1 | J82: =IF(IFERROR(INDEX(Preise!$M$3:$M$53,MATCH(E82,Preise!$A$3:$A$53,0)),"")="dünn",1,0) -> 0
A83: VZ | B83: 250-300 | C83: 294-295 | D83: ↳ Runed Arcanite Rod | E83: Small Brilliant Shard | F83: 4 | G83: =IFERROR(INDEX(Preise!$L$3:$L$53,MATCH(E83,Preise!$A$3:$A$53,0)),"") -> 488 | H83: =IF(G83="","",F83*G83) -> 1952 | I83: =IF(G83="",1,0) -> 0 | J83: =IF(IFERROR(INDEX(Preise!$M$3:$M$53,MATCH(E83,Preise!$A$3:$A$53,0)),"")="dünn",1,0) -> 1
A84: VZ | B84: 250-300 | C84: 294-295 | D84: ↳ Runed Arcanite Rod | E84: Large Brilliant Shard | F84: 2 | G84: =IFERROR(INDEX(Preise!$L$3:$L$53,MATCH(E84,Preise!$A$3:$A$53,0)),"") | H84: =IF(G84="","",F84*G84) | I84: =IF(G84="",1,0) -> 1 | J84: =IF(IFERROR(INDEX(Preise!$M$3:$M$53,MATCH(E84,Preise!$A$3:$A$53,0)),"")="dünn",1,0) -> 0
A85: VZ | B85: 250-300 | C85: 295-300 | D85: Enchant Cloak - Superior Defense x5 | E85: Illusion Dust | F85: 40 | G85: =IFERROR(INDEX(Preise!$L$3:$L$53,MATCH(E85,Preise!$A$3:$A$53,0)),"") -> 1000 | H85: =IF(G85="","",F85*G85) -> 40000 | I85: =IF(G85="",1,0) -> 0 | J85: =IF(IFERROR(INDEX(Preise!$M$3:$M$53,MATCH(E85,Preise!$A$3:$A$53,0)),"")="dünn",1,0) -> 1

Sheet Kreislauf
A1: Kreislauf: Was die grünen LW-Teile beim Entzaubern liefern (Forever-Stufen, Tabelle wow-professions) und wie viel vom VZ-Bedarf das deckt
A2: Mengen pro Teil = Chance × Mittelwert der Spanne (Annahme: gleich verteilt). Werte in Silber, Deckung gegen den VZ-Bedarf aus Blatt Bedarf.
A3: Chance Staub | B3: 0.75
A4: Chance Essenz | B4: 0.2
A5: Chance Splitter | B5: 0.04 | C5: 3–5 % laut Tabelle, Mitte genommen
A7: Stufe von | B7: Stufe bis | C7: Staub | D7: Staub min | E7: Staub max | F7: Essenz | G7: Essenz min | H7: Essenz max | I7: Splitter
A8: 1 | B8: 10 | C8: Strange Dust | D8: 1 | E8: 2 | F8: Lesser Magic Essence | G8: 1 | H8: 2 | I8: –
A9: 11 | B9: 15 | C9: Strange Dust | D9: 2 | E9: 3 | F9: Greater Magic Essence | G9: 1 | H9: 2 | I9: Small Glimmering Shard
A10: 16 | B10: 20 | C10: Strange Dust | D10: 4 | E10: 6 | F10: Lesser Astral Essence | G10: 1 | H10: 2 | I10: Small Glimmering Shard
A11: 21 | B11: 25 | C11: Soul Dust | D11: 1 | E11: 2 | F11: Greater Astral Essence | G11: 1 | H11: 2 | I11: Large Glimmering Shard
A12: 26 | B12: 30 | C12: Soul Dust | D12: 2 | E12: 5 | F12: Lesser Mystic Essence | G12: 1 | H12: 2 | I12: Small Glowing Shard
A13: 31 | B13: 35 | C13: Vision Dust | D13: 1 | E13: 2 | F13: Greater Mystic Essence | G13: 1 | H13: 2 | I13: Large Glowing Shard
A14: 36 | B14: 40 | C14: Vision Dust | D14: 2 | E14: 5 | F14: Lesser Nether Essence | G14: 1 | H14: 2 | I14: Small Radiant Shard
A15: 41 | B15: 45 | C15: Dream Dust | D15: 1 | E15: 2 | F15: Greater Nether Essence | G15: 1 | H15: 2 | I15: Large Radiant Shard
A16: 46 | B16: 50 | C16: Dream Dust | D16: 2 | E16: 5 | F16: Lesser Eternal Essence | G16: 1 | H16: 2 | I16: Small Brilliant Shard
A17: 51 | B17: 55 | C17: Illusion Dust | D17: 1 | E17: 2 | F17: Greater Eternal Essence | G17: 1 | H17: 2 | I17: Large Brilliant Shard
A18: 56 | B18: 60 | C18: Illusion Dust | D18: 2 | E18: 5 | F18: Greater Eternal Essence | G18: 1 | H18: 3 | I18: Large Brilliant Shard
A20: Grünes LW-Teil | B20: benötigte Stufe | C20: Tabellenzeile | D20: Staub | E20: Staub/Teil | F20: Essenz | G20: Essenz/Teil | H20: Splitter | I20: Splitter/Teil | J20: Entzauberungswert (s) | K20: Materialkosten (s) | L20: Händlerpreis (s) | M20: Entzaubern − Kosten (s) | N20: Händler − Kosten (s) | O20: Anzahl in Wowhead-Route | P20: Reagenz 1 | Q20: Menge | R20: Reagenz 2 | S20: Menge | T20: Reagenz 3 | U20: Menge | V20: Reagenz 4 | W20: Menge | X20: Reagenz 5 | Y20: Menge | Z20: Reagenz 6 | AA20: Menge | AB20: Preise fehlen | AC20: Reagenzien laut | AD20: Item-Seite
A21: Embossed Leather Gloves | B21: 8 | C21: =MATCH(B21,$A$8:$A$18,1) -> 1 | D21: =INDEX($C$8:$C$18,C21) -> Strange Dust | E21: =$B$3*(INDEX($D$8:$D$18,C21)+INDEX($E$8:$E$18,C21))/2 -> 1.125 | F21: =INDEX($F$8:$F$18,C21) -> Lesser Magic Essence | G21: =$B$4*(INDEX($G$8:$G$18,C21)+INDEX($H$8:$H$18,C21))/2 -> 0.3 | H21: =INDEX($I$8:$I$18,C21) -> – | I21: =IF(H21="–",0,$B$5) -> 0 | J21: =IFERROR(E21*INDEX(Preise!$L$3:$L$53,MATCH(D21,Preise!$A$3:$A$53,0)),0)+IFERROR(G21*INDEX(Preise!$L$3:$L$53,MATCH(F21,Preise!$A$3:$A$53,0)),0)+IF(H21="–",0,IFERROR(I21*INDEX(Preise!$L$3:$L$53,MATCH(H21,Preise!$A$3:$A$53,0)),0)) -> 1.152 | K21: =IF(P21="",0,IFERROR(Q21*INDEX(Preise!$L$3:$L$53,MATCH(P21,Preise!$A$3:$A$53,0)),0))+IF(R21="",0,IFERROR(S21*INDEX(Preise!$L$3:$L$53,MATCH(R21,Preise!$A$3:$A$53,0)),0))+IF(T21="",0,IFERROR(U21*INDEX(Preise!$L$3:$L$53,MATCH(T21,Preise!$A$3:$A$53,0)),0))+IF(V21="",0,IFERROR(W21*INDEX(Preise!$L$3:$L$53,MATCH(V21,Preise!$A$3:$A$53,0)),0))+IF(X21="",0,IFERROR(Y21*INDEX(Preise!$L$3:$L$53,MATCH(X21,Preise!$A$3:$A$53,0)),0))+IF(Z21="",0,IFERROR(AA21*INDEX(Preise!$L$3:$L$53,MATCH(Z21,Preise!$A$3:$A$53,0)),0)) -> 1.7 | L21: 0.71 | M21: =J21-K21 -> -0.548 | N21: =L21-K21 -> -0.99 | O21: 30 | P21: Light Leather | Q21: 3 | R21: Coarse Thread | S21: 2 | AB21: =IF(P21="",0,IF(IFERROR(INDEX(Preise!$L$3:$L$53,MATCH(P21,Preise!$A$3:$A$53,0)),"")="",1,0))+IF(R21="",0,IF(IFERROR(INDEX(Preise!$L$3:$L$53,MATCH(R21,Preise!$A$3:$A$53,0)),"")="",1,0))+IF(T21="",0,IF(IFERROR(INDEX(Preise!$L$3:$L$53,MATCH(T21,Preise!$A$3:$A$53,0)),"")="",1,0))+IF(V21="",0,IF(IFERROR(INDEX(Preise!$L$3:$L$53,MATCH(V21,Preise!$A$3:$A$53,0)),"")="",1,0))+IF(X21="",0,IF(IFERROR(INDEX(Preise!$L$3:$L$53,MATCH(X21,Preise!$A$3:$A$53,0)),"")="",1,0))+IF(Z21="",0,IF(IFERROR(INDEX(Preise!$L$3:$L$53,MATCH(Z21,Preise!$A$3:$A$53,0)),"")="",1,0))+IF(IFERROR(INDEX(Preise!$L$3:$L$53,MATCH(D21,Preise!$A$3:$A$53,0)),"")="",1,0)+IF(IFERROR(INDEX(Preise!$L$3:$L$53,MATCH(F21,Preise!$A$3:$A$53,0)),"")="",1,0)+IF(H21="–",0,IF(IFERROR(INDEX(Preise!$L$3:$L$53,MATCH(H21,Preise!$A$3:$A$53,0)),"")="",1,0)) -> 0 | AC21: Wowhead-Route | AD21: https://www.wowhead.com/forever/item=4239/embossed-leather-gloves
A22: Fine Leather Belt | B22: 11 | C22: =MATCH(B22,$A$8:$A$18,1) -> 2 | D22: =INDEX($C$8:$C$18,C22) -> Strange Dust | E22: =$B$3*(INDEX($D$8:$D$18,C22)+INDEX($E$8:$E$18,C22))/2 -> 1.875 | F22: =INDEX($F$8:$F$18,C22) -> Greater Magic Essence | G22: =$B$4*(INDEX($G$8:$G$18,C22)+INDEX($H$8:$H$18,C22))/2 -> 0.3 | H22: =INDEX($I$8:$I$18,C22) -> Small Glimmering Shard | I22: =IF(H22="–",0,$B$5) -> 0.04 | J22: =IFERROR(E22*INDEX(Preise!$L$3:$L$53,MATCH(D22,Preise!$A$3:$A$53,0)),0)+IFERROR(G22*INDEX(Preise!$L$3:$L$53,MATCH(F22,Preise!$A$3:$A$53,0)),0)+IF(H22="–",0,IFERROR(I22*INDEX(Preise!$L$3:$L$53,MATCH(H22,Preise!$A$3:$A$53,0)),0)) -> 2.3094 | K22: =IF(P22="",0,IFERROR(Q22*INDEX(Preise!$L$3:$L$53,MATCH(P22,Preise!$A$3:$A$53,0)),0))+IF(R22="",0,IFERROR(S22*INDEX(Preise!$L$3:$L$53,MATCH(R22,Preise!$A$3:$A$53,0)),0))+IF(T22="",0,IFERROR(U22*INDEX(Preise!$L$3:$L$53,MATCH(T22,Preise!$A$3:$A$53,0)),0))+IF(V22="",0,IFERROR(W22*INDEX(Preise!$L$3:$L$53,MATCH(V22,Preise!$A$3:$A$53,0)),0))+IF(X22="",0,IFERROR(Y22*INDEX(Preise!$L$3:$L$53,MATCH(X22,Preise!$A$3:$A$53,0)),0))+IF(Z22="",0,IFERROR(AA22*INDEX(Preise!$L$3:$L$53,MATCH(Z22,Preise!$A$3:$A$53,0)),0)) -> 3.2 | L22: 1.25 | M22: =J22-K22 -> -0.8906 | N22: =L22-K22 -> -1.95 | O22: 0 | P22: Light Leather | Q22: 6 | R22: Coarse Thread | S22: 2 | AB22: =IF(P22="",0,IF(IFERROR(INDEX(Preise!$L$3:$L$53,MATCH(P22,Preise!$A$3:$A$53,0)),"")="",1,0))+IF(R22="",0,IF(IFERROR(INDEX(Preise!$L$3:$L$53,MATCH(R22,Preise!$A$3:$A$53,0)),"")="",1,0))+IF(T22="",0,IF(IFERROR(INDEX(Preise!$L$3:$L$53,MATCH(T22,Preise!$A$3:$A$53,0)),"")="",1,0))+IF(V22="",0,IF(IFERROR(INDEX(Preise!$L$3:$L$53,MATCH(V22,Preise!$A$3:$A$53,0)),"")="",1,0))+IF(X22="",0,IF(IFERROR(INDEX(Preise!$L$3:$L$53,MATCH(X22,Preise!$A$3:$A$53,0)),"")="",1,0))+IF(Z22="",0,IF(IFERROR(INDEX(Preise!$L$3:$L$53,MATCH(Z22,Preise!$A$3:$A$53,0)),"")="",1,0))+IF(IFERROR(INDEX(Preise!$L$3:$L$53,MATCH(D22,Preise!$A$3:$A$53,0)),"")="",1,0)+IF(IFERROR(INDEX(Preise!$L$3:$L$53,MATCH(F22,Preise!$A$3:$A$53,0)),"")="",1,0)+IF(H22="–",0,IF(IFERROR(INDEX(Preise!$L$3:$L$53,MATCH(H22,Preise!$A$3:$A$53,0)),"")="",1,0)) -> 0 | AC22: Wowhead-Route; alle 15 gehen in Dark Leather Belt | AD22: https://www.wowhead.com/forever/item=4246/fine-leather-belt
A23: Light Leather Pants | B23: 14 | C23: =MATCH(B23,$A$8:$A$18,1) -> 2 | D23: =INDEX($C$8:$C$18,C23) -> Strange Dust | E23: =$B$3*(INDEX($D$8:$D$18,C23)+INDEX($E$8:$E$18,C23))/2 -> 1.875 | F23: =INDEX($F$8:$F$18,C23) -> Greater Magic Essence | G23: =$B$4*(INDEX($G$8:$G$18,C23)+INDEX($H$8:$H$18,C23))/2 -> 0.3 | H23: =INDEX($I$8:$I$18,C23) -> Small Glimmering Shard | I23: =IF(H23="–",0,$B$5) -> 0.04 | J23: =IFERROR(E23*INDEX(Preise!$L$3:$L$53,MATCH(D23,Preise!$A$3:$A$53,0)),0)+IFERROR(G23*INDEX(Preise!$L$3:$L$53,MATCH(F23,Preise!$A$3:$A$53,0)),0)+IF(H23="–",0,IFERROR(I23*INDEX(Preise!$L$3:$L$53,MATCH(H23,Preise!$A$3:$A$53,0)),0)) -> 2.3094 | K23: =IF(P23="",0,IFERROR(Q23*INDEX(Preise!$L$3:$L$53,MATCH(P23,Preise!$A$3:$A$53,0)),0))+IF(R23="",0,IFERROR(S23*INDEX(Preise!$L$3:$L$53,MATCH(R23,Preise!$A$3:$A$53,0)),0))+IF(T23="",0,IFERROR(U23*INDEX(Preise!$L$3:$L$53,MATCH(T23,Preise!$A$3:$A$53,0)),0))+IF(V23="",0,IFERROR(W23*INDEX(Preise!$L$3:$L$53,MATCH(V23,Preise!$A$3:$A$53,0)),0))+IF(X23="",0,IFERROR(Y23*INDEX(Preise!$L$3:$L$53,MATCH(X23,Preise!$A$3:$A$53,0)),0))+IF(Z23="",0,IFERROR(AA23*INDEX(Preise!$L$3:$L$53,MATCH(Z23,Preise!$A$3:$A$53,0)),0)) -> 7.19 | L23: 5.99 | M23: =J23-K23 -> -4.8806 | N23: =L23-K23 -> -1.2 | O23: 0 | P23: Light Leather | Q23: 10 | R23: Light Hide | S23: 1 | T23: Salt | U23: 1 | V23: Fine Thread | W23: 1 | AB23: =IF(P23="",0,IF(IFERROR(INDEX(Preise!$L$3:$L$53,MATCH(P23,Preise!$A$3:$A$53,0)),"")="",1,0))+IF(R23="",0,IF(IFERROR(INDEX(Preise!$L$3:$L$53,MATCH(R23,Preise!$A$3:$A$53,0)),"")="",1,0))+IF(T23="",0,IF(IFERROR(INDEX(Preise!$L$3:$L$53,MATCH(T23,Preise!$A$3:$A$53,0)),"")="",1,0))+IF(V23="",0,IF(IFERROR(INDEX(Preise!$L$3:$L$53,MATCH(V23,Preise!$A$3:$A$53,0)),"")="",1,0))+IF(X23="",0,IF(IFERROR(INDEX(Preise!$L$3:$L$53,MATCH(X23,Preise!$A$3:$A$53,0)),"")="",1,0))+IF(Z23="",0,IF(IFERROR(INDEX(Preise!$L$3:$L$53,MATCH(Z23,Preise!$A$3:$A$53,0)),"")="",1,0))+IF(IFERROR(INDEX(Preise!$L$3:$L$53,MATCH(D23,Preise!$A$3:$A$53,0)),"")="",1,0)+IF(IFERROR(INDEX(Preise!$L$3:$L$53,MATCH(F23,Preise!$A$3:$A$53,0)),"")="",1,0)+IF(H23="–",0,IF(IFERROR(INDEX(Preise!$L$3:$L$53,MATCH(H23,Preise!$A$3:$A$53,0)),"")="",1,0)) -> 0 | AC23: AHledger (Forever); nicht in Wowhead-Route | AD23: https://www.wowhead.com/forever/item=7282/light-leather-pants
A24: Dark Leather Boots | B24: 15 | C24: =MATCH(B24,$A$8:$A$18,1) -> 2 | D24: =INDEX($C$8:$C$18,C24) -> Strange Dust | E24: =$B$3*(INDEX($D$8:$D$18,C24)+INDEX($E$8:$E$18,C24))/2 -> 1.875 | F24: =INDEX($F$8:$F$18,C24) -> Greater Magic Essence | G24: =$B$4*(INDEX($G$8:$G$18,C24)+INDEX($H$8:$H$18,C24))/2 -> 0.3 | H24: =INDEX($I$8:$I$18,C24) -> Small Glimmering Shard | I24: =IF(H24="–",0,$B$5) -> 0.04 | J24: =IFERROR(E24*INDEX(Preise!$L$3:$L$53,MATCH(D24,Preise!$A$3:$A$53,0)),0)+IFERROR(G24*INDEX(Preise!$L$3:$L$53,MATCH(F24,Preise!$A$3:$A$53,0)),0)+IF(H24="–",0,IFERROR(I24*INDEX(Preise!$L$3:$L$53,MATCH(H24,Preise!$A$3:$A$53,0)),0)) -> 2.3094 | K24: =IF(P24="",0,IFERROR(Q24*INDEX(Preise!$L$3:$L$53,MATCH(P24,Preise!$A$3:$A$53,0)),0))+IF(R24="",0,IFERROR(S24*INDEX(Preise!$L$3:$L$53,MATCH(R24,Preise!$A$3:$A$53,0)),0))+IF(T24="",0,IFERROR(U24*INDEX(Preise!$L$3:$L$53,MATCH(T24,Preise!$A$3:$A$53,0)),0))+IF(V24="",0,IFERROR(W24*INDEX(Preise!$L$3:$L$53,MATCH(V24,Preise!$A$3:$A$53,0)),0))+IF(X24="",0,IFERROR(Y24*INDEX(Preise!$L$3:$L$53,MATCH(X24,Preise!$A$3:$A$53,0)),0))+IF(Z24="",0,IFERROR(AA24*INDEX(Preise!$L$3:$L$53,MATCH(Z24,Preise!$A$3:$A$53,0)),0)) -> 13.14 | L24: 3.07 | M24: =J24-K24 -> -10.8306 | N24: =L24-K24 -> -10.07 | O24: 22 | P24: Medium Leather | Q24: 4 | R24: Fine Thread | S24: 2 | T24: Gray Dye | U24: 1 | AB24: =IF(P24="",0,IF(IFERROR(INDEX(Preise!$L$3:$L$53,MATCH(P24,Preise!$A$3:$A$53,0)),"")="",1,0))+IF(R24="",0,IF(IFERROR(INDEX(Preise!$L$3:$L$53,MATCH(R24,Preise!$A$3:$A$53,0)),"")="",1,0))+IF(T24="",0,IF(IFERROR(INDEX(Preise!$L$3:$L$53,MATCH(T24,Preise!$A$3:$A$53,0)),"")="",1,0))+IF(V24="",0,IF(IFERROR(INDEX(Preise!$L$3:$L$53,MATCH(V24,Preise!$A$3:$A$53,0)),"")="",1,0))+IF(X24="",0,IF(IFERROR(INDEX(Preise!$L$3:$L$53,MATCH(X24,Preise!$A$3:$A$53,0)),"")="",1,0))+IF(Z24="",0,IF(IFERROR(INDEX(Preise!$L$3:$L$53,MATCH(Z24,Preise!$A$3:$A$53,0)),"")="",1,0))+IF(IFERROR(INDEX(Preise!$L$3:$L$53,MATCH(D24,Preise!$A$3:$A$53,0)),"")="",1,0)+IF(IFERROR(INDEX(Preise!$L$3:$L$53,MATCH(F24,Preise!$A$3:$A$53,0)),"")="",1,0)+IF(H24="–",0,IF(IFERROR(INDEX(Preise!$L$3:$L$53,MATCH(H24,Preise!$A$3:$A$53,0)),"")="",1,0)) -> 0 | AC24: Wowhead-Route | AD24: https://www.wowhead.com/forever/item=2315/dark-leather-boots
A25: Dark Leather Belt | B25: 20 | C25: =MATCH(B25,$A$8:$A$18,1) -> 3 | D25: =INDEX($C$8:$C$18,C25) -> Strange Dust | E25: =$B$3*(INDEX($D$8:$D$18,C25)+INDEX($E$8:$E$18,C25))/2 -> 3.75 | F25: =INDEX($F$8:$F$18,C25) -> Lesser Astral Essence | G25: =$B$4*(INDEX($G$8:$G$18,C25)+INDEX($H$8:$H$18,C25))/2 -> 0.3 | H25: =INDEX($I$8:$I$18,C25) -> Small Glimmering Shard | I25: =IF(H25="–",0,$B$5) -> 0.04 | J25: =IFERROR(E25*INDEX(Preise!$L$3:$L$53,MATCH(D25,Preise!$A$3:$A$53,0)),0)+IFERROR(G25*INDEX(Preise!$L$3:$L$53,MATCH(F25,Preise!$A$3:$A$53,0)),0)+IF(H25="–",0,IFERROR(I25*INDEX(Preise!$L$3:$L$53,MATCH(H25,Preise!$A$3:$A$53,0)),0)) -> 5.1084 | K25: =IF(P25="",0,IFERROR(Q25*INDEX(Preise!$L$3:$L$53,MATCH(P25,Preise!$A$3:$A$53,0)),0))+IF(R25="",0,IFERROR(S25*INDEX(Preise!$L$3:$L$53,MATCH(R25,Preise!$A$3:$A$53,0)),0))+IF(T25="",0,IFERROR(U25*INDEX(Preise!$L$3:$L$53,MATCH(T25,Preise!$A$3:$A$53,0)),0))+IF(V25="",0,IFERROR(W25*INDEX(Preise!$L$3:$L$53,MATCH(V25,Preise!$A$3:$A$53,0)),0))+IF(X25="",0,IFERROR(Y25*INDEX(Preise!$L$3:$L$53,MATCH(X25,Preise!$A$3:$A$53,0)),0))+IF(Z25="",0,IFERROR(AA25*INDEX(Preise!$L$3:$L$53,MATCH(Z25,Preise!$A$3:$A$53,0)),0)) -> 18.08 | L25: 7.03 | M25: =J25-K25 -> -12.9716 | N25: =L25-K25 -> -11.05 | O25: 15 | P25: Light Leather | Q25: 6 | R25: Coarse Thread | S25: 2 | T25: Medium Hide | U25: 1 | V25: Salt | W25: 1 | X25: Fine Thread | Y25: 2 | Z25: Gray Dye | AA25: 1 | AB25: =IF(P25="",0,IF(IFERROR(INDEX(Preise!$L$3:$L$53,MATCH(P25,Preise!$A$3:$A$53,0)),"")="",1,0))+IF(R25="",0,IF(IFERROR(INDEX(Preise!$L$3:$L$53,MATCH(R25,Preise!$A$3:$A$53,0)),"")="",1,0))+IF(T25="",0,IF(IFERROR(INDEX(Preise!$L$3:$L$53,MATCH(T25,Preise!$A$3:$A$53,0)),"")="",1,0))+IF(V25="",0,IF(IFERROR(INDEX(Preise!$L$3:$L$53,MATCH(V25,Preise!$A$3:$A$53,0)),"")="",1,0))+IF(X25="",0,IF(IFERROR(INDEX(Preise!$L$3:$L$53,MATCH(X25,Preise!$A$3:$A$53,0)),"")="",1,0))+IF(Z25="",0,IF(IFERROR(INDEX(Preise!$L$3:$L$53,MATCH(Z25,Preise!$A$3:$A$53,0)),"")="",1,0))+IF(IFERROR(INDEX(Preise!$L$3:$L$53,MATCH(D25,Preise!$A$3:$A$53,0)),"")="",1,0)+IF(IFERROR(INDEX(Preise!$L$3:$L$53,MATCH(F25,Preise!$A$3:$A$53,0)),"")="",1,0)+IF(H25="–",0,IF(IFERROR(INDEX(Preise!$L$3:$L$53,MATCH(H25,Preise!$A$3:$A$53,0)),"")="",1,0)) -> 0 | AC25: Wowhead-Route (Fine Leather Belt + Cured Medium Hide aufgelöst) | AD25: https://www.wowhead.com/forever/item=4249/dark-leather-belt
A26: Hillman's Leather Gloves | B26: 24 | C26: =MATCH(B26,$A$8:$A$18,1) -> 4 | D26: =INDEX($C$8:$C$18,C26) -> Soul Dust | E26: =$B$3*(INDEX($D$8:$D$18,C26)+INDEX($E$8:$E$18,C26))/2 -> 1.125 | F26: =INDEX($F$8:$F$18,C26) -> Greater Astral Essence | G26: =$B$4*(INDEX($G$8:$G$18,C26)+INDEX($H$8:$H$18,C26))/2 -> 0.3 | H26: =INDEX($I$8:$I$18,C26) -> Large Glimmering Shard | I26: =IF(H26="–",0,$B$5) -> 0.04 | J26: =IFERROR(E26*INDEX(Preise!$L$3:$L$53,MATCH(D26,Preise!$A$3:$A$53,0)),0)+IFERROR(G26*INDEX(Preise!$L$3:$L$53,MATCH(F26,Preise!$A$3:$A$53,0)),0)+IF(H26="–",0,IFERROR(I26*INDEX(Preise!$L$3:$L$53,MATCH(H26,Preise!$A$3:$A$53,0)),0)) -> 19.83285 | K26: =IF(P26="",0,IFERROR(Q26*INDEX(Preise!$L$3:$L$53,MATCH(P26,Preise!$A$3:$A$53,0)),0))+IF(R26="",0,IFERROR(S26*INDEX(Preise!$L$3:$L$53,MATCH(R26,Preise!$A$3:$A$53,0)),0))+IF(T26="",0,IFERROR(U26*INDEX(Preise!$L$3:$L$53,MATCH(T26,Preise!$A$3:$A$53,0)),0))+IF(V26="",0,IFERROR(W26*INDEX(Preise!$L$3:$L$53,MATCH(V26,Preise!$A$3:$A$53,0)),0))+IF(X26="",0,IFERROR(Y26*INDEX(Preise!$L$3:$L$53,MATCH(X26,Preise!$A$3:$A$53,0)),0))+IF(Z26="",0,IFERROR(AA26*INDEX(Preise!$L$3:$L$53,MATCH(Z26,Preise!$A$3:$A$53,0)),0)) -> 30.74 | L26: 10.49 | M26: =J26-K26 -> -10.90715 | N26: =L26-K26 -> -20.25 | O26: 0 | P26: Medium Leather | Q26: 14 | R26: Fine Thread | S26: 4 | AB26: =IF(P26="",0,IF(IFERROR(INDEX(Preise!$L$3:$L$53,MATCH(P26,Preise!$A$3:$A$53,0)),"")="",1,0))+IF(R26="",0,IF(IFERROR(INDEX(Preise!$L$3:$L$53,MATCH(R26,Preise!$A$3:$A$53,0)),"")="",1,0))+IF(T26="",0,IF(IFERROR(INDEX(Preise!$L$3:$L$53,MATCH(T26,Preise!$A$3:$A$53,0)),"")="",1,0))+IF(V26="",0,IF(IFERROR(INDEX(Preise!$L$3:$L$53,MATCH(V26,Preise!$A$3:$A$53,0)),"")="",1,0))+IF(X26="",0,IF(IFERROR(INDEX(Preise!$L$3:$L$53,MATCH(X26,Preise!$A$3:$A$53,0)),"")="",1,0))+IF(Z26="",0,IF(IFERROR(INDEX(Preise!$L$3:$L$53,MATCH(Z26,Preise!$A$3:$A$53,0)),"")="",1,0))+IF(IFERROR(INDEX(Preise!$L$3:$L$53,MATCH(D26,Preise!$A$3:$A$53,0)),"")="",1,0)+IF(IFERROR(INDEX(Preise!$L$3:$L$53,MATCH(F26,Preise!$A$3:$A$53,0)),"")="",1,0)+IF(H26="–",0,IF(IFERROR(INDEX(Preise!$L$3:$L$53,MATCH(H26,Preise!$A$3:$A$53,0)),"")="",1,0)) -> 0 | AC26: AHledger (Forever); nicht in Wowhead-Route | AD26: https://www.wowhead.com/forever/item=4247/hillmans-leather-gloves
A27: Barbaric Shoulders | B27: 30 | C27: =MATCH(B27,$A$8:$A$18,1) -> 5 | D27: =INDEX($C$8:$C$18,C27) -> Soul Dust | E27: =$B$3*(INDEX($D$8:$D$18,C27)+INDEX($E$8:$E$18,C27))/2 -> 2.625 | F27: =INDEX($F$8:$F$18,C27) -> Lesser Mystic Essence | G27: =$B$4*(INDEX($G$8:$G$18,C27)+INDEX($H$8:$H$18,C27))/2 -> 0.3 | H27: =INDEX($I$8:$I$18,C27) -> Small Glowing Shard | I27: =IF(H27="–",0,$B$5) -> 0.04 | J27: =IFERROR(E27*INDEX(Preise!$L$3:$L$53,MATCH(D27,Preise!$A$3:$A$53,0)),0)+IFERROR(G27*INDEX(Preise!$L$3:$L$53,MATCH(F27,Preise!$A$3:$A$53,0)),0)+IF(H27="–",0,IFERROR(I27*INDEX(Preise!$L$3:$L$53,MATCH(H27,Preise!$A$3:$A$53,0)),0)) -> 26.75385 | K27: =IF(P27="",0,IFERROR(Q27*INDEX(Preise!$L$3:$L$53,MATCH(P27,Preise!$A$3:$A$53,0)),0))+IF(R27="",0,IFERROR(S27*INDEX(Preise!$L$3:$L$53,MATCH(R27,Preise!$A$3:$A$53,0)),0))+IF(T27="",0,IFERROR(U27*INDEX(Preise!$L$3:$L$53,MATCH(T27,Preise!$A$3:$A$53,0)),0))+IF(V27="",0,IFERROR(W27*INDEX(Preise!$L$3:$L$53,MATCH(V27,Preise!$A$3:$A$53,0)),0))+IF(X27="",0,IFERROR(Y27*INDEX(Preise!$L$3:$L$53,MATCH(X27,Preise!$A$3:$A$53,0)),0))+IF(Z27="",0,IFERROR(AA27*INDEX(Preise!$L$3:$L$53,MATCH(Z27,Preise!$A$3:$A$53,0)),0)) -> 134.74 | L27: 26.09 | M27: =J27-K27 -> -107.98615 | N27: =L27-K27 -> -108.65 | O27: 10 | P27: Heavy Leather | Q27: 8 | R27: Heavy Hide | S27: 1 | T27: Salt | U27: 3 | V27: Fine Thread | W27: 2 | AB27: =IF(P27="",0,IF(IFERROR(INDEX(Preise!$L$3:$L$53,MATCH(P27,Preise!$A$3:$A$53,0)),"")="",1,0))+IF(R27="",0,IF(IFERROR(INDEX(Preise!$L$3:$L$53,MATCH(R27,Preise!$A$3:$A$53,0)),"")="",1,0))+IF(T27="",0,IF(IFERROR(INDEX(Preise!$L$3:$L$53,MATCH(T27,Preise!$A$3:$A$53,0)),"")="",1,0))+IF(V27="",0,IF(IFERROR(INDEX(Preise!$L$3:$L$53,MATCH(V27,Preise!$A$3:$A$53,0)),"")="",1,0))+IF(X27="",0,IF(IFERROR(INDEX(Preise!$L$3:$L$53,MATCH(X27,Preise!$A$3:$A$53,0)),"")="",1,0))+IF(Z27="",0,IF(IFERROR(INDEX(Preise!$L$3:$L$53,MATCH(Z27,Preise!$A$3:$A$53,0)),"")="",1,0))+IF(IFERROR(INDEX(Preise!$L$3:$L$53,MATCH(D27,Preise!$A$3:$A$53,0)),"")="",1,0)+IF(IFERROR(INDEX(Preise!$L$3:$L$53,MATCH(F27,Preise!$A$3:$A$53,0)),"")="",1,0)+IF(H27="–",0,IF(IFERROR(INDEX(Preise!$L$3:$L$53,MATCH(H27,Preise!$A$3:$A$53,0)),"")="",1,0)) -> 0 | AC27: Wowhead-Route (Cured Heavy Hide aufgelöst) | AD27: https://www.wowhead.com/forever/item=5964/barbaric-shoulders
A28: Guardian Gloves | B28: 33 | C28: =MATCH(B28,$A$8:$A$18,1) -> 6 | D28: =INDEX($C$8:$C$18,C28) -> Vision Dust | E28: =$B$3*(INDEX($D$8:$D$18,C28)+INDEX($E$8:$E$18,C28))/2 -> 1.125 | F28: =INDEX($F$8:$F$18,C28) -> Greater Mystic Essence | G28: =$B$4*(INDEX($G$8:$G$18,C28)+INDEX($H$8:$H$18,C28))/2 -> 0.3 | H28: =INDEX($I$8:$I$18,C28) -> Large Glowing Shard | I28: =IF(H28="–",0,$B$5) -> 0.04 | J28: =IFERROR(E28*INDEX(Preise!$L$3:$L$53,MATCH(D28,Preise!$A$3:$A$53,0)),0)+IFERROR(G28*INDEX(Preise!$L$3:$L$53,MATCH(F28,Preise!$A$3:$A$53,0)),0)+IF(H28="–",0,IFERROR(I28*INDEX(Preise!$L$3:$L$53,MATCH(H28,Preise!$A$3:$A$53,0)),0)) -> 63.37375 | K28: =IF(P28="",0,IFERROR(Q28*INDEX(Preise!$L$3:$L$53,MATCH(P28,Preise!$A$3:$A$53,0)),0))+IF(R28="",0,IFERROR(S28*INDEX(Preise!$L$3:$L$53,MATCH(R28,Preise!$A$3:$A$53,0)),0))+IF(T28="",0,IFERROR(U28*INDEX(Preise!$L$3:$L$53,MATCH(T28,Preise!$A$3:$A$53,0)),0))+IF(V28="",0,IFERROR(W28*INDEX(Preise!$L$3:$L$53,MATCH(V28,Preise!$A$3:$A$53,0)),0))+IF(X28="",0,IFERROR(Y28*INDEX(Preise!$L$3:$L$53,MATCH(X28,Preise!$A$3:$A$53,0)),0))+IF(Z28="",0,IFERROR(AA28*INDEX(Preise!$L$3:$L$53,MATCH(Z28,Preise!$A$3:$A$53,0)),0)) -> 89.82 | L28: 13.74 | M28: =J28-K28 -> -26.44625 | N28: =L28-K28 -> -76.08 | O28: 10 | P28: Heavy Leather | Q28: 4 | R28: Heavy Hide | S28: 1 | T28: Salt | U28: 3 | V28: Silken Thread | W28: 1 | AB28: =IF(P28="",0,IF(IFERROR(INDEX(Preise!$L$3:$L$53,MATCH(P28,Preise!$A$3:$A$53,0)),"")="",1,0))+IF(R28="",0,IF(IFERROR(INDEX(Preise!$L$3:$L$53,MATCH(R28,Preise!$A$3:$A$53,0)),"")="",1,0))+IF(T28="",0,IF(IFERROR(INDEX(Preise!$L$3:$L$53,MATCH(T28,Preise!$A$3:$A$53,0)),"")="",1,0))+IF(V28="",0,IF(IFERROR(INDEX(Preise!$L$3:$L$53,MATCH(V28,Preise!$A$3:$A$53,0)),"")="",1,0))+IF(X28="",0,IF(IFERROR(INDEX(Preise!$L$3:$L$53,MATCH(X28,Preise!$A$3:$A$53,0)),"")="",1,0))+IF(Z28="",0,IF(IFERROR(INDEX(Preise!$L$3:$L$53,MATCH(Z28,Preise!$A$3:$A$53,0)),"")="",1,0))+IF(IFERROR(INDEX(Preise!$L$3:$L$53,MATCH(D28,Preise!$A$3:$A$53,0)),"")="",1,0)+IF(IFERROR(INDEX(Preise!$L$3:$L$53,MATCH(F28,Preise!$A$3:$A$53,0)),"")="",1,0)+IF(H28="–",0,IF(IFERROR(INDEX(Preise!$L$3:$L$53,MATCH(H28,Preise!$A$3:$A$53,0)),"")="",1,0)) -> 0 | AC28: Wowhead-Route (Cured Heavy Hide aufgelöst) | AD28: https://ahledger.com/items/5966-guardian-gloves
A29: Nightscape Headband | B29: 36 | C29: =MATCH(B29,$A$8:$A$18,1) -> 7 | D29: =INDEX($C$8:$C$18,C29) -> Vision Dust | E29: =$B$3*(INDEX($D$8:$D$18,C29)+INDEX($E$8:$E$18,C29))/2 -> 2.625 | F29: =INDEX($F$8:$F$18,C29) -> Lesser Nether Essence | G29: =$B$4*(INDEX($G$8:$G$18,C29)+INDEX($H$8:$H$18,C29))/2 -> 0.3 | H29: =INDEX($I$8:$I$18,C29) -> Small Radiant Shard | I29: =IF(H29="–",0,$B$5) -> 0.04 | J29: =IFERROR(E29*INDEX(Preise!$L$3:$L$53,MATCH(D29,Preise!$A$3:$A$53,0)),0)+IFERROR(G29*INDEX(Preise!$L$3:$L$53,MATCH(F29,Preise!$A$3:$A$53,0)),0)+IF(H29="–",0,IFERROR(I29*INDEX(Preise!$L$3:$L$53,MATCH(H29,Preise!$A$3:$A$53,0)),0)) -> 164.43195 | K29: =IF(P29="",0,IFERROR(Q29*INDEX(Preise!$L$3:$L$53,MATCH(P29,Preise!$A$3:$A$53,0)),0))+IF(R29="",0,IFERROR(S29*INDEX(Preise!$L$3:$L$53,MATCH(R29,Preise!$A$3:$A$53,0)),0))+IF(T29="",0,IFERROR(U29*INDEX(Preise!$L$3:$L$53,MATCH(T29,Preise!$A$3:$A$53,0)),0))+IF(V29="",0,IFERROR(W29*INDEX(Preise!$L$3:$L$53,MATCH(V29,Preise!$A$3:$A$53,0)),0))+IF(X29="",0,IFERROR(Y29*INDEX(Preise!$L$3:$L$53,MATCH(X29,Preise!$A$3:$A$53,0)),0))+IF(Z29="",0,IFERROR(AA29*INDEX(Preise!$L$3:$L$53,MATCH(Z29,Preise!$A$3:$A$53,0)),0)) -> 188.95 | L29: 44.95 | M29: =J29-K29 -> -24.51805 | N29: =L29-K29 -> -144 | O29: 11 | P29: Thick Leather | Q29: 5 | R29: Silken Thread | S29: 2 | AB29: =IF(P29="",0,IF(IFERROR(INDEX(Preise!$L$3:$L$53,MATCH(P29,Preise!$A$3:$A$53,0)),"")="",1,0))+IF(R29="",0,IF(IFERROR(INDEX(Preise!$L$3:$L$53,MATCH(R29,Preise!$A$3:$A$53,0)),"")="",1,0))+IF(T29="",0,IF(IFERROR(INDEX(Preise!$L$3:$L$53,MATCH(T29,Preise!$A$3:$A$53,0)),"")="",1,0))+IF(V29="",0,IF(IFERROR(INDEX(Preise!$L$3:$L$53,MATCH(V29,Preise!$A$3:$A$53,0)),"")="",1,0))+IF(X29="",0,IF(IFERROR(INDEX(Preise!$L$3:$L$53,MATCH(X29,Preise!$A$3:$A$53,0)),"")="",1,0))+IF(Z29="",0,IF(IFERROR(INDEX(Preise!$L$3:$L$53,MATCH(Z29,Preise!$A$3:$A$53,0)),"")="",1,0))+IF(IFERROR(INDEX(Preise!$L$3:$L$53,MATCH(D29,Preise!$A$3:$A$53,0)),"")="",1,0)+IF(IFERROR(INDEX(Preise!$L$3:$L$53,MATCH(F29,Preise!$A$3:$A$53,0)),"")="",1,0)+IF(H29="–",0,IF(IFERROR(INDEX(Preise!$L$3:$L$53,MATCH(H29,Preise!$A$3:$A$53,0)),"")="",1,0)) -> 0 | AC29: Wowhead-Route | AD29: https://www.wowhead.com/forever/item=8176/nightscape-headband
A30: Nightscape Pants | B30: 41 | C30: =MATCH(B30,$A$8:$A$18,1) -> 8 | D30: =INDEX($C$8:$C$18,C30) -> Dream Dust | E30: =$B$3*(INDEX($D$8:$D$18,C30)+INDEX($E$8:$E$18,C30))/2 -> 1.125 | F30: =INDEX($F$8:$F$18,C30) -> Greater Nether Essence | G30: =$B$4*(INDEX($G$8:$G$18,C30)+INDEX($H$8:$H$18,C30))/2 -> 0.3 | H30: =INDEX($I$8:$I$18,C30) -> Large Radiant Shard | I30: =IF(H30="–",0,$B$5) -> 0.04 | J30: =IFERROR(E30*INDEX(Preise!$L$3:$L$53,MATCH(D30,Preise!$A$3:$A$53,0)),0)+IFERROR(G30*INDEX(Preise!$L$3:$L$53,MATCH(F30,Preise!$A$3:$A$53,0)),0)+IF(H30="–",0,IFERROR(I30*INDEX(Preise!$L$3:$L$53,MATCH(H30,Preise!$A$3:$A$53,0)),0)) -> 351.21 | K30: =IF(P30="",0,IFERROR(Q30*INDEX(Preise!$L$3:$L$53,MATCH(P30,Preise!$A$3:$A$53,0)),0))+IF(R30="",0,IFERROR(S30*INDEX(Preise!$L$3:$L$53,MATCH(R30,Preise!$A$3:$A$53,0)),0))+IF(T30="",0,IFERROR(U30*INDEX(Preise!$L$3:$L$53,MATCH(T30,Preise!$A$3:$A$53,0)),0))+IF(V30="",0,IFERROR(W30*INDEX(Preise!$L$3:$L$53,MATCH(V30,Preise!$A$3:$A$53,0)),0))+IF(X30="",0,IFERROR(Y30*INDEX(Preise!$L$3:$L$53,MATCH(X30,Preise!$A$3:$A$53,0)),0))+IF(Z30="",0,IFERROR(AA30*INDEX(Preise!$L$3:$L$53,MATCH(Z30,Preise!$A$3:$A$53,0)),0)) -> 521.06 | L30: 87.08 | M30: =J30-K30 -> -169.85 | N30: =L30-K30 -> -433.98 | O30: 20 | P30: Thick Leather | Q30: 14 | R30: Silken Thread | S30: 4 | AB30: =IF(P30="",0,IF(IFERROR(INDEX(Preise!$L$3:$L$53,MATCH(P30,Preise!$A$3:$A$53,0)),"")="",1,0))+IF(R30="",0,IF(IFERROR(INDEX(Preise!$L$3:$L$53,MATCH(R30,Preise!$A$3:$A$53,0)),"")="",1,0))+IF(T30="",0,IF(IFERROR(INDEX(Preise!$L$3:$L$53,MATCH(T30,Preise!$A$3:$A$53,0)),"")="",1,0))+IF(V30="",0,IF(IFERROR(INDEX(Preise!$L$3:$L$53,MATCH(V30,Preise!$A$3:$A$53,0)),"")="",1,0))+IF(X30="",0,IF(IFERROR(INDEX(Preise!$L$3:$L$53,MATCH(X30,Preise!$A$3:$A$53,0)),"")="",1,0))+IF(Z30="",0,IF(IFERROR(INDEX(Preise!$L$3:$L$53,MATCH(Z30,Preise!$A$3:$A$53,0)),"")="",1,0))+IF(IFERROR(INDEX(Preise!$L$3:$L$53,MATCH(D30,Preise!$A$3:$A$53,0)),"")="",1,0)+IF(IFERROR(INDEX(Preise!$L$3:$L$53,MATCH(F30,Preise!$A$3:$A$53,0)),"")="",1,0)+IF(H30="–",0,IF(IFERROR(INDEX(Preise!$L$3:$L$53,MATCH(H30,Preise!$A$3:$A$53,0)),"")="",1,0)) -> 0 | AC30: Wowhead-Route | AD30: https://ahledger.com/items/8193-nightscape-pants
A31: Wicked Leather Gauntlets | B31: 47 | C31: =MATCH(B31,$A$8:$A$18,1) -> 9 | D31: =INDEX($C$8:$C$18,C31) -> Dream Dust | E31: =$B$3*(INDEX($D$8:$D$18,C31)+INDEX($E$8:$E$18,C31))/2 -> 2.625 | F31: =INDEX($F$8:$F$18,C31) -> Lesser Eternal Essence | G31: =$B$4*(INDEX($G$8:$G$18,C31)+INDEX($H$8:$H$18,C31))/2 -> 0.3 | H31: =INDEX($I$8:$I$18,C31) -> Small Brilliant Shard | I31: =IF(H31="–",0,$B$5) -> 0.04 | J31: =IFERROR(E31*INDEX(Preise!$L$3:$L$53,MATCH(D31,Preise!$A$3:$A$53,0)),0)+IFERROR(G31*INDEX(Preise!$L$3:$L$53,MATCH(F31,Preise!$A$3:$A$53,0)),0)+IF(H31="–",0,IFERROR(I31*INDEX(Preise!$L$3:$L$53,MATCH(H31,Preise!$A$3:$A$53,0)),0)) -> 231.77 | K31: =IF(P31="",0,IFERROR(Q31*INDEX(Preise!$L$3:$L$53,MATCH(P31,Preise!$A$3:$A$53,0)),0))+IF(R31="",0,IFERROR(S31*INDEX(Preise!$L$3:$L$53,MATCH(R31,Preise!$A$3:$A$53,0)),0))+IF(T31="",0,IFERROR(U31*INDEX(Preise!$L$3:$L$53,MATCH(T31,Preise!$A$3:$A$53,0)),0))+IF(V31="",0,IFERROR(W31*INDEX(Preise!$L$3:$L$53,MATCH(V31,Preise!$A$3:$A$53,0)),0))+IF(X31="",0,IFERROR(Y31*INDEX(Preise!$L$3:$L$53,MATCH(X31,Preise!$A$3:$A$53,0)),0))+IF(Z31="",0,IFERROR(AA31*INDEX(Preise!$L$3:$L$53,MATCH(Z31,Preise!$A$3:$A$53,0)),0)) -> 212.16 | L31: 68.72 | M31: =J31-K31 -> 19.61 | N31: =L31-K31 -> -143.44 | O31: 32 | P31: Rugged Leather | Q31: 8 | R31: Black Dye | S31: 1 | T31: Rune Thread | U31: 1 | AB31: =IF(P31="",0,IF(IFERROR(INDEX(Preise!$L$3:$L$53,MATCH(P31,Preise!$A$3:$A$53,0)),"")="",1,0))+IF(R31="",0,IF(IFERROR(INDEX(Preise!$L$3:$L$53,MATCH(R31,Preise!$A$3:$A$53,0)),"")="",1,0))+IF(T31="",0,IF(IFERROR(INDEX(Preise!$L$3:$L$53,MATCH(T31,Preise!$A$3:$A$53,0)),"")="",1,0))+IF(V31="",0,IF(IFERROR(INDEX(Preise!$L$3:$L$53,MATCH(V31,Preise!$A$3:$A$53,0)),"")="",1,0))+IF(X31="",0,IF(IFERROR(INDEX(Preise!$L$3:$L$53,MATCH(X31,Preise!$A$3:$A$53,0)),"")="",1,0))+IF(Z31="",0,IF(IFERROR(INDEX(Preise!$L$3:$L$53,MATCH(Z31,Preise!$A$3:$A$53,0)),"")="",1,0))+IF(IFERROR(INDEX(Preise!$L$3:$L$53,MATCH(D31,Preise!$A$3:$A$53,0)),"")="",1,0)+IF(IFERROR(INDEX(Preise!$L$3:$L$53,MATCH(F31,Preise!$A$3:$A$53,0)),"")="",1,0)+IF(H31="–",0,IF(IFERROR(INDEX(Preise!$L$3:$L$53,MATCH(H31,Preise!$A$3:$A$53,0)),"")="",1,0)) -> 0 | AC31: Wowhead-Route | AD31: https://www.wowhead.com/forever/item=15083/wicked-leather-gauntlets
A32: Wicked Leather Headband | B32: 51 | C32: =MATCH(B32,$A$8:$A$18,1) -> 10 | D32: =INDEX($C$8:$C$18,C32) -> Illusion Dust | E32: =$B$3*(INDEX($D$8:$D$18,C32)+INDEX($E$8:$E$18,C32))/2 -> 1.125 | F32: =INDEX($F$8:$F$18,C32) -> Greater Eternal Essence | G32: =$B$4*(INDEX($G$8:$G$18,C32)+INDEX($H$8:$H$18,C32))/2 -> 0.3 | H32: =INDEX($I$8:$I$18,C32) -> Large Brilliant Shard | I32: =IF(H32="–",0,$B$5) -> 0.04 | J32: =IFERROR(E32*INDEX(Preise!$L$3:$L$53,MATCH(D32,Preise!$A$3:$A$53,0)),0)+IFERROR(G32*INDEX(Preise!$L$3:$L$53,MATCH(F32,Preise!$A$3:$A$53,0)),0)+IF(H32="–",0,IFERROR(I32*INDEX(Preise!$L$3:$L$53,MATCH(H32,Preise!$A$3:$A$53,0)),0)) -> 1125 | K32: =IF(P32="",0,IFERROR(Q32*INDEX(Preise!$L$3:$L$53,MATCH(P32,Preise!$A$3:$A$53,0)),0))+IF(R32="",0,IFERROR(S32*INDEX(Preise!$L$3:$L$53,MATCH(R32,Preise!$A$3:$A$53,0)),0))+IF(T32="",0,IFERROR(U32*INDEX(Preise!$L$3:$L$53,MATCH(T32,Preise!$A$3:$A$53,0)),0))+IF(V32="",0,IFERROR(W32*INDEX(Preise!$L$3:$L$53,MATCH(V32,Preise!$A$3:$A$53,0)),0))+IF(X32="",0,IFERROR(Y32*INDEX(Preise!$L$3:$L$53,MATCH(X32,Preise!$A$3:$A$53,0)),0))+IF(Z32="",0,IFERROR(AA32*INDEX(Preise!$L$3:$L$53,MATCH(Z32,Preise!$A$3:$A$53,0)),0)) -> 288.24 | L32: 131.54 | M32: =J32-K32 -> 836.76 | N32: =L32-K32 -> -156.7 | O32: 10 | P32: Rugged Leather | Q32: 12 | R32: Black Dye | S32: 1 | T32: Rune Thread | U32: 1 | AB32: =IF(P32="",0,IF(IFERROR(INDEX(Preise!$L$3:$L$53,MATCH(P32,Preise!$A$3:$A$53,0)),"")="",1,0))+IF(R32="",0,IF(IFERROR(INDEX(Preise!$L$3:$L$53,MATCH(R32,Preise!$A$3:$A$53,0)),"")="",1,0))+IF(T32="",0,IF(IFERROR(INDEX(Preise!$L$3:$L$53,MATCH(T32,Preise!$A$3:$A$53,0)),"")="",1,0))+IF(V32="",0,IF(IFERROR(INDEX(Preise!$L$3:$L$53,MATCH(V32,Preise!$A$3:$A$53,0)),"")="",1,0))+IF(X32="",0,IF(IFERROR(INDEX(Preise!$L$3:$L$53,MATCH(X32,Preise!$A$3:$A$53,0)),"")="",1,0))+IF(Z32="",0,IF(IFERROR(INDEX(Preise!$L$3:$L$53,MATCH(Z32,Preise!$A$3:$A$53,0)),"")="",1,0))+IF(IFERROR(INDEX(Preise!$L$3:$L$53,MATCH(D32,Preise!$A$3:$A$53,0)),"")="",1,0)+IF(IFERROR(INDEX(Preise!$L$3:$L$53,MATCH(F32,Preise!$A$3:$A$53,0)),"")="",1,0)+IF(H32="–",0,IF(IFERROR(INDEX(Preise!$L$3:$L$53,MATCH(H32,Preise!$A$3:$A$53,0)),"")="",1,0)) -> 2 | AC32: Wowhead-Route | AD32: https://ahledger.com/items/15086-wicked-leather-headband
A33: Ohne Wert: Reagenzien oder Entzauberungsmaterial ohne Preis zählen als 0, Spalte «Preise fehlen» zeigt wie viele.
A35: Material (Entzaubern) | B35: Bedarf VZ 1-300 | C35: Ertrag aus LW-Route | D35: Deckung | E35: Fehlmenge | F35: Überschuss | G35: Rechenpreis (s) | H35: Wert genutzter Eigenertrag (Gold) | I35: Kosten Fehlmenge (Gold) | J35: Wert Überschuss (Gold)
A36: Strange Dust | B36: =SUMIFS(Bedarf!$F$3:$F$85,Bedarf!$A$3:$A$85,"VZ",Bedarf!$E$3:$E$85,A36) -> 145 | C36: =SUMPRODUCT(($D$21:$D$32=A36)*$E$21:$E$32*$O$21:$O$32)+SUMPRODUCT(($F$21:$F$32=A36)*$G$21:$G$32*$O$21:$O$32)+SUMPRODUCT(($H$21:$H$32=A36)*$I$21:$I$32*$O$21:$O$32) -> 131.25 | D36: =IF(B36=0,"–",MIN(1,C36/B36)) -> 0.90517241 | E36: =MAX(0,B36-C36) -> 13.75 | F36: =MAX(0,C36-B36) -> 0 | G36: =IFERROR(INDEX(Preise!$L$3:$L$53,MATCH(A36,Preise!$A$3:$A$53,0)),"") -> 0.84 | H36: =IF(G36="","",MIN(B36,C36)*G36/100) -> 1.1025 | I36: =IF(G36="","",E36*G36/100) -> 0.1155 | J36: =IF(G36="","",F36*G36/100) -> 0
A37: Lesser Magic Essence | B37: =SUMIFS(Bedarf!$F$3:$F$85,Bedarf!$A$3:$A$85,"VZ",Bedarf!$E$3:$E$85,A37) -> 1 | C37: =SUMPRODUCT(($D$21:$D$32=A37)*$E$21:$E$32*$O$21:$O$32)+SUMPRODUCT(($F$21:$F$32=A37)*$G$21:$G$32*$O$21:$O$32)+SUMPRODUCT(($H$21:$H$32=A37)*$I$21:$I$32*$O$21:$O$32) -> 9 | D37: =IF(B37=0,"–",MIN(1,C37/B37)) -> 1 | E37: =MAX(0,B37-C37) -> 0 | F37: =MAX(0,C37-B37) -> 8 | G37: =IFERROR(INDEX(Preise!$L$3:$L$53,MATCH(A37,Preise!$A$3:$A$53,0)),"") -> 0.69 | H37: =IF(G37="","",MIN(B37,C37)*G37/100) -> 0.0069 | I37: =IF(G37="","",E37*G37/100) -> 0 | J37: =IF(G37="","",F37*G37/100) -> 0.0552
A38: Greater Magic Essence | B38: =SUMIFS(Bedarf!$F$3:$F$85,Bedarf!$A$3:$A$85,"VZ",Bedarf!$E$3:$E$85,A38) -> 12 | C38: =SUMPRODUCT(($D$21:$D$32=A38)*$E$21:$E$32*$O$21:$O$32)+SUMPRODUCT(($F$21:$F$32=A38)*$G$21:$G$32*$O$21:$O$32)+SUMPRODUCT(($H$21:$H$32=A38)*$I$21:$I$32*$O$21:$O$32) -> 6.6 | D38: =IF(B38=0,"–",MIN(1,C38/B38)) -> 0.55 | E38: =MAX(0,B38-C38) -> 5.4 | F38: =MAX(0,C38-B38) -> 0 | G38: =IFERROR(INDEX(Preise!$L$3:$L$53,MATCH(A38,Preise!$A$3:$A$53,0)),"") -> 1.96 | H38: =IF(G38="","",MIN(B38,C38)*G38/100) -> 0.12936 | I38: =IF(G38="","",E38*G38/100) -> 0.10584 | J38: =IF(G38="","",F38*G38/100) -> 0
A39: Lesser Astral Essence | B39: =SUMIFS(Bedarf!$F$3:$F$85,Bedarf!$A$3:$A$85,"VZ",Bedarf!$E$3:$E$85,A39) -> 25 | C39: =SUMPRODUCT(($D$21:$D$32=A39)*$E$21:$E$32*$O$21:$O$32)+SUMPRODUCT(($F$21:$F$32=A39)*$G$21:$G$32*$O$21:$O$32)+SUMPRODUCT(($H$21:$H$32=A39)*$I$21:$I$32*$O$21:$O$32) -> 4.5 | D39: =IF(B39=0,"–",MIN(1,C39/B39)) -> 0.18 | E39: =MAX(0,B39-C39) -> 20.5 | F39: =MAX(0,C39-B39) -> 0 | G39: =IFERROR(INDEX(Preise!$L$3:$L$53,MATCH(A39,Preise!$A$3:$A$53,0)),"") -> 6.04 | H39: =IF(G39="","",MIN(B39,C39)*G39/100) -> 0.2718 | I39: =IF(G39="","",E39*G39/100) -> 1.2382 | J39: =IF(G39="","",F39*G39/100) -> 0
A40: Small Glimmering Shard | B40: =SUMIFS(Bedarf!$F$3:$F$85,Bedarf!$A$3:$A$85,"VZ",Bedarf!$E$3:$E$85,A40) -> 0 | C40: =SUMPRODUCT(($D$21:$D$32=A40)*$E$21:$E$32*$O$21:$O$32)+SUMPRODUCT(($F$21:$F$32=A40)*$G$21:$G$32*$O$21:$O$32)+SUMPRODUCT(($H$21:$H$32=A40)*$I$21:$I$32*$O$21:$O$32) -> 1.48 | D40: =IF(B40=0,"–",MIN(1,C40/B40)) -> – | E40: =MAX(0,B40-C40) -> 0 | F40: =MAX(0,C40-B40) -> 1.48 | G40: =IFERROR(INDEX(Preise!$L$3:$L$53,MATCH(A40,Preise!$A$3:$A$53,0)),"") -> 3.66 | H40: =IF(G40="","",MIN(B40,C40)*G40/100) -> 0 | I40: =IF(G40="","",E40*G40/100) -> 0 | J40: =IF(G40="","",F40*G40/100) -> 0.054168
A41: Soul Dust | B41: =SUMIFS(Bedarf!$F$3:$F$85,Bedarf!$A$3:$A$85,"VZ",Bedarf!$E$3:$E$85,A41) -> 122 | C41: =SUMPRODUCT(($D$21:$D$32=A41)*$E$21:$E$32*$O$21:$O$32)+SUMPRODUCT(($F$21:$F$32=A41)*$G$21:$G$32*$O$21:$O$32)+SUMPRODUCT(($H$21:$H$32=A41)*$I$21:$I$32*$O$21:$O$32) -> 26.25 | D41: =IF(B41=0,"–",MIN(1,C41/B41)) -> 0.21516393 | E41: =MAX(0,B41-C41) -> 95.75 | F41: =MAX(0,C41-B41) -> 0 | G41: =IFERROR(INDEX(Preise!$L$3:$L$53,MATCH(A41,Preise!$A$3:$A$53,0)),"") -> 7.21 | H41: =IF(G41="","",MIN(B41,C41)*G41/100) -> 1.892625 | I41: =IF(G41="","",E41*G41/100) -> 6.903575 | J41: =IF(G41="","",F41*G41/100) -> 0
A42: Greater Astral Essence | B42: =SUMIFS(Bedarf!$F$3:$F$85,Bedarf!$A$3:$A$85,"VZ",Bedarf!$E$3:$E$85,A42) -> 2 | C42: =SUMPRODUCT(($D$21:$D$32=A42)*$E$21:$E$32*$O$21:$O$32)+SUMPRODUCT(($F$21:$F$32=A42)*$G$21:$G$32*$O$21:$O$32)+SUMPRODUCT(($H$21:$H$32=A42)*$I$21:$I$32*$O$21:$O$32) -> 0 | D42: =IF(B42=0,"–",MIN(1,C42/B42)) -> 0 | E42: =MAX(0,B42-C42) -> 2 | F42: =MAX(0,C42-B42) -> 0 | G42: =IFERROR(INDEX(Preise!$L$3:$L$53,MATCH(A42,Preise!$A$3:$A$53,0)),"") -> 28.54 | H42: =IF(G42="","",MIN(B42,C42)*G42/100) -> 0 | I42: =IF(G42="","",E42*G42/100) -> 0.5708 | J42: =IF(G42="","",F42*G42/100) -> 0
A43: Large Glimmering Shard | B43: =SUMIFS(Bedarf!$F$3:$F$85,Bedarf!$A$3:$A$85,"VZ",Bedarf!$E$3:$E$85,A43) -> 0 | C43: =SUMPRODUCT(($D$21:$D$32=A43)*$E$21:$E$32*$O$21:$O$32)+SUMPRODUCT(($F$21:$F$32=A43)*$G$21:$G$32*$O$21:$O$32)+SUMPRODUCT(($H$21:$H$32=A43)*$I$21:$I$32*$O$21:$O$32) -> 0 | D43: =IF(B43=0,"–",MIN(1,C43/B43)) -> – | E43: =MAX(0,B43-C43) -> 0 | F43: =MAX(0,C43-B43) -> 0 | G43: =IFERROR(INDEX(Preise!$L$3:$L$53,MATCH(A43,Preise!$A$3:$A$53,0)),"") -> 78.99 | H43: =IF(G43="","",MIN(B43,C43)*G43/100) -> 0 | I43: =IF(G43="","",E43*G43/100) -> 0 | J43: =IF(G43="","",F43*G43/100) -> 0
A44: Lesser Mystic Essence | B44: =SUMIFS(Bedarf!$F$3:$F$85,Bedarf!$A$3:$A$85,"VZ",Bedarf!$E$3:$E$85,A44) -> 0 | C44: =SUMPRODUCT(($D$21:$D$32=A44)*$E$21:$E$32*$O$21:$O$32)+SUMPRODUCT(($F$21:$F$32=A44)*$G$21:$G$32*$O$21:$O$32)+SUMPRODUCT(($H$21:$H$32=A44)*$I$21:$I$32*$O$21:$O$32) -> 3 | D44: =IF(B44=0,"–",MIN(1,C44/B44)) -> – | E44: =MAX(0,B44-C44) -> 0 | F44: =MAX(0,C44-B44) -> 3 | G44: =IFERROR(INDEX(Preise!$L$3:$L$53,MATCH(A44,Preise!$A$3:$A$53,0)),"") -> 15.96 | H44: =IF(G44="","",MIN(B44,C44)*G44/100) -> 0 | I44: =IF(G44="","",E44*G44/100) -> 0 | J44: =IF(G44="","",F44*G44/100) -> 0.4788
A45: Small Glowing Shard | B45: =SUMIFS(Bedarf!$F$3:$F$85,Bedarf!$A$3:$A$85,"VZ",Bedarf!$E$3:$E$85,A45) -> 0 | C45: =SUMPRODUCT(($D$21:$D$32=A45)*$E$21:$E$32*$O$21:$O$32)+SUMPRODUCT(($F$21:$F$32=A45)*$G$21:$G$32*$O$21:$O$32)+SUMPRODUCT(($H$21:$H$32=A45)*$I$21:$I$32*$O$21:$O$32) -> 0.4 | D45: =IF(B45=0,"–",MIN(1,C45/B45)) -> – | E45: =MAX(0,B45-C45) -> 0 | F45: =MAX(0,C45-B45) -> 0.4 | G45: =IFERROR(INDEX(Preise!$L$3:$L$53,MATCH(A45,Preise!$A$3:$A$53,0)),"") -> 75.99 | H45: =IF(G45="","",MIN(B45,C45)*G45/100) -> 0 | I45: =IF(G45="","",E45*G45/100) -> 0 | J45: =IF(G45="","",F45*G45/100) -> 0.30396
A46: Vision Dust | B46: =SUMIFS(Bedarf!$F$3:$F$85,Bedarf!$A$3:$A$85,"VZ",Bedarf!$E$3:$E$85,A46) -> 237 | C46: =SUMPRODUCT(($D$21:$D$32=A46)*$E$21:$E$32*$O$21:$O$32)+SUMPRODUCT(($F$21:$F$32=A46)*$G$21:$G$32*$O$21:$O$32)+SUMPRODUCT(($H$21:$H$32=A46)*$I$21:$I$32*$O$21:$O$32) -> 40.125 | D46: =IF(B46=0,"–",MIN(1,C46/B46)) -> 0.1693038 | E46: =MAX(0,B46-C46) -> 196.875 | F46: =MAX(0,C46-B46) -> 0 | G46: =IFERROR(INDEX(Preise!$L$3:$L$53,MATCH(A46,Preise!$A$3:$A$53,0)),"") -> 19.71 | H46: =IF(G46="","",MIN(B46,C46)*G46/100) -> 7.9086375 | I46: =IF(G46="","",E46*G46/100) -> 38.804063 | J46: =IF(G46="","",F46*G46/100) -> 0
A47: Greater Mystic Essence | B47: =SUMIFS(Bedarf!$F$3:$F$85,Bedarf!$A$3:$A$85,"VZ",Bedarf!$E$3:$E$85,A47) -> 2 | C47: =SUMPRODUCT(($D$21:$D$32=A47)*$E$21:$E$32*$O$21:$O$32)+SUMPRODUCT(($F$21:$F$32=A47)*$G$21:$G$32*$O$21:$O$32)+SUMPRODUCT(($H$21:$H$32=A47)*$I$21:$I$32*$O$21:$O$32) -> 3 | D47: =IF(B47=0,"–",MIN(1,C47/B47)) -> 1 | E47: =MAX(0,B47-C47) -> 0 | F47: =MAX(0,C47-B47) -> 1 | G47: =IFERROR(INDEX(Preise!$L$3:$L$53,MATCH(A47,Preise!$A$3:$A$53,0)),"") -> 44 | H47: =IF(G47="","",MIN(B47,C47)*G47/100) -> 0.88 | I47: =IF(G47="","",E47*G47/100) -> 0 | J47: =IF(G47="","",F47*G47/100) -> 0.44
... A58: Large Brilliant Shard | B58: =SUMIFS(Bedarf!$F$3:$F$85,Bedarf!$A$3:$A$85,"VZ",Bedarf!$E$3:$E$85,A58) -> 2 | C58: =SUMPRODUCT(($D$21:$D$32=A58)*$E$21:$E$32*$O$21:$O$32)+SUMPRODUCT(($F$21:$F$32=A58)*$G$21:$G$32*$O$21:$O$32)+SUMPRODUCT(($H$21:$H$32=A58)*$I$21:$I$32*$O$21:$O$32) -> 0.4 | D58: =IF(B58=0,"–",MIN(1,C58/B58)) -> 0.2 | E58: =MAX(0,B58-C58) -> 1.6 | F58: =MAX(0,C58-B58) -> 0 | G58: =IFERROR(INDEX(Preise!$L$3:$L$53,MATCH(A58,Preise!$A$3:$A$53,0)),"") | H58: =IF(G58="","",MIN(B58,C58)*G58/100) | I58: =IF(G58="","",E58*G58/100) | J58: =IF(G58="","",F58*G58/100)
A59: Summe | H59: =SUM(H36:H58) -> 201.58456 | I59: =SUM(I36:I58) -> 600.11424 | J59: =SUM(J36:J58) -> 84.04404
A60: Fehlmengen ohne Preis (z.B. Large Brilliant Shard im Markt NH) fehlen in der Summe; siehe Spalte Rechenpreis.

Sheet Produkte
A1: Was sich verkaufen lässt: Margen pro Herstellung laut AHledger (Forever-Beta, nach 5 % AH-Gebühr), Werte in Silber
A2: Beta-Werte, Stand je Seite 27.09.–12.10.; mehrere Seiten widersprechen sich, siehe Hinweis. Keine Prognose für den Launch.
A3: Produkt | B3: Beruf | C3: AH-fähig | D3: Händlerpreis Forever (s) | E3: Marge NH (s) | F3: Rendite NH | G3: Marge PH (s) | H3: Rendite PH | I3: Absatz/Tag | J3: Hinweis | K3: Quelle
A4: Lesser Magic Wand | B4: VZ | C4: ja (BoE) | D4: 1.1 | E4: -0.7 | F4: -0.27 | G4: 0.18 | H4: 0.1 | I4: ~410 (PH) | J4: Händlerpreis seit Build 08.10. (Dev Notes) | K4: https://ahledger.com/wow-forever/recipes/14293-lesser-magic-wand
A5: Greater Magic Wand | B5: VZ | C5: ja (BoE) | D5: 2 | E5: -1.7 | F5: -0.37 | G5: 0.1 | H5: 0.04 | I5: ~460 (PH) | K5: https://ahledger.com/wow-forever/recipes/14807-greater-magic-wand
A6: Lesser Mystic Wand | B6: VZ | C6: ja (BoE) | D6: 4.5 | E6: -86.86 | F6: -0.7 | I6: ~46 (PH) | J6: PH: Star Wood ohne Preis | K6: https://ahledger.com/wow-forever/recipes/14809-lesser-mystic-wand
A7: Greater Mystic Wand | B7: VZ | C7: ja (BoE) | D7: 6 | E7: -59.17 | F7: -0.47 | G7: -47.98 | H7: -0.5 | I7: ~13 (PH) | K7: https://ahledger.com/wow-forever/recipes/14810-greater-mystic-wand
A8: Novice's Practice Wand | B8: VZ | C8: ja (BoE) | D8: 0.05 | E8: 0.11 | F8: 0.13 | G8: -0.23 | H8: -0.19 | I8: ~120 (NH) | K8: https://ahledger.com/wow-forever/recipes/1245321-novices-practice-wand
A9: Twisted Nether Wand | B9: VZ | C9: ja (BoE) | D9: 10 | I9: – | J9: kein AH-Preis; Reagenzien NH 4g 08s, PH 4g 52s | K9: https://ahledger.com/wow-forever/recipes/1248461-twisted-nether-wand
A10: Dreambough Wand | B10: VZ | C10: ja (BoE) | D10: 15 | I10: – | J10: kein AH-Preis; Reagenzien NH 6g 30s, PH 7g 72s | K10: https://ahledger.com/wow-forever/recipes/1248509-dreambough-wand
A11: Lesser Eternal Wand | B11: VZ | C11: ja (BoE) | D11: 20 | I11: – | J11: kein AH-Preis; Reagenzien NH 3g 48s, PH 1g 74s | K11: https://ahledger.com/wow-forever/recipes/1248505-lesser-eternal-wand
A12: Greater Eternal Wand | B12: VZ | C12: ja (BoE) | D12: 25 | I12: – | J12: kein AH-Preis; Reagenzien ohne Preis | K12: https://ahledger.com/wow-forever/recipes/1248515-greater-eternal-wand
A13: Brilliant Wand | B13: VZ | C13: nein (BoP) | I13: – | J13: nicht verkaufbar; Formel 180 Merchant's Favor | K13: https://www.wowhead.com/forever/item=249385/brilliant-wand
A14: Minor Wizard Oil | B14: VZ | C14: ja | D14: 1 | E14: 7.37 | F14: 1.24 | G14: 3.51 | H14: 0.7 | I14: ~220 (PH) | J14: Crafting-Seite zeigt für PH −2s 86c (Widerspruch) | K14: https://ahledger.com/wow-forever/recipes/25124-minor-wizard-oil
A15: Minor Mana Oil | B15: VZ | C15: ja | D15: 10 | E15: -6.26 | F15: -0.35 | G15: 9.8 | H15: 0.58 | I15: ~190–200 (PH) | J15: Crafting-Seite zeigt für PH −7s 84c (Widerspruch); Händlerpreis laut metaforge | K15: https://ahledger.com/wow-forever/recipes/25125-minor-mana-oil
A16: Lesser Wizard Oil | B16: VZ | C16: ja | E16: -31.96 | F16: -0.57 | G16: -17.34 | H16: -0.48 | I16: ~120 (PH) | K16: https://ahledger.com/wow-forever/recipes/25126-lesser-wizard-oil
A17: Lesser Mana Oil | B17: VZ | C17: ja | I17: – | J17: kein AH-Preis; Reagenzien NH 1g 84s, PH 2g 08s | K17: https://ahledger.com/wow-forever/recipes/25127-lesser-mana-oil
A18: Wizard Oil | B18: VZ | C18: ja | I18: – | J18: kein AH-Preis; Reagenzien NH 34g 05s (Illusion Dust dünn) | K18: https://ahledger.com/wow-forever/recipes/25128-wizard-oil
A19: Brilliant Wizard Oil | B19: VZ | C19: ja | I19: – | J19: kein AH-Preis; Formel BoP über Zandalar Tribe (Classic-Daten) | K19: https://ahledger.com/wow-forever/recipes/25129-brilliant-wizard-oil
A20: Brilliant Mana Oil | B20: VZ | C20: ja | D20: 10 | I20: – | J20: kein AH-Preis; Formel BoP, Zandalar Tribe Friendly (metaforge) | K20: https://ahledger.com/wow-forever/recipes/25130-brilliant-mana-oil
A21: Enchanted Lute | B21: VZ | C21: ja; platzieren nur mit VZ-Fertigkeit | E21: -1.56 | F21: -0.52 | G21: 6.52 | H21: 2.19 | I21: ~15 (PH) | J21: Crafting-Seite zeigt für PH −27c (Widerspruch) | K21: https://ahledger.com/wow-forever/recipes/1230643-enchanted-lute
A22: Arcane Salvager | B22: VZ | C22: ja; platzieren erst ab VZ 140 | E22: 84.49 | F22: 0.42 | G22: 44.13 | H22: 0.16 | I22: ~8 (PH) | J22: «effizienter entzaubern» ohne Zahl; Spielertest: kein Effekt | K22: https://ahledger.com/wow-forever/recipes/1263056-arcane-salvager
A23: Runed Copper/Silver/Golden/Truesilver/Arcanite Rod | B23: VZ | C23: nein (BoP) | I23: – | J23: nicht verkaufbar | K23: https://www.wowhead.com/forever/item=6218/runed-copper-rod
A24: Glimmering Staff, Soulstaff, Orb of Mystic Insight, Radiant Staff | B24: VZ | C24: nein (BoP) | I24: – | J24: nicht verkaufbar | K24: https://www.wowhead.com/forever/item=249392/glimmering-staff
A25: Verzauberung als Auftrag | B25: VZ | C25: nur Handelsfenster | I25: – | J25: kein Preis gefunden; kein Vellum in Forever (Spieleraussagen, Stand 08.10.) | K25: https://us.forums.blizzard.com/en/wow/t/wow-forever-enchanting-vellums-are-needed-%E2%80%94-the-current-system-isnt-working/2375983
A26: Mystic Medium Armor Kit | B26: LW | C26: ja | E26: 9.11 | F26: 0.62 | G26: 8.32 | H26: 0.78 | I26: ~60 (NH) | K26: https://ahledger.com/wow-forever/recipes/1255124-mystic-medium-armor-kit
A27: Medium Armor Kit | B27: LW | C27: ja | E27: 2.61 | F27: 0.33 | G27: -0.54 | H27: -0.06 | I27: ~190 (NH), ~250 (PH) | K27: https://ahledger.com/wow-forever/recipes/2165-medium-armor-kit
A28: Forceful Heavy Armor Kit | B28: LW | C28: ja | E28: 29.23 | F28: 0.46 | G28: -18.87 | H28: -0.3 | I28: – | K28: https://ahledger.com/wow-forever/recipes/1255095-forceful-heavy-armor-kit
A29: Forceful Medium Armor Kit | B29: LW | C29: ja | E29: -6.5 | F29: -0.2 | G29: -12.67 | H29: -0.32 | I29: ~130 (Normal Alliance) | K29: https://ahledger.com/wow-forever/recipes/1255123-forceful-medium-armor-kit
A30: Mystic Heavy Armor Kit | B30: LW | C30: ja | E30: -26.38 | F30: -0.4 | G30: -12.51 | H30: -0.23 | I30: – | K30: https://ahledger.com/wow-forever/recipes/1255096-mystic-heavy-armor-kit
A31: Light Armor Kit | B31: LW | C31: ja | E31: -0.48 | F31: -0.77 | G31: -1.04 | H31: -0.88 | I31: ~1'300 (NH) | K31: https://ahledger.com/wow-forever/recipes/2152-light-armor-kit
A32: Heavy Armor Kit | B32: LW | C32: ja | E32: -23.78 | F32: -0.38 | G32: -34.45 | H32: -0.61 | I32: ~350 (PH) | K32: https://ahledger.com/wow-forever/recipes/3780-heavy-armor-kit
A33: Thick Armor Kit | B33: LW | C33: ja | E33: -59.29 | F33: -0.3 | G33: 54.35 | H33: 0.14 | I33: ~76 (PH) | J33: Crafting-Seite zeigt für PH +94s 79c | K33: https://ahledger.com/wow-forever/recipes/10487-thick-armor-kit
A34: Cured Light Hide | B34: LW | C34: ja | E34: 2.21 | F34: 1.21 | G34: -0.21 | H34: -0.17 | I34: – | K34: https://ahledger.com/wow-forever/recipes/3816-cured-light-hide
A35: Cured Medium Hide | B35: LW | C35: ja | E35: 2.05 | F35: 0.25 | G35: 1.89 | H35: 0.2 | I35: ~340 (PH) | K35: https://ahledger.com/wow-forever/recipes/3817-cured-medium-hide
A36: Cured Heavy Hide | B36: LW | C36: ja | E36: -8.83 | F36: -0.23 | G36: -6.22 | H36: -0.19 | I36: ~490 (PvP Alliance) | K36: https://ahledger.com/wow-forever/recipes/3818-cured-heavy-hide
A37: Heavy Leather | B37: LW | C37: ja | E37: 0.03 | F37: 0 | G37: -1.95 | H37: -0.16 | I37: ~1'700 (NH) | K37: https://ahledger.com/wow-forever/recipes/20649-heavy-leather
A38: Thick Leather | B38: LW | C38: ja | E38: -34.84 | F38: -0.48 | G38: 8.1 | H38: 0.12 | I38: ~1'300 (PH) | K38: https://ahledger.com/wow-forever/recipes/20650-thick-leather
A39: Light Leather Reagent Bag | B39: LW | C39: ja | E39: 2.77 | F39: 0.36 | G39: 86.63 | H39: 10.35 | I39: ~66 (PH) | J39: PH-Wert beruht auf einer 1g-Listung; Itemseite PH-Median 15s | K39: https://ahledger.com/wow-forever/recipes/1302604-light-leather-reagent-bag
A40: Kodo Hide Bag | B40: LW | C40: ja | E40: 0.31 | F40: 0.09 | G40: -0.48 | H40: -0.09 | I40: ~71 (NH) | K40: https://ahledger.com/wow-forever/recipes/5244-kodo-hide-bag
A41: Heavy Quiver | B41: LW | C41: ja | E41: -18.66 | F41: -0.24 | G41: 85.68 | H41: 1.13 | I41: ~47 (PH) | K41: https://ahledger.com/wow-forever/recipes/9193-heavy-quiver
A42: Barbaric Bracers | B42: LW | C42: ja | E42: 605.55 | F42: 1.76 | G42: 1104 | H42: 4.44 | I42: ~68 (PH) | J42: Musterquelle nicht geprüft | K42: https://ahledger.com/wow-forever/recipes/23399-barbaric-bracers
A43: Red Whelp Gloves | B43: LW | C43: ja | E43: 897.94 | F43: 17.25 | G43: 151.85 | H43: 2.8 | I43: ~5 (NH) | J43: NH-Wert beruht auf einer 10g-Listung; Musterquelle nicht geprüft | K43: https://ahledger.com/wow-forever/recipes/9072-red-whelp-gloves
A44: Green Whelp Armor | B44: LW | C44: ja | E44: 1078 | F44: 0.83 | G44: -428.07 | H44: -0.32 | I44: ~1 (NH), ~15 (PH) | J44: Musterquelle nicht geprüft | K44: https://ahledger.com/wow-forever/recipes/9197-green-whelp-armor
A45: Herbalist's Gloves | B45: LW | C45: ja | G45: 422.01 | I45: ~15 (PH) | J45: nur Crafting-Seite PH; Musterquelle nicht geprüft | K45: https://ahledger.com/crafting?market=forever/pvp/horde/us
A46: Dusky Belt | B46: LW | C46: ja | G46: 377.25 | I46: ~10 (PH) | J46: nur Crafting-Seite PH; Musterquelle nicht geprüft | K46: https://ahledger.com/crafting?market=forever/pvp/horde/us
A47: Azure Gustwoven Spaulders | B47: LW | C47: ja | G47: 2643 | I47: ~2 (PH) | J47: nur Crafting-Seite PH; Musterquelle nicht geprüft | K47: https://ahledger.com/crafting?market=forever/pvp/horde/us
A48: Green Leather Armor | B48: LW | C48: ja | G48: 140.51 | I48: ~5 (PH) | J48: nur Crafting-Seite PH; Musterquelle nicht geprüft | K48: https://ahledger.com/crafting?market=forever/pvp/horde/us
A49: White Leather Jerkin | B49: LW | C49: ja | E49: 8.36 | F49: 1.69 | G49: 89.03 | H49: 14.91 | I49: ~21 (PH) | J49: PH-Wert beruht auf einer 1g-Listung | K49: https://ahledger.com/wow-forever/recipes/2163-white-leather-jerkin

Sheet Quellen
A1: Quellen
A2: Wofür | B2: Link
A3: Mengen: Wowhead, Leatherworking Leveling 1-300 (WoW Classic), Stand 02.08.2026, Patch 1.15.8 | B3: https://www.wowhead.com/classic/guide/leatherworking-leveling-1-300-wow-classic
A4: Mengen: Wowhead, Enchanting Leveling 1-300 (WoW Classic), Stand 30.09.2025 | B4: https://www.wowhead.com/classic/guide/enchanting-leveling-1-300-wow-classic
A5: Preise und Margen: AHledger (Forever-Beta, Spieler-Scans), Startseite | B5: https://ahledger.com/
A6: AHledger Markt Normal Horde US | B6: https://ahledger.com/markets/forever/normal/horde/us
A7: AHledger Markt PvP Horde US | B7: https://ahledger.com/markets/forever/pvp/horde/us
A8: AHledger Crafting PvP Horde US | B8: https://ahledger.com/crafting?market=forever/pvp/horde/us
A9: AHledger Verzauberungen (Materialkosten, nur PvP Alliance) | B9: https://ahledger.com/wow-forever/enchants
A10: Entzauberungstabelle Forever: wow-professions | B10: https://www.wow-professions.com/forever/disenchanting-guide
A11: Forever-Routen zum Vergleich: wow-professions Lederverarbeitung | B11: https://www.wow-professions.com/forever/leatherworking-leveling-guide
A12: Forever-Routen zum Vergleich: wow-professions Verzauberkunst | B12: https://www.wow-professions.com/forever/enchanting-leveling-guide
A13: Lehrer Verzauberkunst Forever (Annora, Uldaman) | B13: https://www.wow-professions.com/forever/enchanting-trainers
... A23: Garn-Händlerpreise: warcraft.wiki.gg | B23: https://warcraft.wiki.gg/wiki/Thread
A25: Einzelne Preis-, Rezept- und Item-Seiten stehen in den Blättern Preise, Kreislauf und Produkte jeweils in der Spalte Quelle.
